{"YUKARIYABANLI":["YUKARIYABANLI"],"ŞAĞILUŞAĞI":["KUŞÇU","ŞAĞILUŞAĞI"],"MEŞELİ":["MEŞELİ"],"BOSTANCIK":["BAHÇELER","BOSTANCIK","BULGURLU"],"MEHMETAKİF":["ADNAN KAHVECİ","ATATÜRK","AYVAZPINARI","CAMİ","DİVRİĞİ","EKŞİ","EĞEMEN","FETİ GEMUHLUOĞLU","HUZUR","HÜSEYİN AVNİ PAŞA","KARABAY","KARACA","KARŞIYAKA","KOZLUK","MEHMET AKİF1","MEHMET AKİF10","MEHMET AKİF11","MEHMET AKİF12","MEHMET AKİF13","MEHMET AKİF14","MEHMET AKİF15","MEHMET AKİF16","MEHMET AKİF17","MEHMET AKİF18","MEHMET AKİF19","MEHMET AKİF2","MEHMET AKİF20","MEHMET AKİF21","MEHMET AKİF22","MEHMET AKİF23","MEHMET AKİF24","MEHMET AKİF25","MEHMET AKİF26","MEHMET AKİF27","MEHMET AKİF28","MEHMET AKİF29","MEHMET AKİF3","MEHMET AKİF30","MEHMET AKİF31","MEHMET AKİF32","MEHMET AKİF33","MEHMET AKİF34","MEHMET AKİF35","MEHMET AKİF36","MEHMET AKİF37","MEHMET AKİF38","MEHMET AKİF39","MEHMET AKİF40","MEHMET AKİF41","MEHMET AKİF45","MEHMET AKİF5","MEHMET AKİF6","MEHMET AKİF7","MEHMET AKİF8","MEHMET AKİF9","MEHMET KEREM AYDINLAR","OSMANPAŞA","SAİME HATUN","SEYRANTEPE","SULUCA","SÖNMEZ","TARAKÇI","TUNCAY KAVUNCU PAŞA","YUSUF KAMİL PAŞA","YUSUF KAMİL PAŞA CAD. 114 NOLU","YUSUF KAMİL PAŞA CAD. 115 NOLU","YUSUF KAMİL PAŞA CAD. 116 NOLU","ÇOBAN","ÇOBANLI","ÖMER BABA","ŞEMSİ BELLİ"],"BERENGE":["BERENGE1","CEVAT PAŞA","EMİROĞLU","HACI ŞERİF AĞA","HAMİ AYDINLAR","HAMİ AYDINLAR 1","MÜFTÜLER","MÜFTÜLER 1","MÜFTÜLER 2","NAMIK GEDİK","NEVZAT SEZER","ZEHRA BİLİR","ÇARŞI","İPEKÇİ","İPEKÇİ 1"],"CÖMERTLİ":["CÖMERTLER","EFELER","EFELER1","ERZEN","ERZEN1"],"ÇARŞI":["FEVZİ ÇAKMAK","HACI ŞERİF AĞA","HAMAM","MENEKŞE","NAMIK GEDİK","TAŞPINAR","TOPÇULAR","ÇARŞI1","ÇARŞI10","ÇARŞI2","ÇARŞI3","ÇARŞI4","ÇARŞI5","ÇARŞI6","ÇARŞI7","ÇARŞI8","ÇARŞI9"],"AŞAĞIÇÖRENGE":["EMİROĞLU","FADILLIOĞLU","FADILLIOĞLU 1","FINDIKLI ÇEŞME","MALATYA","SAİTOĞLU","TAŞKÖPRÜ","TAŞKÖPRÜ 1","TAŞKÖPRÜ 2"],"AŞAĞIULUPINAR":["AŞAĞIULUPINAR DİVRİĞİ","DEĞİRMEN","HARMANLI","ZAİMOĞLU"],"AŞAĞIYENİCE":["AKILLIOĞLU","DABAKÇILAR","NAİM CÖMERTLİOĞLU","YENİCE"],"KÖSEOĞLU":["ATATÜRK","AYDINLAR","GAZOZCULAR","HACI YAHYA","HÜKÜMET","KASAPLAR SIRASI","KÖSEOĞLU1","KÖSEOĞLU2","MENEKŞE","NAMIK GEDİK","TOPÇULAR","ÇARŞI","ÇAYLI"],"ÇOBANLI":["ENGİN","SÜTPINAR","ÇOBANLI","ÇOBANLI1","ŞAKİR PAŞA"],"GÖZ":["GÖZ"],"HEZENEK":["BEDRETTİN TOLGA","BEŞDUTLAR","HEZENEK1","HEZENEK2","HEZENEK3","KAYNARCA","KIRKDUTLAR","MALATYA_1","MEHMET ALİ AYDINLAR"],"HOCAALİ":["BAŞESKİ","CUMHURİYET","CİĞERCİ","EMİROĞLU","HOCAALİ1","HOCAALİ2","HOCALİ1","TAŞKÖPRÜ","ZEHRA BİLİR"],"OSMANPAŞA":["AKYOL","ARKBAŞI","CAFERPAŞA","KESİKBAŞ"],"SEKİZSU":["HACI BAYRAMLI","SANTRAL","ÇOBANKAYA"],"ŞIHLAR":["KADIOĞLU","KÜME","KÜME 1","SOFULAR","ŞABANAĞA"],"YENİ":["ATATÜRK","BOLPINAR","BOLPINAR1","DEMİRCİLER","DEMİRCİLER 1","DİVRİĞİ","EMİROĞLU","EMİROĞLU 1","HASTANE","KARAYOLLARI","KAZIM KARABEKİR","MİMAR SİNAN","SANAYİ","SANAYİ 1","SANAYİ 2","SİNANLI","SİNEMA","YENİ","YENİ YOL 21","YENİ2","ZEKAYİ BİNGÜLER","ZİYA GÖKALP","ÇAMLI","ÇAMLI 1","ÇARŞI","ÇERKEZ","ÖZGÜR","ÖZGÜR 1","İNÖNÜ"],"YUKARIÇÖRENGE":["ARİFİN VİRAJI","DABAZPINARI","KARANFİL","MALATYA","MÜDERRİSOĞLU","SARAÇBAŞI","TAHTIKLI","YUKARIÇÖRENGE1","YUKARIÇÖRENGE2","YUKARIÇÖRENGE3","YUKARIÇÖRENGE5","ÇİFT MEZAR"],"YUKARIULUPINAR":["GÖZELİ","HASLIK","ODAPINAR","YUKARIULUPINAR DİVRİĞİ"],"YUKARIYENİCE":["BALİ BEYLER","DERBEDER","MEHMET ALİ AYDINLAR","MÖHTEROĞLU","NAİM CÖMERTLİOĞLU","OĞUZLU","ŞAİR FEHMİ GÜR","ŞEKERCİ"],"ZÖHRAP":["BADEMLİ","OCAKLI","OCAKLI1","OKUL","TEPE"],"GÜNYÜZÜ":["ORTAEVLER","PALANGA","ÇİFTLİK"],"KAYAKESEN":["KAYAKESEN","KOZER","YAYLA EVLERİ"],"PİRALİ":["HARAÇ","MEHMET UŞAĞI","PİRALİ"],"ULAÇLI":["ULAÇLI"],"SERGE":["MEYDAN"],"AKTAŞ":["DUVANLI","DİŞDERİK GEÇİTLİ","MISALI","SARAYLI"],"BUDAK":["BUDAK"],"SELAMLI":["SELAMLI"],"TAŞDİBEK":["TAŞDİBEK"],"KAYNAK":["KAYNAK","LEVENGE"],"ÇAYBAŞI":["ÇAYBAŞI"],"ONAR":["KAYALISU","ONAR","ONAR1","ONAR2","TUTAĞACI"],"SİNİKLİ":["BALLICA","SİNİKLİ","UŞAĞI","YOLUKLU","YUKARI SİNİKLİ"],"YEŞİLYAYLA":["MAHMUDİ DERESİ","YEŞİLYAYLA","YEŞİLYAYLA1"],"KAZANÇ":["KAZANÇ","ROTOP"],"DEREGEZEN":["DEREGEZEN"],"TARHAN":["ALANLI","TARHAN","YILDIZLAR"],"ESİKLİ":["ESİKLİ","TAŞDELEN","ÜÇTEPE"],"TAŞDELEN":["TAŞDELEN"],"ORMANSIRTI":["ORMANSIRTI","ORMANSIRTI 1","İNDERESİ"],"BOĞAZLI":["BOĞAZLI"],"GEBELİ":["GEBELİ","ŞEREK"],"DÜZCE":["DÜZCE"],"PACALI":["PACALI"],"ALIÇLI":["ALIÇLI"],"KORU":["KORU","PROF. DR. HAMDİ SUAT AKNAR","ÇAY","ÇİMEN"],"SUGEÇTİ":["ALHUT","KALIN HARMAN","YANIKLAR"],"YAYLACIK":["YAYLACIK"],"SİPAHİUŞAĞI":["SİPAHİUŞAĞI"],"ÇİĞNİR":["YUMRUTAŞ","ÇİĞNİR"],"SUCEYİN":["DİKİLİTAŞ","HAMZA","KALECİK","SUCEYİN","SUCEYİN1","TAŞKÖPRÜ_1","VİJNA","YAMANGİL","İSUYURT"],"EĞNİR":["BEYPINAR","EĞNİR","TANISA"],"YAZILI":["YAZILI"],"GÖZELİ":["BARDIBAŞ","GÖZELİ"],"KONDUCAK":["AĞCEBENK","KONDUCAK","SARAY","SELİMLER"],"KILIÇLI":["BEYGİLLİ","HACIUŞAĞI","KEBİRUŞAĞI","KILIÇLI"],"ÇAKIRSU":["ÇAKIRSU","ÇİFTLİK_1"],"ÇİMEN":["BALLICA_1","ÇİMEN"],"ESKİARAPGİR":["BOSTANPINARI","ESKİARAPGİR"]}