{"KARAGÖL":["294.","42.","43.","44.","45.","46.","47.","48.","49.","50.","52.","53.","ADALET","AKASYA","ALGI","ALİ RIZA ARDAHANİ","ALİ RIZA EFENDİ","ANI","ARDIÇ","ASKERİYE","ASRIN","ASRİ","AŞIK SÜMMANİ","BAHAR","BAYINDIR","BAYRAK","BEYAZ BEY","BEYAZGÜL","BULUT","BİLGİ","BİLİM","BİRLİK","DAMLA","DEMET","DEVA","DUA","DUMAN","DİLEK","EBRULİ","ERLER","ESNAFLAR","EĞEMENLİK","GENÇLİK","HALİT PAŞA","HAMAM","HASRET","HAYAT","HAZAR","HERCAİ","IHLAMUR","IRMAK","KAFKAS","KALEM","KAMELYA","KAR","KARACA","KARBEYAZ","KARDEŞLİK","KARLI","KARTOPU","KAZIM KARABEKİR","KAZIM MOĞAN","KAŞ","KOCA MUSTAFA PAŞA","KONGRE","KURA","LALE1","LEVENT","LEYLAK","LEYLEK","MAREŞAL FEVZİ ÇAKMAK","MARTI","MERASİM","MESCİT","MEVLANA1","MEVSİM","MEYDAN","MİLLİ","NEHİR","NURİYE KÖKSOY","OKULLAR","ORD. PROF. DR. FAZIL ERDOĞAN","ORKİDE","OZANLAR","PAPATYA","PARK","PETEK","PETROL","RECAİ KÖKSOY","RECAİ KÖKSOY1","RIFKİYE KAĞAN","RÜYA","SABAH","SALİH AKTÜRK","SAĞLAM","SAĞLIK","SEHER","SERPME","SEVGİ","SPOR","SÖĞÜT","SÜLEYMAN ŞAH","TAKIM","TEKEL","TEKEL 75. YIL","TEMA","TERMİNAL","TOMURCUK","TİMSAL","UZUN","VATAN","VEDA","VEFA","VUSLAT","YARGI","YAĞMUR","YILDIZLI","YOKUŞ","YURT","ZAFER","ZAKKUM","ZÜBEYDE HANIM","ZÜMRÜT","ZİRAAT","ÇEVRE YOLU","ÇİLE","ÇİLEK","ÇİM","ÖZKAN","ÖZLEM","ÜSTÜN","İKLİM","İLİM","İNCİR","İSKAN","İSTEK","ŞAFAK","ŞEFİK CAN","ŞEHRİN","ŞEHİT ER İNAN AKÇAM","ŞEHİT HATİCE HANIM","ŞEHİT POLİS TUNCAY POLAT","ŞEHİT TÜRKMEN TEKİN","ŞÖLEN"],"KAPTANPAŞA":["130.","131.","132.","133.","183.","184.","185.","51.","54.","55.","56.","57","58.","62.","ADLİYE","ALİ RIZA ARDAHANİ","ASALET","ASYA","ATATÜRK","AYDINLIK1","AŞIK NİDAİ","AŞIK SÜMMANİ","AŞIK ZÜLALI","AŞIK ZÜLALI1","AŞIK ŞENLİK","BONCUK","BİRLİK","CEVHER","CUMHURİYET","DARACIK","DERE BOYU 2","DEVRAN","DEĞİRMEN","EDİP ÇANAKÇI","ERDEMLİ","FOTO","GÜNEY","GÜNEŞLİ","GÜVEN","HACI HÜSEYİN PAŞA","HAL","HALİT PAŞA","HALİT PAŞA 2","HALİTPAŞA 2","HAMAM","KADİM","KARABAĞ","KARDEŞLİK","KARS1","KAZIM KARABEKİR","KIVANÇ","KIŞLA","KOCA MUSTAFA PAŞA","KONGRE","KUBİLAY","KUM","KÖPRÜ","MAREŞAL FEVZİ ÇAKMAK","MEHTAP","MENEKŞE","MERCAN","MERYEM","METEOROLOJİ","MEVLANA","MUKTED DEMİR","NAZAR","NEZİH","ONUR","ORDU","POYRAZ-","SABIR","SABIR-","SEDEF","SELAMET-","SESSİZ","SESSİZ-","SEVGİ 1","SEVİYE-","TAŞ","TAŞ1","TEKEL 75. YIL","TELEKOM","TEMİZ","TUFAN","TÜY","UÇURTMA","VALİ HURŞİT BEY","VALİ HURŞİT BEY1","VERİMLİ-","YANLIZ","YAYLACIK","YUNUS ZEYREK","YÜN","ÇARŞI","ÇAĞRI","ÇEVRE YOLU","ÇIKMAZ 2","ÇIKMAZ 2-","ÜMİT KAPTANCIOĞLU","İMAR","İNCE 1","İNCE 2","İNÖNÜ","ŞEFİK CAN","ŞEHİT ER BİLGİN VARLI","ŞEHİT TÜRKMEN TEKİN","ŞEN"],"YENİ":["144.","145.","146.","147.","148.","149.","150.","151.","152.","153.","154.","155.","158.","160.","161.","164.","165.","166.","167.","168.","169.","170.","171.","172.","173","174.","175.","178.","179.","180.","181.","182.","ALAGÜL","ALPASLAN","ALİM","ATMACA","AVCILAR","AZİZİYE","AŞIK ŞENLİK","BAL","BAYRAM","BOSTAN 2","BULUŞ","CENNET","CILDIR ZAMBAĞI-","DEREBOYU","DESTAN","DOGU","ELVAN","EVREN","EZGİ","FAKÜLTE-","GELİN","KARANFİL","KARS","KASAPHANE","KAZANKALE","KAÇAR","KEŞİF","KUDRET","MEZBAHA","NAME","OKUL","OLGUN","PINAR","PIRILTI","SARDUNYA","SARMAŞIK","SAZLIKGÖL-","SÜMBÜL","TALİMGAH","TALİMGAH1","VALİ HURŞİT BEY-","VALİ HURŞİT BEY1","YAVRU","YENİ","YILMAZ-","YOKUŞLU","ÇAYKENARI","ÇAĞLAR","ÇİSİL","ÇİÇEKLİ","ÜNİVERSİTE-","ŞEHİT ER MUZAFFE ÇELİK","ŞEHİT ER SERHAT ŞANLI","ŞEHİT ER UMUT GÖKDEMİR","ŞEHİT MAKSUT AKTAŞ"],"İNÖNÜ":["1.","10.","11.","12.","13.","14 MART","14.","15.","16.","17.","18.","19.","2.","20.","23 ŞUBAT","4.","5.","6.","7.","78.","79.","8.","80.","81.","82.","83.","84.","86.","87.","88.","89.","9.","90.","91.","92.","93.","ACİL","ACİL 1","AHMED DURSUN NATIKİ","AHİLER","AKAR","ARDA","BADEM","BERFİN","BERFİN1","BESTE","BURCU","BURÇ","BÖLÜM","BÜLBÜL","BİLGİNLER","BİTKİ","CELAL TUNUS","CESUR","COŞKU","DEMİR","DOKTORLAR","DSİ","DURSUN AKÇAM","DURU","DÖNEM","DÜNYA","DÜZEY","DÜŞLER","DİYAR","ECDAT","EFELER","EFLATUN","EKİN","ELMAS","EMEK","ERTUĞRUL GAZİ","ERZURUM","ESİLA","EĞEMENLİK","GEÇİM","GÖNÜL","GÖRGÜLÜ","GÖZLEM","GÜMRÜK","GÜMÜŞ","GÜN","GÜRÇAYIR","GÜVERCİNLİ","HASTAHANE","HAYDAR ÇETİNKAYA","HAZİNE","HIZIR","HOŞ","IRMAK2","IŞIK","KAMİL","KARAYOLLARI","KARÇİÇEĞİ","KAZIM MOĞAN","KENT","KILIÇ","KISMET","KIZILCIK","KOCA MUSTAFA PAŞA","KONGRE","KONGRE1","KONUT","KORU","KUMRU","KURA","KURTULUŞ","KİTAP","LALE","MEHTAP1","MERT","MEYVELİ","MEŞE","MUTLU","MİLLET","NERGİS","ORD. PROF. DR. FAZIL ERDOĞAN","ORMAN","ORTAM","OSKAR","OSMAN SERVER ATABEK","PROF. DR. AZİZ SANCAR","PROF. DR. M. FAHRETTİN KIRZIOĞLU","PROF.DR.A.MECİT DOĞRU","RAMPA","SAYGIN","SAYGIN1","SAĞLIK1","SEDİR","SELVİ","SERÇE","SERİN","SEVİNÇ","SEÇKİN","SOĞANLI","SUNUM","TAKIM","TALİH","TALİM","TEKEL 75. YIL","ULU","UĞURLU","VAKİT","VATAN","YASEMİN","YEL","YEMENİ","YENİ HASTANE","YENİ TOKİ","YEŞİLEVLER","YOLCU","YUNUS EMRE","ZAMBAK","ZEMHERİ","ZIPKIN","ZORLU","ÇAMLIK","ÇEVRE YOLU","ÇINAR","ÇİMEN","ÖMÜR","ÜŞENMEZLER","İBNİ ARABİ","İMAR YOLU","İNCİ","İNÖNÜ1","ŞAHİN","ŞEHİT HATİCE HANIM","ŞİRİN"],"HALİLEFENDİ":["186.","187.","188.","189.","190.","191.","192.","193.","194.","195.","196.","197.","198.","199.","201.","202.","203.","204.","205.","206.","207.-","208.","209.","210.","211.","212.","213.","214.","215","216.","217.","218.","219.","220.","221.","222.","223.","224.","226.","227.","228.","229.","230.","231.","232.","233.","234.","235.","236.","237.","238.","239.","240.","241.","242.","243.","244.","245.","246.","247.","248.","249.","250.","251.","252.","253.","254.","255.","256.","257.","258.","259.","260.","261.","262.","263.","264.","265.","266.","267.","268.","269.","270.","271.","272.","273.","274.","275.","276.","277.","278.","279.","280.","281.","282.","283.","284.","285.","286.","287.","288.","289.","290.","291.","292.","293","ABİDE","AHISKA","AHSEN","ANT","ARI","ARICILIK","ARTVİN","ARTVİN1","ARTVİN2","AYAR","AŞIK MAZLUMİ","BAHTİYAR VAHAP ZADE","BARIŞ","BAYIR","BEKLENTİ","BOSTAN","BOSTAN1","BOSTAN3","BOSTAN4","BOSTAN5","BİTİRİM","CAMİ","CİHAN","DAL","DAR","DAĞ YOLU","DAĞLAR-","DEHA","DEMET EVLER","DEMET EVLER1","DENİZ","DUMLUPINAR","DUYGU","DİVAN","ENVER KESKİN","ERENLER","GARİPLER","GAZİLER","GAZİLER1","GAZİLER2","GENÇ","GEÇİT","GURBET","GÖKKUŞAĞI","GÖKKUŞAĞI1","GÖLLER","GÖRGÜ","GÖÇERLER","GÜL","HAKLAR","HANAK","HANAK1","HANAK2","HANAK3","HANAK4","HANAK5","HANAK6","HARMAN","KADER","KADER-","KALE","KAMER","KARAYOLU1","KARDELEN","KARTALPINAR1","KAYA","KAYALAR","KAYNAK","KELEBEK","KEMER","KERVAN","KIŞ","KOCATEPE","KÜR","MADEN","MEHMET BAYRAKTAR","MEHMET BAYRAKTAR1","MEŞALE","MİTHAT CİNCOROP","OP.DR. HALİS SOYLU","OSMAN SERVER ATABEG","PEKMEZLER","RENK","RÜZGARLI","SABRİ TURAN","SARI HAFIZ EFENDİ","SARI HAFIZ EFENDİ1","SARIÇİÇEK","SELAM","SU","SULAKYURT1","SUR","SUR-","TARIM","TARIM1","TAŞLI","TURKUAZ","TURNA","VOLKAN","VOLKAN1","YANIK CAMİ","YAPRAK","YAPRAK1","YAREN","YAŞAM","YIL","YUSUF GÜNGÖR","ZALOĞLU RÜSTEM TOPÇU","ZALOĞLU RÜSTEM TOPÇU1","ZALOĞLU RÜSTEM TOPÇU2","ZÜMRÜT BAYRAKTAR","ZİKRİ GÜNAL","ÇARE","ÇEŞMELER","ÖĞÜT","İCAT","İSTİKLAL","ŞEHİT ER BİLGİN VARLI","ŞEHİT ER ERKAN GÖKTAŞ","ŞEHİT ER ÖMER KAHYA","ŞEHİT ER İLHAMİ GÖRMÜŞ","ŞEHİT POLİS HAKKI ÇELİK","ŞEHİT POLİS HAKKI ÇELİK1","ŞEHİTLER","ŞEHİTLER1","ŞİFA","ŞİFA1"],"DEĞİRMEN":["DEĞİRMEN"],"ORTA":["ORTA NEBİOĞLU"],"TULUMBA":["TULUMBA"],"YUKARI":["AŞAĞI AÇIKYAZI","KÜÇÜKSÜTLÜCE","YUKARI","YUKARI AÇIKYAZI","YUKARI SAMANBEYLİ","ÖMERAĞA"],"YAYLACIK":["YAYLACIK"],"MERKEZ":["ÇAĞLAYIK"],"ORTAGEÇİT MÜCAVİR":["ORTAGEÇİT MÜCAVİR"],"SUGÖZE MÜCAVİR DIŞI":["-"],"AŞAĞI":["AŞAĞI","AŞAĞI AÇIKYAZI","AŞAĞI MEVKİ","AŞAĞI SAMANBEYLİ","DEDEGÜL","ÖMERAĞA"],"GÜRÇAYIR":["21.","22.","23.","24.","25.","26","27.","28.","29.","30.","31.","32.","33.","34.","35.","36.","37.","38.","39.","40.","41.","42.","AŞIK SÜMMANİ","BİRLİK","DİKİLİ","GÜLİZAR OĞLU ABDULLAH","GÜR","GÜRCAYIR","GÜRCAYIR1","GİZEM","KARDEŞLİK","LALE","SANCAK","YAZI","ÇEVRE YOLU","ŞEREF TAŞLIOVA"],"KÖYÜN KENDİSİ":["AŞAĞI","BAĞDEŞEN","HÇ.HASKÖY","ORTAGEÇİT","SUGÖZE","YALNIZÇAM BUCAĞI","YANLIZÇAM HASKÖY","YANLIZÇAM YAYLA","YUKARI","ÇERME"],"KIZILKİLİSE":["KIZIL KİLİSE"],"ÇİFTLİK":["ÇİFTLİK"],"ŞEHİRYOLU":["ŞEHİR YOLU"],"GİRİŞ":["AŞAĞI","LATİF-"],"ESKİ":["ESKİ"],"MEZRA":["MEZRA"],"DERE":["DERE"],"KÖPRÜBAŞI":["HÇ. HASKÖY KÖPRÜBAŞI"],"ÇERME":["ÇERME"],"ATATÜRK":["100.","101.","102.","103.","104.","105.","106.","107.","109.","110.","111.","112.","113.","114.","115.","116","117","118","119","120.","121.","122.","123.","124.","125.","126.","127.","128.","129","134.","135.","136.","137.","138.","139.","140.","141.","142.","56","59","61","62-1","63.","64.","65.","66.","67.","68.","69.","70.","71.","72.","73.","74.","75.","76.","77.","94","95.","96.","97.","98.","99.","AHENK","ARAYIŞ","ARMAĞAN","ASIM","AYDINLIK","AÇELYA","AŞIK FAKİRİ","AŞIK SÜMMANİ","BALCILAR","BAĞLAR","BEREKET","BEYAZIT","BULGU","BURÇAK","BUZLU","CEM ENDER ARSLANOĞLU","CEYLAN","DERVİŞ","DERYA","DEĞİRMEN","DOLUNAY","DR. ESAT OKTAY","DR.ESAT OKTAY1","ELA","EMİR","GAZEL","GELİNCİK","GÖKSU","GÖKÇE","GÜNEY","GÜNEŞ","GÜRCÜBEY","HACI HÜSEYİN PAŞA","HAZAN","HAZAN2","HUDUT","KADİR","KANARYA","KARAKAYA","KARS","KAVAK","KIRAZ","KIRLANGIÇ","KONAK","KUĞU","KUŞBURNU","KÖPRÜ","LADİN","LAVİNYA","MERDİVENLİ","MİRA","NARİN","NUH","OYLUM","PAŞA","PERÇEM","POLEN","REHBER","SANAYİ","SAYGI","SAZLIK","SEMA","SILA","SULTAN","SÜLİN","SİTE EVLER","TABLO","TARÇIN","UMAR","VEFA1","YAMAÇ","YAYLA","YAZ","YAĞIZ","YELKEN","YILDIRIM","YONCA","YORGUN","YORUM","YİĞİTLER","ZERDA","ÇAKIL","ÇAKIR","ÇAKIR1","ÇAYIR","ÇAĞLA","ÇAĞLAYAN","ÇEVRE YOLU","İDİL","İLKE","İRADE","ŞANS","ŞEHİT ER EROL ŞİT","ŞEHİT ER GÖKHAN ÖZDEMİR","ŞEHİT ER GÜNDAY POLAT","ŞEHİT ER GÜNDAY POLAT1","ŞEHİT ER METİN DEMİRCİ","ŞELALE"],"KARTALPINAROSB":["1. SANAYİ","2. SANAYİ","3. SANAYİ","4. SANAYİ"],"ÇAMLIÇATAK MÜCAVİR":["AŞAĞI"],"SULAKYURT MÜCAVİR DIŞI":["DEĞİRMENLİ","SULAKYURT"],"YAYLACIK MÜCAVİR DIŞI":["YAYLACIK MÜCAVİR DIŞI"]}