{"ORTA":["1","19 MAYIS","2","3 KASIM","5","ATATÜRK","BİLİNMEYEN","BİLİNMEYEN 200","CUMHURİYET","DR.İBRAHİM GÖKÇE","FİDAN","FİKRET AVCI","HALİTPAŞA","HOCA AHMET YESEVİ","KARANFİL","KAZIM KARABEKİR","LATİF AKÜZÜM","MANDIRA","PARK","SERVETTİN DURMUŞ","VATAN","ZÜBEYDE HANIM","ÇİÇEK","ŞHT.FİKRET LAÇİN"],"BAHÇELER":["19 MAYIS","ATATÜRK","BİLİNMEYEN","BİLİNMEYEN 201","BİLİNMEYEN 205","BİLİNMEYEN 208","CUMHURİYET","GÖKHAN ERGUN","MEDET ALİBEYOĞLU"],"YALINÇAYIR":["MİLLİ EGEMENLİK","MİLLİ EGEMENLİK 1"],"YENİ":["AHMET ARSLAN","BİLİNMEYEN 202","BİLİNMEYEN 206","BİLİNMEYEN 207","BİLİNMEYEN2","CUMHURİYET","CUMHURİYET 1","CUMHURİYET 2","DR.İBRAHİM GÖKÇE","FİKRET AVCI","HACI MECİT GÜNTAY","KAZIM KARABEKİR","TÜRKÖZÜ","ZİLFALİ ÖZKAYA"],"GAZİLER":["6","ATATÜRK","AY","BELEDİYE","CAN","GÜN","KARAKOL","ŞHT.KURBAN KORKMAZ"],"GÜLTEPE":["3","4","KAZIM KARABEKİR","KÜME","NEŞE","SELVİ","VATAN","ÇİLEM"],"CARCIOĞLU AFET EVLERİ":["KÖY"]}