{"DAĞYENİCE":["AHESTE ÇIKMAZI","AKBAYIR","AKIN BAŞOĞLU ÇIKMAZI","AYBERK ÇIKMAZI","BAHÇEDERE","BALABAN","DÜBEK","GÜLFER ÇIKMAZI","GÜLGONCA ÇIKMAZI","GÜLVEREN ÇIKMAZI","GÜLYALI ÇIKMAZI","GÜMRÜK","GÜN","GÜNBATIMI ÇIKMAZI","GÜNDÜZ","GÜNGÖR","GÜRAY ÇIKMAZI","GÜRCAN","GÜRGEN ÇIKMAZI","HALAY ÇIKMAZI","KALFAKÖY","KARACAKÖY","KONUT","KORDON","KURMAKÖY","KÜÇÜKDERE","NAMAZGAH","RANA ÇIKMAZI","SAHRA","SEHER","TAŞ ÇIKMAZI","VAKIF ÇIKMAZI","YETKİN","ZİRVE","ÇAMLICA","ÖZVATAN","ŞEFAAT ÇIKMAZI","ŞEHİTLİK"],"İNCEĞİZ":["ACISU ÇIKMAZI","AFACAN ÇIKMAZI","ALACALI","ARİF NİHAT ASYA","AYNUR","AÇIKALIN ÇIKMAZI","BERFİN","BİLİM","BİRGÜL","CAN","GAZİBABA","GELİNCİK","GÜLAĞACI","HAMAMÖNÜ","HANİCE","KABAKÇA","KARAÇALI","LOKMACIK ÇIKMAZI","MAZİ","MAĞAZACI","MEDDAH","MEDENİYET","MEHMETEFENDİ","MEHPARE ÇIKMAZI","MEHTER ÇIKMAZI","MEHİR ÇIKMAZI","MEKAN ÇIKMAZI","MELEK ÇIKMAZI","MELİKE","MEMDUH","MEMLEKET ÇIKMAZI","MENEMEN","MENGÜ","MENTEŞE","MENZİL ÇIKMAZI","MERA ÇIKMAZI","MERCAN","MERDİVEN ÇIKMAZI","NUMAN ÇIKMAZI","RÜZGAR","SULTAN ÇEŞME","SÜMER","YÜKSEL","ZARİF","ÖZYUVA","İNCEĞİZ","ŞEHİT PİYADE ER ERHAN ÇİYAPUL"],"KABAKÇA":["ABİR ÇIKMAZI","AHENK ÇIKMAZI","AKGÜVERCİN","AKŞEMSEDDİN","ALABEY ÇIKMAZI","ALASYA","ASİL","ATAÇ ÇIKMAZI","ATLAS ÇIKMAZI","AYVAÇEŞME","AŞURE","BEGONYA","BEKİRLİ","BERGÜZAR ÇIKMAZI","BEYPINARLAR","BEYZADE","BİLEK","CEMAL OGAN","CENGİZHAN","DİLAN","FESLEĞEN","FETTAH ÇIKMAZI","GÜLBAHAR","GÜLHAYAT","GÜNÇİÇEĞİ ÇIKMAZI","HABİBE","HALİTPAŞA","HANİCE","HATİP","KARDELEN","KASIMPATI","KIRLANGIÇ","LADİK","LEVENT ÇIKMAZI","LEYLA ÇIKMAZI","LEYLAK","LEYLEK ÇIKMAZI","LODOS","LOKMAN ÇIKMAZI","LÜTUF ÇIKMAZI","LİDER ÇIKMAZI","LİLA ÇIKMAZI","LİMAN","MABET ÇIKMAZI","MADALYA ÇIKMAZI","MADEN ÇIKMAZI","MAHYA ÇIKMAZI","MAHİR","MAKUL","MALKOÇ","MANAV","MANAVGAT","MANDIRA","MANSUR ÇIKMAZI","MARAL","MARAŞ","MARİF ÇIKMAZI","MARİFET","MELEKOTU","NEHİR ÇIKMAZI","NİZAM ÇIKMAZI","OKAN ÇIKMAZI","PALA","REHA ÇIKMAZI","RÜZGAR","SALTUK","SALİH","SARDUNYA","SARMAŞIK","SEVİM","SOLMAZ","SUZAN","SÜRMELİ ÇIKMAZI","SÜVARİ ÇIKMAZI","TOYGAR","UHUD ÇIKMAZI","ULUYOL","UYGUÇ ÇIKMAZI","VALİDE","YAVUZ SELİM","YAZGÜLÜ ÇIKMAZI","ZAFER","ZAKKUM","ZORLU","ÇALMAR","ÇARŞIKAPI","ÇAYIRKAPI","ÇINARCIK","ÖZDİL","ÜZÜLMEZ ÇIKMAZI","İNCİ","İSTANBUL"],"YALIKÖY":["29 EKİM","ADA","AFİYET","AGAH","AKABE","AKSUNA","ASALET","AYDENİZ","AYKUT","AÇIKEL","AÇIKGÖZ","BARAN","BAYKARA","BAŞÖZ","BEYLİK ÇIKMAZI","BUKET","BULUT ÇIKMAZI","BULUŞ ÇIKMAZI","BURAK ÇIKMAZI","BURCU","BURHAN","BURMA","BURÇ","BURÇİN","BUSE","BUĞRA ÇIKMAZI","BÜRDE","BÜYÜK ÖNDER MUSTAFA KEMAL","CAFER","CANAN","CANAY","CANAYDIN ÇIKMAZI","CANBERK","CANDAN","CANDAŞ","DENİZ KÖŞKLER","DERE YANI","DSİ","DÜZ","EFTELYA","ESEN YALI","FATİH","GÖKDENİZ","GÖL YANI","GÖL YOLU","GÜLSÜM","GÜZEL YALI","GİZEM","ISTIRANCA","KAYALIK","KESTANE","KIR ÇİÇEĞİ","KIŞLA YOLU","KUMSAL","KUZULDERE","KUĞULUGÖL","MELİSA","NAR ÇİÇEĞİ","NECLA AKBEN","OKAY","ORMANTEPE","PANAYIR","PODİMA EVLERİ","PROF. DR. TANSU ÇİLLER","RENK","RÜZGARLI","SERGEN","SEYHAN","SÜLEYMAN DARCAN","TEVHİD","TÜLİN BERBERGİL","YALIKÖY","YELKEN","YEMENİ ÇIKMAZI","YEŞİLBAĞ","YOSUN","YUKARI BAĞLAR","ÇAKIL TAŞI","ÇANKAYA","ÇATALMEŞE","ÇİLİNGOZ","ÖĞRETMEN","İSKELE","ŞAH","ŞAHİNTEPE","ŞEBBOY","ŞEKER"],"AYDINLAR":["AKBİLGE ÇIKMAZI","AYPARE","BAHA","BAKLA","BALCI ÇIKMAZI","BAŞKUMANDAN","BİNKILIÇ","BİTENGÜL","GÖÇ","GÜREL","KARACA AHMETPAŞA","KARAN","KAYINPINAR","KEMALPAŞA","MEDENİ","MERHAMET","MERMER","MERİH","MEYDAN","MEŞELİK","MİMAR SİNAN","NİŞANCI ÇIKMAZI","OSMANGAZİ","PEHLİVAN ÇIKMAZI","RIDVAN","SAFİR ÇIKMAZI","SERVİ","SEVİNÇ ÇIKMAZI","SULTAN MEHMET","YILMAZ","ZEKİ ÇIKMAZI","ÇINARALTI","ÇOLAK","ÇİLEKÇİ ÇIKMAZI","ÖZKUL ÇIKMAZI","ÖZTUNÇ","ŞAN ÇIKMAZI","ŞENNUR"],"KALEİÇİ":["ACET EVLERİ","ADEMEFENDİ","AHMET ACET ÇIKMAZI","AKAT","ALTINAY","ASAF","ASLAN","ATAOL BEHRAMOĞLU","AVŞAR","BAHAR","BAKIR","BAŞAK","BERBEROĞLU","BEŞ KAVAKLAR","BURÇAK","BÜKLÜM","BİLGİN","BİLİM","BİNBAŞI TEMEL ÜNSAL","CAMBAZ","CAMBAZ ALİEFENDİ","CANLAR","CEVDET BARIN","CEYDA","CEYLAN ÇIKMAZI","CEZVE","CİHAN","CİHANNUR","CİVANMERT","DAİRE","DOKTOR ÇEŞME","DOMUZDERE","DUTLUK ÇIKMAZI","DİK","EDA","EKREM AKBAŞAK","ER","ER-","ETHEM","ETİ","FANİ","FASIL","FERAY","FETİH","GENCAY","GÖK","GÖKHAN KALAYCIOĞLU","GÖKÇEALİ","HALE","HAN","HANEDAN","HANGAR","HANÇER","HANİCE","HASAN UZUN","HAYRİ KUYAŞ","KALE","KALEARKASI","KALEDIŞI","KALYON","KAPAKLI","KARAAĞAÇLAR","KARADENİZ","KARAKOL ÇIKMAZI","KARAMAN","KARASU","KARAÇALI","KARAÇAY ÇIKMAZI","KARTAL","KASAPLAR","KASIM ÇIKMAZI","KAVAKLAR","KAVAKLIK ÇIKMAZI","KAYA","KESKİN ÇIKMAZI","KIBRIS ŞEHİDİ ABDÜLKADİR TANGUÇ","KIRAN","KIZILCA","KOVAN ÇIKMAZI","KOÇYİĞİT","KUMRU","KUĞU","KUŞKAYA","KÖPRÜ","KÜHEYLAN","LAVANTA ÇIKMAZI","LEMAN","LOMBORİOZ","LİMON","MAKBUL","MARANGOZ","MARTI","MAZLUM SAYLAM","MEHMET ŞANLI","MEHTAP","MUHTAR ENVER ÇAĞLAYAN","MUKADDER ÖKTEN","MÜNİF SEVİ","MİSAFİRHANE","NADİR AĞACI","OGÜN","OLCAY","OLTU","OLUK","OLUŞUM","ONAT KUTLAR","ONAY","ONUR","ORKUN","ORUÇ","ORÇUN","OSMAN GÖZLER","OTAĞ","OVA","OYMAK","OZAN ÇIKMAZI","OĞUZ","OĞUZHAN","PETEK","PETUNYA","PİROĞLU","PİYALE","SABIR","SANAYİ ÇARŞISI","SARRAF","SEFA","SIĞLA","SU DEPOSU","SUR","SÜNNETÇİ FETHİBEY","SİPER ÇIKMAZI","TALİP ERASLAN ÇIKMAZI","TAN","TEKCAN","TEVFİK ERDÖNMEZ","TOLUNAY","TOMURCUK","TOPUKLU","TURGUT ÖZAL","TÜNEL ÜSTÜ ÇIKMAZI","ULU CAMİ","UMUTLU","UYGUR","VAROL","VATANSEVER-","VEZİR FERHATPAŞA","VİŞNE","YAMAÇ ÇIKMAZI","YELTEPE ÇIKMAZI","YENİCE","YILDIRIM","YURT","YÖRE","ZİYA OTÇU","ÇUKURÇEŞME","ÖDEMİŞ","ÖDÜL","ÖKTEN","ÖMÜR","ÖNAL","ÖNCEL","ÖNCÜ","ÖNEM","ÖNER","ÖREN","ÖRGÜN","ÖRNEK","ÖYKÜ","ÖZAY","ÖZAYDIN","ÖZGE","ÖZGÜVEN ÇIKMAZI","ÖZTÜRK ÇIKMAZI","ÖĞRETMEN GALİP AKSU","ÖĞRETMEN HANDAN ÖZDEMİR","ÖĞÜT ÇIKMAZI","ÜLKÜ","ÜNAL","ÜRGÜP","ÜÇ KONAKLAR","İBRAHİM KILIÇ ÇIKMAZI","İNCEĞİZ","İSKENDER ÇIKMAZI","İSTASYON","İSTİKBAL -","ŞAİR NECMETTİN HALİL ONAN","ŞEHİT ALPER SÜRÜCÜOĞLU","ŞEHİT HALİL İBRAHİM GÜREL","ŞEHİT KADRİ ÇAKMAKYAPAN","ŞEHİT MÜMİN DEMİRALP","ŞEHİT NABİH ÖZKAN","ŞEHİT UZAY KİŞİN","ŞEHİT İLHAN SONKAYA","ŞENLİK","ŞÜKÜR","ŞİFA ÇIKMAZI"],"MURATBEY MERKEZ":["19 MAYIS","30 AĞUSTOS","71.","AHMEDİYE-BAHŞAYİŞ","AKBUĞDAY","AKYOL","AKÇEŞME","AKŞEN","ALTINDAL","ANAVATAN","ANIT","ATİYE","AYDINAY","BAHARATLI","BAHTIŞEN","BAHÇELER","BAĞIMSIZLIK","BAŞEĞMEZ","BAŞTUĞ","BEND","BOZBEYLİ","BİLİR","BİNNUR","CANLI","CANPARE","CANSEV","CEPHANECİ","CEPHANELİK","CERRAHPAŞA","CEVİZAĞACI","CEVİZCİ","CEVİZLİBAHÇE","CEYİLAĞACI","COŞKUNER","CÜMLE","DAMAT İBRAHİMPAŞA","DAĞBÜLBÜLÜ","DEKOR","DEMRE","DEMİRBAHÇE","DEMİRHİSAR","DEMİRKENT","DEMİRTAŞ","DERVİŞZADE","DERİCİLER","DERİNÖZ","DEYİM","DOST","DUMLUPINAR","DÖNÜŞÜM","DÜZLÜKLER","DÜZOVA","DİBEK","DİNAR","EDİNCİK","EFDAL","EKONOMİ","EMİRGAN","ERBATUR","ERTAN","ERTAÇ","ERTEM","ERİKLİ","FABRİKALAR","FAVORİ","FERHATPAŞA","FERİDE","FİLDİŞİ","GAZİPAŞA","GEÇİT","GÖRKEMLİ","GÜMÜŞPALA","GÜNDEŞ","GÜNEBAKAN","GÜNEYGİRİŞİ","GÜZGÜLÜ","GÜZİDE","HAK","HAYRABOLU","HELAL","HENDEK","HIDRELLEZ","HÜRRİYET 3","KADEM","KADI ÇEŞMESİ","KADIPAŞA","KADRİBEY","KALAMAN ÇIKMAZI","KALDIRIM","KALEAĞASI","KALEBAHÇE","KALEBOYU","KALELİ","KALKANCI","KALPAKLI","KAMACI","KAMBER","KAMPÜS","KAMİL","KANARYA ÇİÇEĞİ","KANATLI","KANCA","KANDAŞ","KANDİLLİBAHÇE","KANGAL","KANISICAK","KANTARCILAR","KANTAŞI","KAPANCA","KAPIKULU","KAPTANLAR","KARADAL","KARAGAZİ","KARAMANLAR","KARATOPRAK","KAZAKÇILAR","KAĞITÇIBAŞI","KAĞNICILAR","KEMAH","KEMAL","KEMANCI","KEMENT","KEMENÇE","KEMERALTI","KEMERBOYU","KEMERKÖŞK","KERPİÇHANE","KERİMAĞA","KERİMEHATUN","KESMEKAYA","KESİCİLER","KESİKKAYA","KEYİF","KEZBAN","KEÇECİLER","KEÇECİZADE","KEÇİYOLU","KEŞAN","KEŞİF","KIRANKAYA","KIRAÇLAR","KIRIKKALE","KOLON ÇIKMAZI","KURTULUŞ","KUZEYOĞLU","KİTAPÇI","LADİN","LATİF","MAHLÜL","MANASTIR","MELEZ","MENDİREK","MÜBADELE","MÜŞFİK","NACAROĞLU","NACİ","NACİBEY","NADAS","NAKİL","NAL","NALBANTATAR","NALDÖKEN","NAME","NARDALI","NAĞMELİ","NAİLBEY","NAİME","NURŞEN","NİYET","OKÇULAR","PERİHAN","PINARBAŞI","RAY","SAADETLİ","SEYFETTİN ÖPÇİN","SUSAR","SİGORTA","SİMAY","TELLİ","TOPÇUTEPE","TURHALLI","VAHA","YAĞMURLU","YENİHAMAM","YEŞİLTEPE","YÜZBAŞI MURATBEY","ÇAKIRAĞA","ÇALGICI","ÇALIŞLAR","ÇALLI","ÇAMDERE","ÇAMLIBAHÇE","ÇAMLIKÖŞK","ÇAMLIPARK","ÇAMOVA","ÇANAKÇI","ÇANKIRI","ÇARIKÇI","ÇARKÇILAR","ÇARŞIARDI","ÇATAL","ÇATALCA YOLU","ÇATALÇAM","ÇAVDARCI","ÇAYIROVA","ÇAYIRYOLU","ÇAYIRÖNÜ","ÇAYKUR","ÇAYÇİÇEĞİ","ÇEKİM","ÇEKİRDEKÇİ","ÇELİKBİLEK","ÇERÇİ","ÇEVRECİ","ÇEVİRMECİ","ÇINARLIKÖŞK","ÇIRAK","ÇOBANÇAVUŞ","ÇORBACIBAŞI","ÇUBUKÇU","ÇULLUK","ÇİFTEHAVUZLAR","ÇİFTEÇINAR","ÇİLEK","ÇİMENLİK","ÇİNGÜLÜ","ÇİÇEKLİBAHÇE","ÇİĞDEMLİ","ÇİĞTANESİ","ŞEHİT ER MEHMET ALİ GÜMÜŞ"],"KESTANELİK":["AKALIN","AKDEMİR ÇIKMAZI","ARA","AŞİKAR","BALAT ÇIKMAZI","BALKAYA","BALKIZ ÇIKMAZI","BAYINDIR","BAĞLAR","BAŞKUMANDAN ATATÜRK","BEYDAĞ ÇIKMAZI","BUDAK","DOĞANYURT","DÜLGER","DİSPANSER","EGEMENLİK","ENES ÇIKMAZI","ESKİ EDİRNE ASFALTI","GÖKTUĞ","HUKUK","HUSUSİ ÇIKMAZI","HÜDA","HÜDAYİ","ILGIT ÇIKMAZI","ILICA ÇIKMAZI","ILIMAN ÇIKMAZI","IRMAK","ITIR","IŞILTI","KAAN","KABATAŞ ÇIKMAZI","KADER ÇIKMAZI","KADIRGA","KADİFE","KADİM ÇIKMAZI","KADİR","KAFKAS","KAHYA","KALAMIŞ","KALBUR","KALEM ÇIKMAZI","KALENDER","KALFA","KALKAN","KAMER","KAMURAN","KANAAT","KANAL","KANDEMİR","KANDIRA","KANDİL ÇIKMAZI","KANYON","KAPLAN","KAPLICA ÇIKMAZI","KAPTAN","KAR ÇIKMAZI","KARABAYIR ÇIKMAZI","KARABULUT ÇIKMAZI","KARABURUN ÇIKMAZI","KARACAKÖY","KARACASU ÇIKMAZI","KARADUMAN ÇIKMAZI","KARAGÖZ","KARAHAN","KAYANDERE","KAYYUM","KAÇKAR","KAİNAT","KESTANELİK","KORAL","KUŞLAR VADİSİ","KUŞLAR YAYLASI","MARUF","MAYIS","MECNUN","MEŞETOPU","MİHRİCAN","MİHRİMAH","NEBİYE","NENEHATUN","NURDOĞAN","PARK","REİS","SAMATYA","SERAMİK","SIVAT","SULARBAŞI","TABYALAR","TAZEGÜL ÇIKMAZI","TEBESSÜM","TEKGÜL","TESTİ ÇIKMAZI","UYSAL","YALDIZ","YENİ","YEŞİLAY","ZERDE","ÖVÜNÇ","ÖZNUR","ÜMMET ÇIKMAZI","İCLAL","İDEAL ÇIKMAZI","İDİL ÇIKMAZI","İFFET ÇIKMAZI","İFTİHAR","İHLAS","İHSAN","İKBAL","İKRAM","İLAYDA","İLBEY","İLHAM","İLYAS","İLİM","İMAR","İMRAN","İMREN","İNAN","İNANÇ","İNDERE","İNEBOLU","İNEGÖL","İNKILAP","İRADE ÇIKMAZI","İREM","İRFAN","İTİBAR","İTİMAT","İTİNA","İYİSOY","İĞDE","İŞTİRAK"],"GÖKÇEALİ":["AHSEN ÇIKMAZI","ASMA","AYDAN ÇIKMAZI","BAHÇE","BALKAN","BAŞÖĞRETMEN ATATÜRK","BESTE","BUĞDAY ÇIKMAZI","CEVİZLİK","DRAMA","EREN","GEVHER ÇIKMAZI","GEZEGEN","GEZER","GEZGİN ÇIKMAZI","GEZİCİ ÇIKMAZI","GÖKALP ÇIKMAZI","GÖKDEMİR ÇIKMAZI","GÖKDOĞAN ÇIKMAZI","GÖKDUMAN","GÖKHAN ÇIKMAZI","GÖKKUŞAĞI ÇIKMAZI","GÖKOVA ÇIKMAZI","GÖKSEL","GÖKÇAY","GÖKÇEALİ","GÖKŞAH","GÖL ÇIKMAZI","GÖLBAŞI ÇIKMAZI","GÖLCÜK ÇIKMAZI","GÖLHİSAR ÇIKMAZI","GÖÇMEN ÇIKMAZI","GÜLKURUSU ÇIKMAZI","KARAÇALILIK ÇIKMAZI","KAZIM KARABEKİR","MAREŞAL FEVZİ ÇAKMAK","MEHMET AKİF ERSOY","NERGİS","PEKMEZCİ","RAVZA","SANCAK ÇIKMAZI","SELAM ÇIKMAZI","SOĞUKSU","TÜRKÖZ","ZİYA GÖKALP","ÖZVERİ","İKİZLİ ÇEŞME","ŞAFAK ÇIKMAZI"],"FERHATPAŞA":["ACAR","ADLİYE","ADNAN","ADNAN DİNÇER","ADNAN KANTEK","AHMET DUYMAZ","AKHUN","AKYAKA","ALAÇAM ÇIKMAZI","ALİPAŞA","ALİÇAVUŞ","ARDA","ARDIÇ","ARK ÇIKMAZI","ARMAĞAN ÇIKMAZI","ARPALIK","ARİF NİHAT","ATA","ATATÜRK","ATİLLA","AVCI SULTAN MEHMET","AYAZ","AYDER","AYIŞIĞI","AŞIKLAR","BAHTINUR","BAHTİYAR","BAHÇIVAN","BALTACI","BALÖZÜ","BANU","BAYIR","BAĞ","BAŞOL","BEGÜM","BEYAZ","BEYLER","BÜLBÜL","BİLGE KAĞAN","BİLGEHAN","BİLGİNUR","BİRİKİM","CAMİ","CELAL YÜCEL","COŞKU","CUMHURİYET","CİHANGİR","DALGIÇ","DARI","DEDEKORKUT","DEMİRBAĞ","DENİZ","DERUNİ","DEĞİRMEN","DOLUNAY ÇIKMAZI","DOĞUŞ","DR. MEHMET ALİ","DÜDEN","DÜZGÜN","DİKMEN","DİLARA","DİZDAR","DİŞBUDAK","EBEDİ","ECZACI LÜTFÜ ÖREN","EFE","EGE","EMİN","ENDER","ENVERPAŞA","ERBAY","ERENLER","ERGENE","ERGUVANLI","ERGÜVEN ÇIKMAZI","ERKUT","ERKİN BALABAN","ERLER","ERTUNGA","ERTUĞRUL","ERÇETİN","ESENTEPE ÇIKMAZI","EĞRİ","FAHRİ","FAZİLET","FERHAT AYGEN","FİRUZAN","GAMZE","GENÇLİK","GONCA","GÖKBERK","GÖKSU","GÖRGÜLÜ","GÖRKEM","GÖÇMENLER","GÜL","GÜLBAHÇE","GÜLDEFNE ÇIKMAZI","GÜLENAY","GÜLENDAM","GÜLTEN","GÜNAYDIN","GÜNDOĞDU","GÜNER","GÜNEY TEZ","GÜRHAN","GÜZ","GÜZEL ÇIKMAZI","HACI HAMDİBEY","HACI OSMAN","HAKİM ORHAN SEZGİN","HAMAM","HANLI","HASAN AKIN","HASAN BÜYÜK","HASAT","HAYRİ UĞUR","HAZİNE","HAZİRAN","HEYBETLİ ÇIKMAZI","HOCA AHMETEFENDİ","HURMA","HİDAYET","HİS","ILGAZ","KADI ÖMER","KADRİ DUYMAZ","KAFTAN","KAMİL GÖK","KARAMANLAR","KARANFİL","KARATAŞ","KARTEPE","KEKLİK ÇIKMAZI","KERVANSARAY","KIZILAY","KOVALIK ÇIKMAZI","KUTLUHAN","KİTAPÇI","LÜLE","LİSE","MANYAS ÇIKMAZI","MANİSA","MAZLUM","MEHMET ÖZCAN","MEKTEP","MERAL","MERT","MERİÇ ÇIKMAZI","MESCİT","MEŞE","MÜFTÜ LÜTFÜ DAVRAN ÇIKMAZI","MÜNİF SEVİ","NACİ ÇAM","NADİR","NALBANT","NAR","NATO","NESİM","NEYZEN","NUH ÇIKMAZI","NURALEM","NUSRET","NÜKHET ÇIKMAZI","NİYAZİ AKŞİT ÇIKMAZI","NİYAZİ KARADUMAN","OBA","OBALI","OCAK","OKYANUS","ORTA","ORTA SOFA","OĞUZCAN","PAPATYA ÇIKMAZI","PAZARYERİ ÇIKMAZI","PAŞA","PEKGÖZ","RAMAZAN SEMERCİOĞLU","RAŞİT AYKUT","REZZAN","RIZA ÖZDEN","SABRİ PESEN","SAKA ÇIKMAZI","SAKARYA","SEDA","SEFERAĞA","SELVİ ÇIKMAZI","SEVGİ","SEZAİ BÜRGE","SIR","SÜLEYMAN BİNGÖL","SÜLEYMAN ÖCAL","SÜTÇÜ PINAR","TAHTA KÖPRÜ","TAŞDEMİR","TAŞKÖPRÜ","TEKKE","TEVFİK ERDÖNMEZ","TEVFİK TEZCAN ÇIKMAZI","TOPLU KONUTLAR","TOPOROZ MUSTAFA","TUNA ÇIKMAZI","TURNA","TUTKU","TUĞBA","TÜTENGİL","TİYATRO","ULUS","USLU ÇIKMAZI","VEZİR FERHATPAŞA","VİLDAN","YAKAMOZ ÇIKMAZI","YAKUT","YATIR","YAĞMUR","YELDEĞİRMENİ","YEŞİM","YUSUFHOCA","ZEMZEM","ZİYA ALTINOĞLU","ZİYA KÖKTÜRK","ÇALIŞKAN ÇIKMAZI","ÇARE","ÇATALCA","ÇATALCA YOLU","ÇAYIR","ÇAĞLAYAN EGE","ÇAĞRI","ÇELTİK","ÇETİNCE","ÇEŞME","ÇÖMLEK","ÇİFTLİK","ÇİMEN","ÖZBEK","ÖZSOYLAR ÇIKMAZI","ÖĞRETMEN CEMAL ARAL","ÖĞRETMEN HAKKI KIMIZ","ÖĞRETMEN MEHMET CAVİT TALAY","ÖĞRETMEN NEVZAT TEKİN","ÖĞRETMEN NİHAT ERDEM","ÖĞRETMEN İLHAMİ ERDEM","ÖĞRETMEN ŞEHABETTİN AKALIN","ÜLFET","İCADİYE","İDRİS GENÇ","İHSANİYE","İHTİŞAM","İKİZLER","İLKİN","İMAM SIRRI PEKŞEN","İNFAK","İSTASYON","İZCİ","ŞAİR NECMETTİN HALİL ONAN","ŞEFKAT ÇIKMAZI","ŞEHİT J. ASTEĞMEN ALİ YILMAZ","ŞEHİT OKTAY ORKAN","ŞEHİT PİLOT DÜNDAR ÇIKMAZI","ŞEHİTLER","ŞERAFETTİN ARDA","ŞEYHÜLİSLAM","ŞÖHRET"],"ATATÜRK":["ADALET","AKTEKİN ÇIKMAZI","AKÇAKALE","ALPDEMİR","AYSEVEN","BAHARÇİÇEĞİ","BAŞKAYA","BAŞKUMANDAN","BUZAĞLIK ÇIKMAZI","BİLGE","BİNKILIÇ","DIRGAZ","DİNÇ","EBRULİ","FATİH SULTAN MEHMET","FAİK YUMUŞAK","FUNDA","GAZİ MUSTAFA KEMAL","GÖKNAR","GÜLERYÜZ","KORUK ÇIKMAZI","KUM","KURAL","KURDELE","KURTARAN","KURTULUŞ_1","KUVVET","KUYU","KUZGUN","KUZU","KUŞDİLİ ÇIKMAZI","KUŞKONMAZ","KÜBRA","KÜLHAN","KÜMBET","KÜPELİ","LAÇİN","META ÇIKMAZI","SAKLIBAHÇE ÇIKMAZI","SAMYELİ","SARGIN","SELMA","SEMİH","SEVCAN","TOPRAK","TUNAY","TÜFEK","UĞUR","ZİŞAN","ÇAKAR","ÇAMOLUK","ÖZLÜ","ÖZTEKİN"],"ÇANAKÇA":["AKBOĞA","AKGÜL ÇIKMAZI","AKKAN ÇIKMAZI","AMBARLI","AYŞEN","AŞIK ÇIKMAZI","BAHÇEDERE","BAHÇELİ","BALCILAR","BARAKA","BÜYÜK ÖNDER ATATÜRK","DEĞİRMENALTI","EKOL ÇIKMAZI","ESEN ÇIKMAZI","FERHATHOCA ÇIKMAZI","FIRIN ÇIKMAZI","GALİP HOCA","GÜNGÖR","GÜNNUR","GÜRBÜZ 1.","GÜRPINAR ÇIKMAZI","GÜRSOY","GÜRSU ÇIKMAZI","GÜVEN","GÜVERCİN ÇIKMAZI","GÜVERTE ÇIKMAZI","GÜZİN ÇIKMAZI","HAFIZ ÇIKMAZI","HAFIZ ÖMER","HAKAN ÇIKMAZI","HAKKI ÇIKMAZI","HAKİKAT ÇIKMAZI","HAKİM ÇIKMAZI","HAKİMİYET","HALDUN ÇIKMAZI","HALİM AKYEL ÇIKMAZI","HAMİDE ÇIKMAZI","HAVRUZ","HÖYÜKLER","HÜDAYİ","HÜMEYRA","HÜNER ÇIKMAZI","HÜNKAR ÇIKMAZI","HÜRMET","KARACAKÖY","KİRAZ ÇIKMAZI","MEŞETOPU","OKUL","PERİ ÇIKMAZI","PİREN","RIHTIM","SAFRAN","SONGÜL ÇIKMAZI","STAD","TABYALAR","TAZEGÜL ÇIKMAZI","TAŞ ÇIKMAZI","UYSAL","UYUM","VUSLAT","YANIK ALAY","YANKI ÇIKMAZI","YOLAÇAN","ZERDA","ÇAMSAKIZI ÇIKMAZI","ÇANAKÇI DEDE","ÇINAR","İBRAHİMÇAVUŞ"],"İZZETTİN":["ADAGÜLÜ","ADIM","AKİF","ALTINOK","BAHÇESARAY","BAŞARI","BELDE","BENTLER","BEYDAĞ ÇIKMAZI","BUHARA","BUKLE","BÜKLÜM","BÜLENT KARPAT","BİRLİK","CANDEMİR","CAVİDAN","CENGİZ ÇIKMAZI","DESTAN","DOBURCA","EFLATUN","ERCAN KÖYÜ","ERGUVAN","FARABİ","FULYA","GÖKÇEK ÇIKMAZI","GÜLER","HÜLYA CÖMERT","HÜRRİYET","IŞIL ÇIKMAZI","KAMELYA","KARLIOVA","KESTANELİK","KIRIM","KUDRET","LALEZAR","MECİT","MELTEM","MESLEK ÇIKMAZI","MEŞRUTİYET","MUNTAZAM","MİHRAP","MİLLET","MİSAFİR ÇIKMAZI","NADİDE","NAFİ TALU","NAZLIGÜL","NEVBAHAR","NİHAL","NİYAZİ TOPTOPRAK","RUKİYE","SADULLAH BOZ","SELİM","SEMERKANT","SENCER","SÜLEYMAN BİNGÖL","SÜTÇÜ PINAR","TAKDİR ÇIKMAZI","TATLIPINAR","TAŞLI PARA","TEMİZ ÇIKMAZI","UMUT","YOL ALTI","ÇİFTÇİ ÇIKMAZI","ÖZGÜN","ÖZGÜRLÜK","ÖZSU","İBRAHİM KOLCUOĞLU","İSTASYON","İZZETBABA","ŞERİF AKYÜREK"],"ELBASAN":["ASKER","ATÖLYE","AYAZMA","AYVALIDERE","BAKİ","BAYRAK","BAŞYİĞİT","BERRİN","BESİM","BETÜL","BEY","BEŞİKÇİ ÇIKMAZI","BEŞİR ÇIKMAZI","EBRU","ECE","ELBASAN","GURBET ÇIKMAZI","GÖLYAKA ÇIKMAZI","GÖNEN ÇIKMAZI","GÖNÜL","GÖZDE","GÖZLEM ÇIKMAZI","GÜLAY ÇIKMAZI","GÜLBEN","GÜLBERK ÇIKMAZI","GÜLBEYAZ ÇIKMAZI","GÜLCAN ÇIKMAZI","GÜLEÇ ÇIKMAZI","GÜLGÜN","GÜLHANE","GÜLNİHAL ÇIKMAZI","GÜLPERİ","GÜLSEVER","GÜLSUYU ÇIKMAZI","GÜLŞAH","KADIKÖY","KARADAYI","KARAHİSAR","KOOPERATİF","KÜTÜPHANE","MAĞAZACI","OVAYENİCE ELBASAN YOLU","SELANİK","SEYFİ DEMİRSOY","SOĞUKÇEŞME","TÜRKAN ÇIKMAZI","TÜRKER","ULVİ ÇIKMAZI","YAR ÇIKMAZI","İNCEĞİZ","İNCİRLİ","ŞELALE"],"SUBAŞI":["AKKAYA","AKMEŞE","AKMİNARE ÇIKMAZI","ASYA ÇIKMAZI","ATEŞ ÇIKMAZI","AVCI ÇIKMAZI","BAĞCI","BÜKLÜM","BÜKLÜM-","ESKİ EDİRNE ASFALTI","FATMA SULTAN","FİLİZ ÇIKMAZI","GÖKÇEALİ","GÜMÜŞPINAR","HAKEMLER","HAVUZLAR","KAPLAN GİRAY","KARAMAN","KARANİ ÇIKMAZI","KARASU","KAYAPINAR","KAYISI","KAZAN","KINIK","KOVANLIK","KOYUNCU ÇIKMAZI","KOZALAK ÇIKMAZI","KOŞU","KRİSTAL ÇIKMAZI","KUBBE ÇIKMAZI","KUDRET","KÖKLÜ ÇIKMAZI","KÖKSAL ÇIKMAZI","KÖRFEZ","KÖSE ÇIKMAZI","MUŞMULA DEĞİRMENİ","NİHAL","PEKMEZCİ","PİLOTLAR ÇIKMAZI","SELİM GİRAY","SOĞANLIK","SUBAŞI ÇIKMAZI","SİVRİKAYA","TUFAN","YAVER","YEDİ EVLER","YURDAGÜL","ÇAMAŞIRDERE","ÇELİK ÇIKMAZI","ÖZBİL ÇIKMAZI","ÖZDEMİR ÇIKMAZI","ÖZERDEM","ÖZTAŞ ÇIKMAZI","İPEK","İSTANBUL"],"HALLAÇLI":["AFŞİN","AKINCILAR","AYDIN","BAYCAN","BAŞKUMANDAN","CANER ÇIKMAZI","CANFEDA","DÖNENCE","DİDEM","ERGÜN","FİDAN","HACI YILMAZ","KADI","KARA TREN","KARA ÇIKMAZI","KARABAĞ","LAMBA TARLA","METİN","MORAL","MUCİZE","MUHABBET","MUHARREM ÇIKMAZI","MUHLİS ÇIKMAZI","MUHTEREM","MUKADDES","MURAT","MUTEBER","MUTLU","MUZAFFER","MÜBAREK","MÜCEVHER","MÜDAFA","MÜELLİF ÇIKMAZI","MİLLİ ŞAİR","MİSVAK ÇIKMAZI","MİZAN ÇIKMAZI","MİZAÇ ÇIKMAZI","SAYAN","SEBAT","SERBEST","SEZER","VATAN","YUNUS","ZÜMRÜT","İSMET İNÖNÜ"],"ÇAKIL":["AKTAŞ ÇIKMAZI","AKTEPE ÇIKMAZI","AKŞEN","ALAMET","ALTINBAŞAK","AZA HASAN","BENZİNLİK ARKASI","BEREKET","BERHUDAR","BERRAK ÇIKMAZI","BERİL","BEŞEVLER","CABBAR ÇIKMAZI","CELAL İLALDI","DOSTLAR","DUYGU","DÜZLÜK ÇIKMAZI","DİNÇER","DİYAR","EBABİL","EFENDİ ÇIKMAZI","EFSANE ÇIKMAZI","EGENUR","EKBER","EKER","EKREM ÇIKMAZI","ELA","ELBASAN","ELMAS","ELVAN","ELÇİ","ELİF","EMANET ÇIKMAZI","EMEL ÇIKMAZI","EMRAH ÇIKMAZI","EMRE ÇIKMAZI","EMİR ÇIKMAZI","EMİROĞLU ÇIKMAZI","ENGİNAR ÇIKMAZI","ENGİNSOY ÇIKMAZI","ENGİNSU ÇIKMAZI","ENSAR ÇIKMAZI","ENİS ÇIKMAZI","ERAY","ERBERK ÇIKMAZI","ERCAN ÇIKMAZI","ERCÜMENT","ERCİHAN ÇIKMAZI","ERCİYES ÇIKMAZI","ERDAL","ERDEM","ERDİNÇ ÇIKMAZI","ERENGÜL","ERKAN","ERKUL ÇIKMAZI","ERMAN ÇIKMAZI","ERMİŞ ÇIKMAZI","EROL ÇIKMAZI","ERSEVEN","ERSOY","ERSİN ÇIKMAZI","ERTAŞ ÇIKMAZI","ERTUNÇ","ERTÜRK ÇIKMAZI","ERYAMAN ÇIKMAZI","ERYILMAZ ÇIKMAZI","ERYİĞİT ÇIKMAZI","ERİK","ERİŞ ÇIKMAZI","ESAS ÇIKMAZI","ESENDAL ÇIKMAZI","ESENKAYA ÇIKMAZI","ESENLER","ESENLİK","ESENYEL ÇIKMAZI","ESER","ESKİHİSAR","ESMA","ESNAF","ESRA","ESİN","ESİNTİ","ETHEM TATLI","EVLİYA","EVREN","EVRENSEL","EVİN","EYLÜL","EYMEN","EYVAN ÇIKMAZI","EZBER","EZEL","EZGİ ÇIKMAZI","EĞİLMEZ","EĞİTİM","FARUK","FAZIL ÇIKMAZI","FAZLI ÇIKMAZI","FEDAKAR ÇIKMAZI","FELEK","FENER","FERDA","FERDİ ÇIKMAZI","FERMAN","FERZAN","FERİDUN","FERİT","FEYZA","GÜLİSTAN","GÜLŞEN","GÜNEBAKAN","HAREM","HIDRELLEZ","HÜSEYİN YILMAZ","KAMAN ÇIKMAZI","KARAMANLAR","KARAYOL","KAYIN ÇIKMAZI","KAZIM SAVAŞ","KILIÇ ALİ","MANASTIR","MUSTAFA KEMAL ATATÜRK","NAZLIHAN","NURİ BABA","ON EVLER","PIRLANTA ÇIKMAZI","RAMAZAN PEHLİVAN","SEDEF ÇIKMAZI","SEYFİ DEMİRSOY","TAŞKIN ÇIKMAZI","UFUK ÇIKMAZI","YALIN ÇIKMAZI","YAZAR ÇIKMAZI","YUNUS EMRE","ÇAKIL YOLU","ÇATALCA","ÇAVUŞ","ÇAY","ÖZGÜ","ÜSTÜN","ÜZEYİR COŞKUN","ŞEHİT TEĞMEN TAMER AYDIN","ŞEMENOĞLU"],"ÖRCÜNLÜ":["ASAR","AYTAÇ ÇIKMAZI","BAĞDERE ÇIKMAZI","BAĞLIK ÇIKMAZI","BAŞARAN","BAŞKOMUTAN","ERDOĞAN","ESKİ EDİRNE ASFALTI","GÜR","GÜRBÜZ 1.","KAYANDERE","KIDEM ÇIKMAZI","KILAVUZ ÇIKMAZI","KILIÇ ÇIKMAZI","KINCAL","KIR","KIRAAT ÇIKMAZI","KIRAÇ","KIRKPINAR ÇIKMAZI","KIRMAN ÇIKMAZI","KIZILCABAYIR ÇIKMAZI","KÖRBÜVET ÇIKMAZI","SEFERŞAH","SIVAT","TABYALAR","TANSU","TOROS","YAZ","YEKTA","ZENCEFİL","ÇALILI","ÇATAK","ÖZKAN","ŞAHİT ÇIKMAZI"],"OVAYENİCE":["4051.","AKASYA","ALAÇATI","AYÇİÇEK ÇIKMAZI","BAKİ","BAYRAKTAR","BEKA","BEKİRAĞA","BEREKET","BEŞER ÇIKMAZI","DAMLICA","DERYA ÇIKMAZI","DESTE ÇIKMAZI","DEVELİ","DORUK","DOSTANE ÇIKMAZI","DOĞA","DOĞAN ÇIKMAZI","DOĞANTEPE ÇIKMAZI","DOĞUHAN","DURU","DURUSU","DUT","DUYGU","DÜLDÜL","DÜNYA","DÜRÜST","DÜZEN","DÜZYOL","DİCLE","DİLA","DİLAVER","DİLRUBA ÇIKMAZI","DİLŞAD","DİNAMİK ÇIKMAZI","DİRHEM ÇIKMAZI","DİRLİK ÇIKMAZI","DİVAN","EBRAR","EBRU","ECE","ECLA","FEZA ÇIKMAZI","GAZİ ATATÜRK","GÜLTEPE ÇIKMAZI","GÜLŞAH","GÜZELCE","HANIMELLER ÇIKMAZI","HİLMİ ÇALIŞ","KADIKÖY","KARAYOL","KIBLE","KIZIL","KURUMANDIRA","LALE","MANOLYA","MENEKŞE","NECMİ SÜZEN","OVAYENİCE","PARILTI ÇIKMAZI","PARSELLER","SELEN","SEMAZEN","SEÇENLER","SIRMA ÇIKMAZI","SÜMBÜL","TEPE ÇAYIR","YENİAY","YENİDOĞAN ÇIKMAZI","ZENGİN","ÇATALCA","ÖZBAY","ÖZÇINAR","ÜMİT","İLKE"],"BAHŞAYİŞ":["AKAĞAÇ","AKSARAY","AKÇA","ATABEY","CEMAHİR","DAĞ ÇİLEĞİ","FEYZULLAH","KURUÇEŞME","SÜTÇÜ PINAR","ÇAMLIKTEPE","ÇAMLITEPE","ÇANAKKALE","ÇAĞRIBEY","ÇINARLAR","ÇOTANAK","ÇUHA ÇİÇEĞİ","ÇİÇEKTEPE","İZZETTİN"],"FATİH":["AÇANGÜL","BEKİR ÇIKMAZI","BEYZA","BİNKILIÇ","CANGÜL","CANSEL ÇIKMAZI","CANSEVER","CANSOY","CANTEKİN","CANTÜRK","CANİK","CEBECİ","CEBRAİL","CEBİR","CEFAKAR","CELİL","CEMAL","CEMRE","CEMİYET","CENGAVER","CENK","CENNET","CEREN","CERRAH","CESARET","CESUR","CESİM","CEVAHİR ÇIKMAZI","CEVVAL","CEVİZ","CEYHAN ÇIKMAZI","CEYHUN","CEZMİ","DOLAPDERE","FATİH SULTAN MEHMET","FIRTINA","FİGEN","GAZEL","GAZİ","GAZİ MUSTAFA KEMAL","GECE ÇIKMAZI","ISTIRANCA KALE ÇIKMAZI","KIRMIZI ÇEŞME","KIRMIZIGÜL","LALEGÜL","MARMARA","PAZAR","PEKMEZ DERESİ","REYHAN","RUHSAR","SARIÇİÇEK","SEMAVİ","TEFEKKÜR","VADİ","YEGANE","ÖZTUNA","ÜRKMEZ"],"ÖRENCİK":["ACEM ÇIKMAZI","AKARSU","AKSOY","AKSU","AKSÖĞÜT","ATİK ÇIKMAZI","BİLGİLİ ÇIKMAZI","CEVİZLER","DAR","FIRAT","GALİP","GÖKÇE ÇIKMAZI","GÜLİZAR","KARACAKÖY","KAVAK","KIREVLERİ ÇIKMAZI","KIVANÇ ÇIKMAZI","KIVILCIM ÇIKMAZI","KIYMET","KIZILCIK ÇIKMAZI","KIZILDAĞ ÇIKMAZI","KIZILÇAM ÇIKMAZI","KOCATEPE","KOLAYLI","KONAK","KONAKTEPE ÇIKMAZI","KONUK","KONURALP ÇIKMAZI","KONUT","KORDON","KORKUT","KOÇ ÇIKMAZI","KİBAR","KİLİM ÇIKMAZI","MAZHAR","MORGÜL","SARAL ÇIKMAZI","SERENGÜL","SEÇKİN","TEPEBAŞI","YAZICI","YERYÜZÜ","ÇAKMAK","ÇAM","ÖRENCİK","ŞEHİT MUSTAFA ALTINAN"],"KARACAKÖY MERKEZ":["AKYURT","ALADAĞ","ANI","ARKADAŞ","ASIR","ASLI","ASİYE","AY","AÇELYA ÇIKMAZI","AŞİYAN","BABACAN","BAKIRCI","BALLI","BEKO EVLERİ","BERNA","COŞAR ÇIKMAZI","COŞKUN ÇIKMAZI","CUMA","CÖMERT","CÜNEYT","CİHANGÜL","CİHANŞAH","CİVAN","CİVELEK ÇIKMAZI","DOKTORLAR SİTESİ ÇIKMAZI","DR. CELALETTİN ÜNLÜTÜRK","DİLAY ÇIKMAZI","DİLBER","ELDEMİR ÇIKMAZI","ELMALI","EMEK","FERAH ÇIKMAZI","GÜLDESTE","HAFIZ EFENDİ","HANIMELİ","HAYAT","HAŞİM HOCA","HUZUR","HİSAR","KAHRAMAN ÇIKMAZI","KANARYA","KARACA","KARACA AHMETPAŞA","KARACAKÖY","KARATEPE ÇIKMAZI","KULELİ","KÜLTÜR","MOR SALKIM","MUHACİR","MUSTAFA KEMALPAŞA","NARİN","NEŞELİ","OSMANBEY","PAŞA BAYIRI","PEKER","PROF. DR. TANSU ÇİLLER","PİRİ REİS","REHBER ÇIKMAZI","RUMELİLER ÇIKMAZI","RÜŞTÜ","SADAKAT","SEFER","SERÇE","SIHHAT","SIRA MEŞELER ÇIKMAZI","SIRDAŞ ÇIKMAZI","SONBAHAR","SULTAN FATİH","TAHA","TAŞLI TARLA","ULUCAN","VEDA ÇIKMAZI","YADİGAR","YAREN","YAYLA","YİĞİT","ZEYBEK","ZÜMRE ÇIKMAZI","ÇAKIL ÇIKMAZI","ÇAKIR ÇIKMAZI","ÇALDIRAN","ÇALIKUŞU","ÇALIŞ ÇIKMAZI","ÇAMLIBEL","ÇAMLIDERE","ÇAĞ ÇIKMAZI","ÇAĞDAŞ","ÇAĞLAR","ÇAĞLAYAN","ÇIRÇIR","ÜSTAD ÇIKMAZI","İZZET CİNSER","ŞAHİN ÇIKMAZI","ŞEN","ŞEREF","ŞERİFE ACAR"],"İHSANİYE":["ADEM","AKAY","AKİK","ASENA","BAHADIR","BALAMİR","BAŞKÖY ÇIKMAZI","BEKİRLİ","BENT ÇIKMAZI","BEYPINARLAR","BOZYİĞİT","BUCAK","CAMİ ALTI","CAMİ ARKASI","DESTEGÜL","DÜĞÜN SALONU","EDİRNE","GAZİ MUSTAFA KEMALPAŞA","HALİTPAŞA","HARUN ÇIKMAZI","HARİKA ÇIKMAZI","HARİTA ÇIKMAZI","HASGÜL ÇIKMAZI","HASKÖY ÇIKMAZI","HASRET ÇIKMAZI","HASTÜRK ÇIKMAZI","HATEM","HATIRA","HAVADAR","HAVUZ","HAYRAN","HAYRAT","HAZAR ÇIKMAZI","HAŞMET ÇIKMAZI","HECE","HEKİM","HEMŞİRE","HERCAİ ÇIKMAZI","HİLAL","KUPA ÇIKMAZI","KÜÇÜKBEY","NİLÜFER ÇIKMAZI","PALMİYE","PARADİSE","PINAR","PINARCA","REFET ÇIKMAZI","RIZA ÇIKMAZI","SARILALE ÇIKMAZI","SAĞLIK OCAĞI","SEBİL","SOHBET ÇIKMAZI","TEPE","VAKKAS","YASEMİN","YENİBAHAR ÇIKMAZI","YILDIZ","ZAMBAK","İHSAN AKDOĞAN","İLKBAHAR ÇIKMAZI","İSTANBUL"],"NAKKAŞ":["ALACA","ALİ RIZA EFENDİ","AYŞULE","BABA NAKKAŞ","BARIŞ","COŞKUNDERE","DERİNDERE","DESEN","ESKİCİ BABA","EYÜP PEHLİVAN","GÜNDOĞUŞU","HACI TEVFİK","HADIMKÖY-NAKKAŞ YOLU","HARMANLIKLAR","HÜRREM","KOŞUYOLU","MAHYACI","MASLAK","MÜHENDİS","NAKKAŞ","NARLI","OTLUK","PAŞAÇAYIRI","RÜYA","SADIK ONBAŞI","TEKİN","VURAL","YAZLIK","ZEYREK","ÇANGIR","ÇARŞI","ÇETİNER","ÖRENBAYIRI"],"ÇİFTLİKKÖY":["AKADEMİ","AKAĞAÇ","AKÇE","AKŞAMSEFASI","ALTIN","ALTINEL","ARİF","ATALAY ÇIKMAZI","AYCAN","BAHRİYELİ ÇIKMAZI","BAĞDAGÜL","BAŞPINAR","BAŞÖĞRETMEN","BOZTEPE","BOĞAZ","CEVHER","DAL","DALKILIÇ","DALYAN ÇIKMAZI","DAMAT","DAMLA","DAVET","DAĞ","DAĞHAN","DEFTERDAR","DEHA ÇIKMAZI","DEHLİZ","DELFİN","DEM","DEMİRCAN","DEMİRKAPI","DEMİRKAYA","DEMİRYOLU","DEMİRÖZ","DENGE","DENİZHAN","DENİZKIZI","DENİZLİ","DERECİK ÇIKMAZI","DEREN","DERMAN","DEĞER ÇIKMAZI","DEĞİRMENDERE","DURAN","DURMAZ","DÜNDAR","DÜŞ","GÜLDALI","IHLAMUR","KARAÇAM","KEMAL ATATÜRK","NEZİH","NİDA","OSMANLI","RUŞEN","RÜZGARGÜLÜ","SAĞLAM","SERÇELER ÇIKMAZI","SUDE","SULTAN FATİH","SULTAN SÜLEYMAN","SÖĞÜT","VAKAR","VARDAR","VARLIK","VEFA","YAPRAK","YEKPARE ÇIKMAZI","YEŞİL","ZEREN","ÇAPA","ÇARDAK","ÇARŞIBAŞI ÇIKMAZI","ÇATALDERE ÇIKMAZI","ÇATI","ÇAVDAR","ÇAYIRBAŞI","ÇEKMECE ÇIKMAZI","ÇEKİRDEK ÇIKMAZI","ÇELEBİ ÇIKMAZI","ÇELEN","ÇELİKEL","ÇEMBERLİTAŞ","ÇEMENZAR","ÇENGEL","ÇERKEZ","ÇERİ ÇIKMAZI","ÇEVRE","ÇEVİK","ÇINGIRAK","ÇOBAN","ÇORLUK","ÇUBUK","ÇÖMLEKÇİ ÇIKMAZI","ÇÖZÜM ÇIKMAZI","ÇİLLER","ÇİLİNGİR","ÇİSİL ÇIKMAZI","ÇİTLEMBİK","ÖZÜDOĞRU","ŞAŞMAZ","ŞÖLEN"],"AKALAN":["AKÇAY","ALTAYLI ÇIKMAZI","AYAZMA ÇEŞME","CAHİD","DEMOKRASİ","DERVİŞ","DİRAYET","FINDIK","FLORYA ÇIKMAZI","FİKRET ÇIKMAZI","FİKİR ÇIKMAZI","FİLYOS ÇIKMAZI","FİRUZE ÇIKMAZI","GÖÇMEN ÇIKMAZI","HARMANÜSTÜ","KARAÇUKUR ÇIKMAZI","MUSTAFA KEMAL","OCAKLAR","YARDIM","YEDİVEREN","ÇIRA","ÖZDENİZ","İSTANBUL","İSTİKLAL"],"KIZILCAALİ":["BAŞKOMUTAN ATATÜRK","ESKİ EDİRNE ASFALTI","GÜLFİDAN","GÜRBÜZ 1.","GÜZÜN ÇIKMAZI","HALK","KARAKAVAK ÇIKMAZI","KARAKAYA","KARAKOÇAN ÇIKMAZI","KARAKUŞ","KARAYEL ÇIKMAZI","KARBEYAZ ÇIKMAZI","KARDEŞ","KARINCA ÇIKMAZI","KASAP ÇIKMAZI","NURHAYAT ÇIKMAZI","ORKİDE","PAMUK","SAMET","TİTİZ ÇIKMAZI","YEKTA"],"OKLALI":["23 NİSAN","AKKAYA","BERKANT","DİLEK ÇIKMAZI","ESKİ EDİRNE ASFALTI","HAKEMLER","KARÇİÇEĞİ","KASIRGA ÇIKMAZI","KASİDE ÇIKMAZI","KATMER ÇIKMAZI","KATRE ÇIKMAZI","KATİP","KAVUN ÇIKMAZI","KAYAPINAR","KAYGISIZ ÇIKMAZI","KAYISI","KAYNAK ÇIKMAZI","KAYYUM","KAZAN","KAŞIKÇI ÇIKMAZI","KAŞMİR ÇIKMAZI","KAŞİF","KEHRİBAR","KEKİK ÇIKMAZI","KELEBEK","KELKİT","KENAN","KEPEZ","KEREM ÇIKMAZI","KERMES ÇIKMAZI","KERVAN ÇIKMAZI","KERİM ÇIKMAZI","KETEN ÇIKMAZI","KEVSER ÇIKMAZI","KUŞLAR YAYLASI","KÖRFEZ","KÖSE ÇIKMAZI","KÜPTEPE","NİHAL","SERCAN","SEVAL","TEPECİK","TOMRUK ÇIKMAZI","TRAFO ÇIKMAZI","TUĞRA ÇIKMAZI","YOL ALTI","ÖZELLER","İMREN","ŞAHİNLER"],"KALFA":["AKYILDIZ","AYCİHAN","BAĞLARBAŞI ÇIKMAZI","BAŞAKKÖY","BERK","DAĞYENİCE","EMSAL","EROĞLU","ESENGÜL","GARİPLER ÇIKMAZI","HOŞGÖRÜ ÇIKMAZI","HOŞNUT ÇIKMAZI","HOŞSEDA","HUDUT","HİCRAN ÇIKMAZI","HİKMET ÇIKMAZI","HİTİT ÇIKMAZI","KARACAKÖY","KARİYE ÇIKMAZI","KORU ÇIKMAZI","KUŞTEPE","MENEVİŞ","MEZARLIK","NESRİN ÇIKMAZI","ORTANCA ÇIKMAZI","OSMANLI","RAHMAN","SADEGÜL","SİDRE ÇIKMAZI","TÜRBE","YONCA","ÇAMÖZÜ","ÜZÜM","ŞAMDAN"],"GÜMÜŞPINAR":["ATASOY ÇIKMAZI","AYDINLIK","AYVALI","AŞKIN","BESTEGÜL ÇIKMAZI","BOZYİĞİT","BİLLUR","DOKUZEVLER","DUYARLI ÇIKMAZI","EDALI","ESTERGON","GÜLDEN ÇIKMAZI","GÜMÜŞ","GÜNEŞ","HALİS","HAMZA","HAMİDİYE ÇIKMAZI","HAMİT","HAMİYET ÇIKMAZI","KÖY KONAĞI","LİMONLU","RABİA","RAZGIRAT","SALKIM ÇIKMAZI","TEKİRDAĞ","TÜMSEK","ULUBATLI","VAKİT ÇIKMAZI","YELPAZE","YUDUM ÇIKMAZI","ZİVER","ÖNDER ATATÜRK","ÖZYURT ÇIKMAZI","ŞEFFAF","ŞÜHEDA","ŞİMŞEK"],"KARAMANDERE":["AKBAŞ","KARACA AHMETPAŞA","KARATEPE ÇIKMAZI","MÜGE","MÜJDE ÇIKMAZI","MÜJGAN","MÜLAYİM","MÜLK","MÜMİN ÇIKMAZI","MÜNİR","MÜRVER","MÜRŞİT ÇIKMAZI","MÜSLİM ÇIKMAZI","MÜSTESNA","NAKIŞ ÇIKMAZI","NALAN ÇIKMAZI"],"BELGRAT":["AKAĞAÇ","BİRİCİK","MERVE","MERYEM ÇIKMAZI","MESKEN","MESUT","MESİRE","METANET","METE","METEHAN","MEVLÜT","MEVSİM","MEŞALE ÇIKMAZI","MISIR","MISRA","MIZRAK","MİHRAÇ","MİĞFER ÇIKMAZI","NİDA","SULTAN FATİH","SİMGE","VARLIK","ÇAVDAR","ÇİLİNGİR"],"HİSARBEYLİ":["ACIÇEŞME","EĞİTMEN","HANDE","HANDEGÜL ÇIKMAZI","HANYERİ","HANZADE","HARDAL","KARACAKÖY","KARADAĞ","KARAKARTAL","PELİN","SÖNMEZ","ŞEHİT MUSTAFA ALTINAN"],"BAŞAK":["AKYÜREK ÇIKMAZI","ATANUR ÇIKMAZI","BAL ÇIKMAZI","BAŞÖĞRETMEN","BEYAZ AKASYA ÇIKMAZI","CEVHER","DEMİR","ESKİ DEĞİRMEN ÇIKMAZI","ESKİCİ ÇIKMAZI","GARDENYA ÇIKMAZI","GENİŞ","GERÇEK ÇIKMAZI","KARACAKÖY","KARADUT","OSMANLI","SANTRAL","SULTAN SÜLEYMAN","TORLUK","ÇİÇEK"],"YAYLACIK":["BERKAY ÇIKMAZI","BONCUK","BİNKILIÇ","BİRSİN ÇIKMAZI","BİTKİ","REZENE","YAĞIZ ÇIKMAZI"],"CELEPKÖY":["MİKAİL ÇIKMAZI","MİMAR","MİMOZA ÇIKMAZI","MİNARE","MİNE ÇIKMAZI","MİNYATÜR","MİRALAY","MİRCAN","RESİM ÇIKMAZI","ŞEHİT MUSTAFA ALTINAN"],"YAZLIK":["BAŞOĞLU","BORA","BOTANİK","BOZ","BOZDAĞ ÇIKMAZI","BOZDOĞAN","BOZKAYA","BOZKIR","DOĞANYOL","KORDON","YETKİN"],"ORMANLI":["ACIBADEM","BOĞAÇHAN","BİROL","KARACAKÖY","KIŞ","KUMLUK","NAMIK","NAMLI","NAMZET","NASİP","NAZ","NAZAR","NAZDAR","NAZENDE","NAZLI","NAZLICAN","NAZİF","NAZİK ÇIKMAZI","NAZİLLİ ÇIKMAZI","NAZİRE ÇIKMAZI","SANAYİ","YAYLACIK"],"FERHATPAŞA SB":["AKASYA","ALAÇAM","ALİ RIZA EFENDİ","ATATÜRK","AÇELYA","BEGONYA","DEFNE","ERGUVAN","FULYA","GONCA","HANIMELİ","IHLAMUR","KARDELEN","KÖKNAR","LADİN","LALE","LEYLAK","MANOLYA","MENEKŞE","NİLÜFER","ORTANCA","SELVİ","SÜMBÜL","YASEMİN","ZAMBAK","ÇINAR","ÇİĞDEM"]}