{"YENİ":["41.","42.","43.","44.","45.","46.","47.","48.","49.","50.","51.","52.","53.","54.","55.","56.","57.","58.","59.","74.","CELAL DOĞAN","CEVAHİR","CUMHURİYET","CUMHURİYET1","DURSUN ÖZÜN","ESEN1","GİRNE","HOZAT İSİMSİZ 201","HÜSNİYE ANA","KOZMAN","MEHMET DOĞAN","NİHAT SALTIK","SAPİK","ŞEHİT ALİ HAYDAR SABAN"],"GÖKÇEN-YEŞİLSEGEDİK":["GÖKÇEN YEŞİLSEGEDİK"],"SEGEDİK-KARAMANSEGEDİK":["SEGEDİK KARAMANSEGEDİK"],"AŞAĞI KARDELEN":["AŞAĞI KARDELEN"],"YEŞİLYURT":["YEŞİLYURT"],"BAŞATLI(DOLUÇEŞME)":["BAŞATLI DOLUÇEŞME"],"KÖYÜN KENDİSİ":["KÖYÜN KENDİSİ"],"BALOLAR":["BALOLAR"],"FİKRİPAŞA":["44.","71.","72.","73.","74.","75.","ALP","AŞAĞI ÇARŞI","BAHÇELER","BAYIR","CAMİİ","CUMHURİYET1","DOLAMAÇ","DURSUN ÖZÜN","EMRELER","ESEN1","GÖZE","GÖZELER","HAMAM","HASAN ERDOĞAN","HÜSNİYE ANA","NİHAT SALTIK","YÜKSEK","ÇAĞLA","ÇIKMAZ","ÖMER EFENDİ","ŞEHİT ALİ HAYDAR SABAN"],"DİYAP AĞA":["1.","2.","4.","5.","6.","7.","8.","AŞAĞI ÇARŞI","BAHÇELER","CUMHURİYET","CUMHURİYET1","DAR","FUAT YALIN","HIDIR YAVUZ","HOZAT İSİMSİZ 101","HOZAT İSİMSİZ 102","HOZAT İSİMSİZ 103","HOZAT İSİMSİZ 105","HOZAT İSİMSİZ 106","HOZAT İSİMSİZ 107","HOZAT İSİMSİZ 108","HOZAT İSİMSİZ 109","HOZAT İSİMSİZ 110","HOZAT İSİMSİZ 111","HOZAT İSİMSİZ 113","HOZAT İSİMSİZ 114","HOZAT İSİMSİZ 115","KOZMAN","MUSTAFA EKREM TÜZEMEN","SALİH ZEKİ TUNCER","SERKAN DOĞAN","SÜLEYMAN KAHRAMAN","TÜNEL","YOĞUN TOPRAK","ÖMER EFENDİ","ÖZGÜRLÜK","İHSAN HIDIR TURGUT"],"KÖPRÜBAŞI":["2 TEMMUZ","21.","22.","23.","24.","25.","26.","27.","28.","29.","30.","DEĞİRMEN","EMEK","GEÇİT","GÖZELER","KAZIM KOYUNCU","KAZIM KOYUNCU 1.","KAZIM KOYUNCU 2.","KAZIM KOYUNCU 3.","KAZIM KOYUNCU 4.","KAZIM KOYUNCU 5.","TANER YOLU","TANER YOLU 1."],"KIZIL KOM":["KIZIL KOM"],"SORPİYAN":["SORPİYAN"],"ÇAM YAZI":["ÇAM YAZI"],"BOYALI":["BOYALI"],"NİŞANGAH":["NİŞANGAH"],"YOĞUN TOPRAK":["YOĞUN TOPRAK"],"BULGURLU":["BULGURLU"],"BILANIK":["BILANIK"],"KÜÇÜK DALÖREN":["AKBULUT","KÜÇÜK DALÖREN"],"AKBULUT":["AKBULUT"],"ÇAKMAKLI":["ÇAKMAKLI"],"FARUKLAR":["FARUKLAR"],"MERECİK":["MERECİK"],"AKPINAR":["AKPINAR"],"ÖDEMİŞ":["ÖDEMİŞ"],"POTİN":["POTİN"],"KALANKOZ":["KALANKOZ"],"YAZI":["YAZI"],"GÜLENLER":["GÜLENLER"],"DELİKTAŞ":["DELİKTAŞ"],"ERENLER":["ERENLER"],"SÜTLÜCE":["SÜTLÜCE"],"MERK":["MERK"],"SEYİT MEMETLER":["SEYİT MEMETLER"],"YORGANLI":["YORGANLI"],"KAYABAĞI":["KAYABAĞI"],"MEŞEDİBİ":["MEŞEDİBİ"],"İBRAHİM TANER":["İBRAHİM TANER"],"DARIKOLU":["DARIKOLU"],"AŞAĞI BUZLUPINAR":["AŞAĞI BUZLUPINAR"],"VENK":["VENK"],"MEŞELİ":["MEŞELİK"],"ÜZÜMLÜ":["ÜZÜMLÜ"],"SALKIMLI":["SALKIMLI"],"HOPAĞAÇ":["HOPAĞAÇ","ÜZÜMLÜ"],"KURUKAFALAR":["KURUKAFALAR"],"KÜLÜNK":["KÜLÜNK"],"UZUNÇAYIR":["UZUNÇAYIR"],"HALİLAĞA":["HALİLAĞA"],"HIDIRDAMI":["HIDIRDAMI"],"HADİŞAR-BAYRAM":["HADİŞAR BAYRAM"],"KARATAŞ":["KARATAŞ"],"BEZAVUT":["BEZAVUT"],"GÖZEREK":["GÖZEREK"],"AĞMEZRA":["AĞMEZRA"],"KİNZİR":["KİNZİR"],"KARSEL":["KARSEL"],"BİLİKAN":["BİLİKAN"],"ZİYAL":["ZİYAL"],"GÜMÜŞSUYU":["GÜMÜŞSUYU"],"KUZULUK":["KUZULUK"],"AKVEYSİ":["AKVEYSİ"],"AKÖREN":["AKÖREN"],"AKSEKİ":["AKSEKİ"],"AMAÇLI":["AMAÇLI"],"DERİNDERE":["DERİNDERE"],"IŞIKLAR":["IŞIKLAR"],"KÖYBAŞI":["KÖYBAŞI"],"MAŞA":["MAŞA"],"AĞIRBAŞAK":["AĞIRBAŞAK"],"ESENLİ":["ESENLİ"],"DİKENLİ":["DİKENLİ"]}