{"ÜZÜMBAĞI":["SEYRANBAĞI","SİVRİ ALTI","VERENBAĞI","ÇAMLIK","ÇAMLIK-","ÇILDIR","ÜZÜMBAĞI MERKEZ"],"CANKURTARAN":["CANKURTARAN"],"ELMALI":["AFET EVLER/1","AFET EVLER/10","AFET EVLER/11","AFET EVLER/12","AFET EVLER/14","AFET EVLER/2","AFET EVLER/3","AFET EVLER/4","AFET EVLER/7","AFET EVLER/8","AFET EVLER/9","AFET EVLERİ-","BAĞLAR","ELMALI","ELMALI.","ELMALI/1","ELMALI/2","ELMALI/3","ELMALI/4","ELMALI/5","ELMALI/6","ELMALI/7","ULUBEL MERKEZ","ÜZÜMLÜK"],"MADENKÖPRÜBAŞI":["BAHÇECİK","BAYBURT","CEVİZLİ","KAĞARİK","KUZULUK","MADEN","MADEN/1","MADENKÖPRÜBAŞI","MEYDANLI","SELAHATTİN TOPUZ-","YENİ","YENİ1","ÇATAK","ÇAYDERE","İSPİR","İSPİR/1","İSPİR/2"],"GÜLLÜBAĞ":["GÜLLÜBAĞ"],"İKİSU":["GÜLHAS","İKİSU"],"AŞAĞI ÖZBAĞ":["AŞAĞI ÖZBAĞ MERKEZ","AŞAĞI ÖZBAĞ MERKEZ /3","AŞAĞI ÖZBAĞ MERKEZ /4","AŞAĞI ÖZBAĞ MERKEZ /6","AŞAĞI ÖZBAĞ MERKEZ 5","AŞAĞI ÖZBAĞ MERKEZ 8","AŞAĞI ÖZBAĞ MERKEZ/1","AŞAĞI ÖZBAĞ MERKEZ/7","BAĞLARBAŞI","BAĞLARBAŞI/1","BAĞLARBAŞI/2","BAĞLARBAŞI/3","GAZİLER","GAZİLER/1","KÖPRÜBAŞI","YENİYOL"],"ÇİÇEKLİ":["ARMUTLU","HALİLPAŞA","ÇİÇEKLİ"],"GAZİLER":["GAZİLER","GAZİLER MERKEZ","GAZİLER/1","GAZİLER1","GAZİLER2","GAZİLER3","GAZİLER4"],"BAŞKÖY":["BAHÇELİ","BALLI","BAŞ","GÜLTEPE","KAŞIKLI","ORTA2","SÜTLÜCE","YELESER","ÇERMİK","ÇİÇEKLİ1"],"ÇAMLICA":["ÇAMLICA"],"BOZAN":["BOZAN"],"ALACABÜK":["ALACABÜK MERKEZ","GÜNEY B.M","KAZANCIK","YENI","ZEYREK"],"KARAKAMIŞ":["KARAKAMIŞ","SARIÇAY"],"PETEKLİ":["BİLİNMEYEN1","PETEKLİ"],"ARDIÇLI":["ARDIÇLI"],"YEŞİLTEPE":["YEŞİLTEPE"],"AKGÜNEY":["AKGÜNEY MERKEZ","ÇAYDERE"],"KARAKAYA":["KARAKAYA"],"ÇAMLIKAYA":["ARABLI YOLU","ARAPLI-","AĞAGİL-","AĞAP-","AŞAĞI","AŞAĞI (MERKEZ)","AŞGİK-","BALIKLI-","BAYRAKTAR","BİLİNMEYEN 2","BİLİNMEYEN 3","BİLİNMEYEN 5","BİLİNMEYEN 7","BİLİNMEYEN2","CAMİİ BOYNU","CEBECİLİ","COŞ-","DABAKLI","DERE-","DÜZTEPE","EMİNELİ-","ENSE SIRT-","ERAHMUT","ERESEL-","ESKİ KÖY-","ESKİVAN-","EŞİĞİN SIRT-","GAANS-","GAHNUT-","GATES-","GAÇ","GÖÇ MERKEZ","GÜRCÜLÜ-","GÜRCÜOĞLU","GÜRCÜOĞLU-","HALVER-","HANZAR","HANZARLI-","HINZIRAT-","HOROSKO-","IŞKINLININ MANGUT","KARZER-","KAÇGEÇ-","KUZ-","MERKEZ (YAVUZLAR)","MERKEZZ","MUTİGİL-","ORTA","ORTASIRT-","PALOŞLU","PETEKLİ-","PIÇAKÇI","SAVAKLI-","SOLUKLU-","SOSTANLI","TAUNS-","TELLİGİLİN MANGUT","TOSGOR-","VANK","ZINGİK-","ÇAMLIKAYA","ÇAMLIKAYA1","ÇAVUŞLAR","ÇERMANS","ÖTE MANGUT-","İMAMGİL-","ŞAVLAK-"],"YUNUSKÖY":["YUNUSKÖY"],"ATÜRKÜTEN":["ATÜRKÜTEN MERKEZ"],"DEVEDAĞI":["ARAKÖY MERKEZ2","ARAKÖY MERKEZ3","ARAKÖY MERKEZ4","DEVEDAĞI MERKEZ","MEZRA"],"GÜLHAS":["GAZİLER","GÜLHAS","GÜLHAS MERKEZ","GÜLHAS/2","GÜLHAS/3","GÜLHAS/4","GÜLHAS/5","GÜLHAS/6","GÜLHAS/7","GÜLHAS/8","GÜLHAS/9"],"ÇAYIRBAŞI":["ÇAYIRBAŞI"],"ÇATAKKAYA":["DAYİHİSAR-","ZORNİ","ÇATAKKAYA MERKEZ"],"GÜNDOĞDU":["GÜNDOĞDU","GÜNDOĞDU1","GÜNDOĞDU2","GÜNDOĞDU3","GÜNDOĞDU4"],"KÜMETAŞ":["KÜMETAŞ","PINARLI"],"PINARLI":["AKTAŞ1","PINARLI","PINARLI 1","PINARLI 2","PINARLI 4"],"AKTAŞ":["AKTAŞ","AKTAŞ1","BOSTANCI","GÜNDOĞDU2"],"YEDİGÖZE":["YEDİGÖZE","YEDİGÖZE/1","YEDİGÖZE/2","YEDİGÖZE/3","YEDİGÖZE/4","YEDİGÖZE/5"],"DEMİRBİLEK":["DEMİRBİLEK"],"AKPINAR":["AKPINAR"],"MÜLKKÖY":["MÜLKKÖY"],"DEMİRKAYA":["DEMİRKAYA","TAŞBAŞI MERKEZ"],"KARASEYDİ":["KARASEYDİ"],"KIZILHASAN":["KIZILHASAN"],"SANDIKLI":["SANDIKLI MERKEZ"],"TAŞBAŞI":["ORTAKÖY","TAŞBAŞI MERKEZ"],"BADEMLİ":["BADEMLİ"],"GÜNEY":["GÜNEY B.M","MÜLKKÖY"],"GÖLYURT":["GÖLYURT"],"SIRAKONAK":["AKBAŞ","ALTINTAŞ","ARAKİ","BALCI-","CEBRUNKAS-","CEVİZLİ-","CÜCEBAĞI","DALLICA","GÜNEŞLİ","KARAKALE MERKEZ","KÖY-","KİSAR-","MASURAS","MASURUS-","OCAKLI","SOĞUCAK","SOĞUCAK/1","SUNGURLU","TAŞBAŞI","YONCALI","YUMURCA","YUMURCA-","ÇAVUŞLAR1","ÜÇKARDEŞ","İNCİLİ"],"MESCİTLİ":["MESCİTLİ"],"LEYLEKKÖY":["LEYLEKKÖY"],"TAŞLICA":["MERKEZZ","TAŞLICA"],"ÖZLÜCE":["ÖZLÜCE"],"TEKPINAR":["AKKOYUN","TEKPINAR MERKEZ","ÖZTOPRAK"],"YILDIZTEPE":["BİRİCK","YILDIZTEPE"],"BOSTANCI":["AKTAŞ","BOSTANCI"],"IRMAKKÖY":["ARMUTLU","DEĞİRMENLİ","IRMAK MERKEZ","TOSUNLU"],"KAYNAKBAŞI":["KAYNAKBAŞI"],"AKSEKİ":["AKSEKİ"],"ULUTAŞ":["ULUTAŞ","ULUTAŞ-"],"DEĞİRMENDERE":["DEĞİRMENDERE"],"KIRIK":["KIRIK"],"ARAKÖY":["ARAKÖY MERKEZ","ARAKÖY MERKEZ1","ARAKÖY MERKEZ2","ARAKÖY MERKEZ3","ARAKÖY MERKEZ4"],"KAVAKLI":["1.KAVAKLI","HALİLPAŞA","KAVAKLI 2","ÇAMLICA"],"GEÇİTAĞZI":["GEÇİTAĞZI","GEÇİTAĞZI MERKEZ","KARŞI","YUKARI"],"ŞENKÖY":["ŞENKÖY"],"KİRAZLI":["KİRAZLI","KİRAZLI/1","KİRAZLI/2"],"AVCIKÖY":["AVCIKÖY"],"ARMUTLU":["ARMUTLU"],"İNCESU":["İNCESU"],"ORTAKÖY":["ORTAKÖY"],"AŞAĞI FINDIKLI":["AŞAĞI FINDIKLI"],"BAŞÇEŞME":["BAŞÇEŞME","SOĞUKSU"],"KARAHAN":["KARAHAN"],"AKSU":["BİRİCK","DEREAĞZI","KADIBAĞI","KUŞDİLİ","KÖKLÜCE","MEZRA/11","OTLUCA","YILDIZTEPE","ÇAKMAKLI MERKEZ","ŞENTEPE"],"NUMANPAŞA":["AKKOYUN","GODLAR","NUMANPAŞA"],"YUKARI FINDIKLI":["YUKARI FINDIKLI"],"İYİDERE":["İYİDERE"],"TEPECİK":["TEPECİK"],"YAĞLI":["CANKURTARAN","YAĞLI"],"BAŞPINAR":["BAŞPINAR","CANKURTARAN"],"ÖZTOPRAK":["AKKOYUN","TEKPINAR MERKEZ","ÖZTOPRAK"],"ULUBEL":["KAROR-","ULUBEL MERKEZ"],"MORYAYLA":["MORYAYLA"],"KARAKALE":["BAGLIK","KARAKALE MERKEZ"],"ÇAYIRÖZÜ":["ULUTAŞ","ÇAYIRÖZÜ"],"KÖPRÜKÖY":["1.KAVAKLI","AŞAĞI ÖZBAĞ MERKEZ/1","DERE-","DERE1","ELMADERE","ESKİKÖY","KARŞI/1","KUYULAR","KÖPRÜKÖY","SAMIŞLIK","ÇAMLICA"],"ZEYREK":["ZEYREK"],"DEĞİRMENLİ":["ARMUTLU","DEĞİRMENLİ","ÖZTOPRAK"],"YAYLACIK":["YAYLACIK","YAĞLI"],"KOÇ":["ARMUTLU","GÜNDOĞDU2","GÜNDOĞDU4","KOÇ","TOSUNLU"],"ÇAKMAKLI":["BAĞLAR-","ÇAKMAKLI MERKEZ","ÇAKMAKLI/1"],"DÜZKÖY":["DÜZKÖY"],"CİBALİ":["CİBALİ"],"YEDİGÖL":["YEDİGÖL MERKEZ","YOLBİLEN"],"AHLATLI":["AHLATLI MERKEZ"],"ORTAÖREN":["ORTAÖREN"],"BAHÇELİ":["BAHÇELİ","YEDİGÖZE"],"HALİLPAŞA":["HALİLPAŞA","PINARLI","PINARLI 4"],"DURUKÖY":["DURUKÖY"],"GÖÇKÖY":["GÖÇ BAĞLARI","GÖÇ MERKEZ"],"SOĞUKSU":["SOĞUKSU"],"YEŞİLYURT":["BAĞLAR/1","KUŞLU","YEŞİLYURT MERKEZ"],"YUKARI":["1. 25 ŞUBAT","1.ESENTEPE","1.ETAP TOKİ","1.GÜNEY","1.HASTANE","1.KAVAKLI AFET KONUTLARI","1.KIRMIZIBAYIR","1.ORTA","1.TAŞLICA-TEKPINAR AFET KONUTLARI","1.ÇORUH","1.ŞEHİTLİK","2. ETAP TOKİ AŞAĞI","2. ETAP TOKİ YUKARI","2.ESENTEPE","2.KAVAKLI AFET KONUTLARI","2.TAŞLICA-TEKPINAR AFET KONUTLARI","2.ŞEHİTLİK","25 ŞUBAT","3.ESENTEPE","3.KAVAKLI AFET KONUTLARI","3.TAŞLICA-TEKPINAR AFET KONUTLARI","4.ESENTEPE","ANAOKULU-GÜNEY","AYDIN","BERBER","CUMHURİYET","ESENTEPE","FATİH","GÜLLÜBAĞ","GÜNEY","HALİTPAŞA","HASTANE","KALE","KAVAKLI","KIRMIZIBAYIR","MALTEPE","OKULLAR-GÜNEY","TAŞLICA-TEKPINAR AFET KONUTLARI","YUKARI1","ÇARŞIBAŞI","ÇORUH","İSPİR TRAFO MERKEZİ","ŞEHİTLİK"],"KARŞIYAKA":["1.FATİH","1.KALE","1.KAVAKLI","1.ZİYA PAŞA","1.ÇİÇEKLİ","1.İNAYETİN OSMAN","1.İNÖNÜ","1.İZMİTLİ","1.ŞEHİT ABDULKERİM TURHAN","2.KALE","2.İNAYETİN OSMAN","2.İZMİTLİ","2.ŞEHİT ABDULKERİM TURHAN","25 ŞUBAT","3.ŞEHİT ABDULKERİM TURHAN","AHIRLAR BÖLGESİ","ATATÜRK","BİLİNMEYEN3","CUMHURİYET","FALGEDİĞİ","FATİH","FATİH-","GÜLLÜBAĞ","HALİLPAŞA-AHLATLI-AKSU AFET KONUTLARI","HÜKÜMET","KADIOĞLU","KALE","KÜMBET-","MEHMET CİMİLLİ","MENEMŞE","MUSTAFA ÇAVUŞ","MÜFTÜ BAŞKAPAN","SÖGÜTLÜDERE","YUKARI1","ZİYA PAŞA","ÇAMLICA","ÇİÇEKLİ","İNAYETİN OSMAN","İNÖNÜ","İNÖNÜ-","İZMİTLİ","ŞEHİT ABDULKERİM TURHAN"],"YUKARI ÖZBAĞ":["AŞAĞI ÖZBAĞ MERKEZ","BAĞLARBAŞI","BAĞLARBAŞI/3","GAZİLER","HASBAĞ","HASBAĞ/1","MERKEZ","MERKEZ/1","MERKEZ/2","YUKARI ÖZBAĞ"]}