{"KÜTÜKLÜYURT":["KÜTÜKLÜYURT"],"KÜRÜLLÜK":["KÜRÜLLÜK"],"ÇAMBAŞI":["ÇAMBAŞI"],"ÇAMAT":["ÇAMAT YAYLASI"],"İBRAHİM ALANI":["İBRAHİM ALANI YAYLASI"],"ÇIKRIKDÜZÜ":["ÇIKRIKDÜZÜ YAYLASI"],"CAMİ":["CAMİ","CAMİ MEVKİİ K.B"],"ALAN":["ALAN","ALAN YAYLASI","ELCİĞEZ ALANI YAYLASI"],"KAYALGİL":["KAYALGİL"],"GÜLLÜŞAH":["GÜLLÜŞAH"],"CAYRA":["AYANOS","BARAJ TATİL KÖYÜ","BARINAK","BAŞ MAH.","BELEDİYE","BÜK YOLU","CAMİ YOL ALTI","CAYRA MAHALLESİ","CUMHURİYET","GALİROS","MESLEK YÜKSEK OKULU","MUSTAFA DERESİ","ONNABA","SEVGİ YOLU","SİNOR","TOKİ AFET KONUTLARI","ZİYARET TEPESİ","ÇÖPLÜCE","ŞAHİNLER","ŞEHİT YUSUF YAKIŞIR","ŞINA"],"TEKNECÜK":["TEKNECÜK"],"KIZILLIK":["KIZILLIK K.B"],"SOĞUK OLUK":["SOĞUK OLUK K.B"],"ÇATALKAYA":["ÇATALKAYA"],"MERKEZ":["AKTAŞ MERKEZ K.B.","ARPACIK MERKEZ","BAĞLAMA MERKEZ","BEYTARLA MERKEZ MEVKİİ","EKİNCİLER MERKZ","EĞRİGÜNEY","GÖNDERE MERKEZ MEVKİİ","GÜRGENLİ MERKEZ","KARAAĞAÇ","KONACIK MERKEZ","KUŞLUK","MERKEZ K.B.","SAPMAZ MERKEZ MEVKİİ","TAŞLICA MERKEZ K.B.","YUKARIKARADERE MERKEZ MEVKİİ K.B.","ÜÇTAŞ MERKEZ MEVKİİ","ŞENDERE MERKEZ MEVKİİ KB."],"ANBARLI":["ANBARLI"],"PATIRYURDU":["PATIRYURDU"],"CAMİİ":["CAMİİ","CAMİİ MEVKİİ K.B."],"KARAAĞAÇ":["KARAAĞAÇ"],"ESELÜCE-KURUMADEN-KÖRÜKALANI-GÖNDERE":["ESELÜCE KURUMADEN KÖRÜKALANI GÖNDERE"],"SOĞUKOLUK":["SOĞUKOLUK"],"KUTLU":["KUTLU MEVKİİ"],"KANYAŞ":["KANYAŞ(AĞDAŞ) YAYLASI"],"İĞNESİBURNU":["İĞNESİBURNU"],"DERE OBA":["DEREOBA YAYLASI","KIRICAK YAYLASI"],"EMİNLİ":["EMİNLİ"],"AŞAĞI ULUKÖY":["3.","4.","4./1","ACIKLI","BELEDİYE","CABALİ","DEREYATAĞI","EYÜPOĞLU","EYÜPOĞLU/1","GÜVENDE","HANYANI","HASTANE","J. ER NEVZAT GÜL","PALIÇUKURU","SEYRANTEPE","TOKİ","TRANSİT","TRANSİT/1","TRANSİT/3","TRANSİT/4","ULUKÖY","ULUKÖY 2","ÇÖPLÜCE","ÖZKANLAR","ÖZKANLAR/1","ÖZKANLAR/2"],"CAMİ YANI":["ACIKLI","AHMATLI","BEKİRLİ","BOYALIK","EYÜPOĞLU","PAŞALI","YAVERLİ","ÇAĞALLI","ÇAĞALLI 1"],"KÖYİÇİ":["AHMATLI","BEDİRLİ","CAMİDÜZÜ"],"ORTAKÖY":["ACIKLI","AHMATLI","CAMİDÜZÜ","DEREYATAĞI","KELVANLI","KONUTLAR","OKULLAR","PAŞALI","ÇOBANLI","ŞEYHLİ"],"YUKARI ULUKÖY":["CAMİDÜZÜ","GÜZLEK MEVKİİ","KELVANLI","KIRAN","KONAKYANI","MÜFTÜGİL"],"KARAÇUKUR":["BÜYÜKOBA","CAMİ","DOLUNLU","EMİRLİ","ENGİRGE","KADI ÇAYIRI","KARAÇUKUR MEVKİİ","MANDIRA","SULAHLI","YALAKYURT","ÇORAK","İNCİRLİ"],"SÜME":["ACUKLU","ALANCUK","ALAÇAM","ARPAKÖY","AYANOS","AYVATLI","BALDIRAN","BAŞOBA1","CAMİ YOL ALTI","CAMİ YOL ÜSTÜ","CORAK","DAVUNLU","DEREAĞZI","DEĞİRMEN KARŞISI","DİKENLİ","ERİKBELİ","ERİKBELİ FINDICAK","ESKALA","FINDICAK","GERİŞ","KADIRGA","KALEBAŞI","KALEDİBİ","KARAGÖZLÜ","KARAKAYA","KAVAKLI","KAYADİBİ","KAZMADERE","KEFLİ","KIZILAĞAÇ","KÖYCEĞİZ","KÜÇÜKARPAKÖY","KÜÇÜKKÖY","KİREÇ DERESİ","MEHMET HOZANI","OKUL YANI","OLUK KIRANI","OĞUZ","PİNAS","SARIOĞULLARI","SEYİTALİ","SİNANLI","URUGUA","ÇAKMAKLAR","ÇALDERE","ÇATMA","ŞAHMELİK"],"ALT":["ALT"],"KIRAN":["KIRAN"],"KABADÜZ":["KABADÜZ"],"KÖKEÇ":["KÖKEÇ"],"KARŞI":["KARŞI","KARŞI MEVKİİ K.B."],"AŞAĞI":["AŞAĞI"],"ESKİYURT":["ESKİYURT"],"TAŞDİBİ":["TAŞDİBİ YAYLASI","YAYLALI TAŞDİBİ YAYLASI"],"ÇAKMAKKAYA":["ÇAKMAKKAYA"],"SARIÇ":["SARIÇ YAYLASI","SARIÇÇ"],"ORTA":["DEMİRCİLER ORTA","KIRGERİŞ ORTA MEVKİİ","ORTA"],"FINDICAK":["FINDICAK"],"NASRETTİN YAYLASI":["NASRETTİN YAYLASI"],"HAYATDERESİ":["HAYATDERESİ YAYLASI"],"KEPEZ":["KEPEZ"],"ATKOYU":["ATKOYU"],"KUZUGÖLÜ":["KUZUGÖLÜ","KUZUGÖLÜ YAYLASI"],"KEKRE":["KEKRE"],"KÖROĞ":["KÖROĞ"],"MELİKLİ":["ALTUNTAŞLAR","GÜZLEK MEVKİİ","KELVANLI","KONAKYANI","MELİKLİ","MÜFTÜGİL","ŞEYHLİ"],"OCAK":["OCAK"],"YENİ":["ARPACIK YENİ YAYLASI"],"GUGULE":["GUGULE"],"IMUKYURT":["IMUKYURT YAYLASI"],"BAŞÖVET":["BAŞÖVET MEVKİİ KB."],"CAMİİ YANI":["CAMİİ YANI MEVKİİ"],"KURUKIRAN":["KURUKIRAN"],"ÇAVUŞ KIRAN":["ÇAVUŞ KIRAN"],"DERE":["DERE","ÇAMEYİN YAYLASI"],"AYGERİŞ":["AYGEVİŞ"],"GÖCÜ MEREĞİ":["GÖCÜ MEREĞİ"],"KAKILLI":["KAKILLI"],"ALINCA":["ALINCA YAYLASI"],"KARALLI":["KARALLI"],"HEREKLİ":["HEREKLİ"],"KIRAN ÇEĞEL":["KIRAN ÇEĞEL YAYLASI"],"GÖLCEĞİZ":["GÖLCEĞİZ YAYLASI"],"KIZILTAŞ":["DALLİ","KIZILTAŞ"],"TAŞBOĞAZI":["TAŞBOĞAZI"],"BALIKLI":["BALIKLI YAYLASI"],"HARMANCIK":["HARMANCIK"],"YANIK MEREK":["YANIK MEREK"],"ÇOKMA":["ÇOKMA"],"PINAR GÖZÜ":["PINAR GÖZÜ"],"YONCALIK":["YONCALIK"],"HALİL BEY":["HALİL BEY YAYLASI"],"GÜVENDE":["GÜVENDE YAYLASI"],"ÇARDAK ALANI":["ÇARDAK ALANI YAYLASI"],"ALANTARLA":["ALANTARLA K.B."],"MEREK YANI":["MEREK YANI"],"ÖKSÜZ":["ÖKSÜZ"],"ALAN YAYLA":["KASNAK ALANI YAYLASI"],"ÇALALANI":["ÇALALANI YAYLASI"],"KUZ":["KIRGERİŞ ORTA MEVKİİ","KUZ"],"BÜYÜK ÇEĞEL":["BÜYÜK ÇEĞEL YAYLASI"],"MEMİŞLİ":["MEMİŞLİ"],"LANGAS":["LANGAS"],"DÜZ YAYLA":["DÜZ YAYLA"],"PİNTİ":["PİNTİ YAYLASI"],"ÜST":["ÜST","ÜST MEVKİİ","ÜST MEVKİİ K.B."],"SEVİNCEK":["SEVİNCEK"],"KIRIK":["KIRIK"],"DÜZLÜCE":["DÜZLÜCE MEVKİİ"],"AYKUTLU":["AYKUTLU"],"ÇÖPLÜCE":["ÇÖPLÜCE MEVKİİ"],"PINARBAŞI":["PINARBAŞI"],"ÜTÜK":["ÜTÜK"],"TUTLUCA":["TUTLUCA"],"KİRAZALANI":["KİRAZALANI"],"İSMİRLİ":["İSMİRLİ"],"HAYİN DERE":["HAYİNDERE"],"AŞAĞI ALAN":["AŞAĞI ALAN"],"KAVASTAMYANI":["KAVASTAMYANI"],"TEPEKÖY":["TEPEKÖY"],"YUKARI ALAN":["YUKARI ALAN"],"MURSAL":["MURSAL"],"DEREGÖZÜ":["DEREGÖZÜ"],"ÇATAK":["ÇATAK"],"DAĞTARLA-KARAAĞAÇ-KÖKBÜKÜ":["DAĞTARLA KARAAĞAÇ KÖKBÜKÜ"],"KIZILALİ ÜST":["KIZILALİ ÜST"],"TÜFEKÇİLİ":["TÜFEKÇİLİ"],"KÖRO-DELİKLİTAŞ-YAYLACIK":["KÖRO-DELİKLİTAŞ-YAYLACILIK"],"SULUÇAYIR":["SULUÇAYIR"],"ARALICAK":["ARALICAK YAYLASI"],"KUŞ ALANI":["KUŞ ALANI YAYLASI"],"ENGÖZÜ":["ENGÖZÜ"],"MASUL YURDU":["MASUL YURDU YAYLASI"],"İKİBACA":["İKİBACA"],"SULUCA":["SULUCA"],"TOHTAMUR":["TOHTAMUR"],"KABAYALAK":["KABAYALAK"],"KAVRAZ":["KAVRAZ"],"KIZILALİ ALT":["KIZILALİ ALT"],"KIZILÇUKUR":["KIZILÇUKUR"],"ÇARDAKYANI":["TAŞLICA"],"KİSELİCE":["KİSELİCE"],"YELBELEĞİ":["YELBELEĞİ"],"ÇETLİCE-CİNKAYASI":["ÇETLİCE CİNKAYASI"],"KÜÇÜKDERE":["KÜÇÜKDERE"],"SARITAŞ":["SARITAŞ YAYLASI"],"YEMİŞEN":["YEMİŞEN YAYLASI"],"KELEŞOĞLU":["KELEŞOĞLU"],"MALLICA":["MALLICA","MALLICA YAYLASI"],"ALACAİNEK":["ALACAİNEK YAYLASI"],"KÜÇÜK KÖYCEĞİZ":["KÜÇÜK KÖYCEĞİZ MEVKİİ KB."],"BÜYÜK KÖYCEĞİZ":["BÜYÜK KÖYCEĞİZ"],"MÜRÜTLÜ":["MÜRÜTLÜ"],"İMAT KIRANI":["İMAT KIRANI"],"İNCELİDÜZ":["İNCELİDÜZ MEVKİİ"],"BALİÇUKUR":["BALİÇUKUR"],"AKKÖY":["AKKÖY MEVKİİ K.B."],"CAMÖNÜ":["CAMÖNÜ-ÇAMİN YAYLASI"],"YAZICI OĞULLARI":["YAZICIOĞULLARI"],"YEHENCELİ":["YEHENCELİ"],"SIRGANLIK":["SIRGANLIK"],"EĞRİKAR":["EĞRİKAR YAYLASI"],"AYAZMANE":["AYAZMANA"],"DÜZ":["DÜZ"],"TOPRAKLIYURT":["TOPRAKLIYURT"],"BEŞİRALTI":["BEŞİRALTI"],"KARŞIKI":["KARŞIKİ"],"YUKARI-ORTA-KARŞI":["YUKARI ORTA KARŞI"],"DOĞUBA":["DOĞUBA"],"KIRICAK":["KIRICAK YAYLASI"],"KARABOYA":["KARABOYA YAYLASI"],"ERİK DERESİ":["ERİK DERESİ YAYLASI"],"MİNDİZLİ":["MİNDİZLİ"],"HOROZ":["HOROZ"],"BAYRAKALANI":["BAYRAKALANI"],"AVLEKA":["AVLEKA"],"HOCALİ":["HOCALİ"],"AKBABA":["AKBABA"],"GEVÜKLÜ":["DAĞDİBİ MERKEZ MEVKİİ K.B","GEVÜKLÜ"],"RAMAZANYURDU":["RAMAZANYURDU"],"DERİNDERE":["DERİNDERE"],"AYUTLU":["AYUTLU"],"APSA":["APSA"],"TÜRKMEN":["TÜRKMEN"],"BAŞ":["ALİSTRA YAYLASI","BAŞ","KALINÇAT YAYLASI","KAZIKBELİ YAYLASI"],"KOMANYURT":["BÜYÜK BARAK YAYLASI","KOMANYURT YAYLASI","KÜÇÜK BARAK YAYLASI"],"YILANLI":["YILANLI YAYLASI"],"HAPANDÜZÜ":["HAPANDÜZÜ"],"ERİCEK":["ERİCEK","ERİCEK MEVKİİ K.B."],"ÖKSÜZLÜ":["ÖKSÜZ"],"MEREKDERE":["MEREKDERE","TAMYANI"],"ÇORUHLU":["ÇORUHLU MEVKİİ"],"GÖLÖNÜ":["GÖLÖNÜ"],"YÜRÜMEZ":["YÜRÜMEZ"],"GÜNEY":["GÜNEY"],"KALEDÜZÜ":["KALEDÜZÜ"],"ÇARŞI":["ÇARŞI"],"ALDA DÜZÜ":["ALDA DÜZÜ"],"SOBATLI":["SOBATLI"],"SAZLIBÜK":["SAZLIBÜK MEVKİİ"],"YAYLA":["MEREKGÖZÜ","PAÇACI","YAYLA MEVKİİ K.B.","ÇAYIRAĞZI"],"SİCİMLİ":["SİCİMLİ"],"KARAHAMZALI":["KARAHAMZALI"],"KUŞLAĞANAĞZI":["KUŞLAĞANAĞZI"],"OKULYANI":["OKULYANI"],"TAŞBAŞI":["TAŞBAŞI YAYLASI"],"KÖPRÜBAŞI":["KÖPRÜBAŞI MEVKİİ"],"YENİÇERİ":["YENİÇERİ MEVKİİ"],"HACILI":["HACILI"],"DELMECE":["DELMECE YAYLASI"],"KODALI":["KODALI"],"YARAŞ":["YARAŞ YAYLASI K.B."],"ARMUTALANI":["ARMUTALANI MEVKİİ"]}