{"TEPEKUM":["1130 NOLU","1131 NOLU","1132 NOLU","1133 NOLU","1134 NOLU","1135 NOLU","1136 NOLU","1137 NOLU","1138 NOLU","1139 NOLU","1140 NOLU","1141 NOLU","1142 NOLU","1143 NOLU","1144 NOLU","1145 NOLU","1146 NOLU","1147 NOLU","1148 NOLU","1149 NOLU","1150 NOLU","1151 NOLU","1152 NOLU","1153 NOLU","1154 NOLU","1155 NOLU","1156 NOLU","1157 NOLU","1158 NOLU","1159 NOLU","1161 NOLU","1162 NOLU","1164 NOLU","1165 NOLU","1166 NOLU","1167 NOLU","1168 NOLU","1169 NOLU","1170 NOLU","1171 NOLU","1178 NOLU","1179 NOLU","ALPARSLAN TÜRKEŞ","ARI","BELGİN","BENT","BEYAZ","BEYHEKİM","CENGİZ","EMİR","HAZER","KARASU YOLU","KERKÜK","KOZA","KUMKÖY","MAHSUN","MEÇ","MİMAR SİNAN","PAZAR","SAKARYA","SAZ","SET ARKASI","SIRA","TIKIZ","TURAN","ÇİMEN","İRFAN","ŞANTİYE","ŞEHİT MEHMET NURİ KOCABIYIK","ŞEHİT SADULLAH BENDER"],"KARADERE":["ADAPAZARI KAYNARCA","ADAPAZARI KAYNARCA/12","ADAPAZARI KAYNARCA/20","ADAPAZARI KAYNARCA/3.","ADAPAZARI KAYNARCA/4.","ADAPAZARI KAYNARCA/5.","ADAPAZARI KAYNARCA/6","ELMALI","KAYNAK","KAYNAK/1","KAYNAK/2","KAYNAK/3","KAYNAK/4","KAYNAK/5","KAYNAK/6","KAYNARCA KANDIRA","KIRLANGIÇ","KIRLANGIÇ/1","MEŞE","MEŞE/1","MEŞE/2","MEŞE/3","MEŞE/4","MEŞE/5","SANDAL","SEZGİN","SEZGİN/1","SEZGİN/2"],"AKINCILAR":["10 NOLU","11 NOLU","12 NOLU","13 NOLU","14 NOLU","15 NOLU","18 NOLU","19 NOLU","2 NOLU","20 NOLU","21 NOLU","22 NOLU","23 NOLU","25 NOLU","5 NOLU","6 NOLU","7 NOLU","8 NOLU-","9 NOLU","ADNAN MENDERES","AKINCILAR","ARA","ARZU","BAHÇE","BERBER","BEREKET","BÜYÜK GEÇİT","DEĞİRMEN","EKİCİ","ELİF","HOROZLU","KESKİN","KOMŞU","KUŞ","MEYDAN","POLAT","SAKARYA","TATLI","YEŞİL","ÇEKER","ÇİLEK","ŞEHİT MURAT FATİH DİKTAŞ"],"SALMANLI":["ATILGAN","ILICA","ILICA/1","KANDIRA","KANDIRA/1","KANDIRA/2","KANDIRA/3","KANDIRA/4","KİLİM","OBA","OBA/1","OBA/2","OBA/3"],"YAĞCILAR":["1227 NOLU","1228 NOLU","1301 NOLU","1302 .","1303 NOLU","1304 NOLU","1305 NOLU","1306 NOLU","1308 NOLU","1311 NOLU","1312 NOLU","1313 NOLU","1314 NOLU","1315 NOLU","1316 NOLU","1317 NOLU","1318 NOLU","1319 NOLU","1320 NOLU","1321 NOLU","1322 NOLU","1323 NOLU","1324 NOLU","1325 NOLU","1326 NOLU","1327 NOLU","1328 NOLU","1329 NOLU","1330 NOLU","1331 NOLU","1332 NOLU","1333 NOLU","1334 NOLU","1335 NOLU","1336 NOLU","1337 NOLU","1338 NOLU","1339 NOLU","1340 NOLU","1341 NOLU","1342 NOLU","1343 NOLU","1344 NOLU","1345 NOLU","1346 NOLU","1347 NOLU","1348 NOLU","1349 NOLU","1350 NOLU","1351 NOLU","1352 NOLU","1353 NOLU","1354 NOLU","1355 NOLU","1357 NOLU","1358 NOLU","1359 NOLU","1360 NOLU","1361 NOLU","1362 NOLU","1363 NOLU","1364 NOLU","1365 NOLU","1366 NOLU","1367 NOLU","1368 NOLU","1369 NOLU","1370 NOLU","1371 NOLU","1372  NOLU","1373 NOLU","1374 NOLU","1375 NOLU","1376 NOLU","1377 NOLU","1378 NOLU","1379 NOLU","1380 NOLU","1381 NOLU","1382 NOLU","1383 NOLU","1384 NOLU","1385 NOLU","1386 NOLU","1387 NOLU","1388 NOLU","1389 NOLU","1390 NOLU","1392 NOLU","1393 NOLU","1394 NOLU","1395 NOLU","1396 NOLU","1397 NOLU","1398 NOLU","1399 NOLU","1400 NOLU","1401 NOLU","1402 NOLU","1403 NOLU","1404 NOLU","1405 NOLU","1406 NOLU","1407 NOLU","1408 NOLU","1409 NOLU","1410 NOLU","1411 NOLU","1412 NOLU","1413 NOLU","1414 NOLU","1415  NOLU","1416 NOLU","1417 NOLU","1418 NOLU","1419 NOLU","1420 NOLU","1421 NOLU","1422 NOLU","1423 NOLU","1424 NOLU","1425 NOLU","1426 NOLU","1427 NOLU","1428 NOLU","1429 NOLU","1430 NOLU","15 TEMMUZ","5021 NOLU","ADAŞLAR","ALPARSLAN TÜRKEŞ","ANKARA","ARAR","ARAÇ","ARİFAĞA","ATAR","BAKIR","BESLER","BOYLU","BURCU","BİNNUR","CÖMERT","DARABA","DAYI","DERYA","DESTAN","DEVOĞLU","DÜZGÜN","DİLER","ENDAMLI","ER","ERKAYA","ESKİ HENDEK","GAYE","GAZELLER","GONCA","GÖKSEL","GÖL","GÖNÜLLER-","GÜLER","GÜLHAN","GÜLLE","GÜRZ","GÜZELLER","HALI","HAS","HAYAT","HİLAL","IŞIL","KANAL","KANDİL","KAPTAN","KARASU YOLU","KEBİR","KEMER","KERKÜK","KERİM","KEVSER","KIBRIS","KINALI","KOVAN","KUMKÖY","LEVENT","MESUDİYE","MİLLET","MİMOZA","NAR","NAZ","NİLÜFER","ORUÇ","PAK","PUL","REİS","SAADET","SET ARKASI","SEÇKİN","SÖĞÜT","TAŞLI","TUNA","TURAN","UHUD","UYGUN","UZAY","YENİ ÇARŞI","YEĞENLER","YILDIRIM","YUVACI","ÇÖREK","ÇİÇEKLİ","ŞEBBOY"],"TEKELER":["1.ARA","1000 NOLU","1001 NOLU","1002 NOLU","1003 NOLU","1004 NOLU","1005 NOLU","1006 NOLU","1007 NOLU","1008 NOLU","1009 NOLU","1010 NOLU","1011 NOLU","1012 NOLU","1013 NOLU","1014 NOLU","1015 NOLU","1016 NOLU","1017 NOLU","1018 NOLU","1019 NOLU","1020 NOLU","1021 NOLU","1023 NOLU","1024 NOLU","1025 NOLU","1026 NOLU","1027 NOLU","1028 NOLU","1030 NOLU","1031 NOLU","1032 NOLU","1033 NOLU","1034 NOLU","1035 NOLU","1037 NOLU","1038 NOLU","1039 NOLU","1047 NOLU","1048 NOLU","1050 NOLU","1051 NOLU","1052 NOLU","1053 NOLU","1054 NOLU","1057 NOLU","1058 NOLU","1061 NOLU","1062 NOLU","1063 NOLU","1064 NOLU","1065 NOLU","1066 NOLU","1067 NOLU","1068 NOLU","1069 NOLU","1070 NOLU","1071 NOLU","1072 NOLU","1073 NOLU","1074 NOLU","1075 NOLU","1076 NOLU","1077 NOLU","1078 NOLU","1079 NOLU","1080 NOLU","1081 NOLU","1082 NOLU","1083 NOLU","1085 NOLU","1086 NOLU","1087 NOLU","1088 NOLU","1089 NOLU","1090 NOLU","1091 NOLU","1092 NOLU","1093 NOLU","1094 NOLU","1095 NOLU","1096 NOLU","1097 NOLU","1098 NOLU","1099 NOLU","1100 NOLU","1101 NOLU","1102 NOLU","1103 NOLU","1104 NOLU","1105 NOLU","1106 NOLU","1107 NOLU","1108 NOLU","1109 NOLU","1110 NOLU","1112 NOLU","1113 NOLU","1114 NOLU","1115 NOLU","1116 NOLU","1118 NOLU","1119 NOLU","1120 NOLU","1121 NOLU","1122 NOLU","1123 NOLU","1124 NOLU","1126 NOLU","2.ARA","3.ARA","45 NOLU","54 NOLU","955 NOLU","960 NOLU","965 NOLU","966 NOLU","967 NOLU","968 NOLU","969 NOLU","970 NOLU","971 NOLU","972 NOLU","973 NOLU","974 NOLU","976 NOLU","977 NOLU","978 NOLU","979 NOLU","980 NOLU","982 NOLU","984 NOLU","985 NOLU","988 NOLU","989 NOLU","990 NOLU","992 NOLU","993 NOLU","994 NOLU","995 NOLU","996 NOLU","997 NOLU","998 NOLU","999 NOLU","ADAPAZARI KAYNARCA","ATIK","BAĞLI","BEYKALFA","CEVİZ","DERMAN","EĞİTİM","GEBEŞLER","GÜÇLÜ","HALAS","HANCI","HIZAR","KALEM","KARAGÖZ","KARAKAMIŞ","KARASU","KAVACIK","KAYNARCA","KERESTECİLER","KERVAN","KUYU","KÜLTÜR","MARANGOZCULAR","MEYVE","NEŞELİ","PAŞA","SULTAN-","TAHİR","TEK","TEKELER","TOMRUK","TUNCA","YASA","YAŞAR","ÇEVRE YOLU","ÇİFTLİK","ÖĞRETMENLER","İNCE","İSMET İNÖNÜ","İŞLER","ŞEHİT ADİL UMUTLU","ŞEHİT AYHAN ERCAN","ŞEHİT FETHİ AKALIN","ŞEHİT HAMİT DENİZ","ŞEHİT NACİ ÇAKAR","ŞEHİT NEDİM ÖZPOLAT"],"KAYRANCIK":["ADAPAZARI KAYNARCA","ADAPAZARI KAYNARCA/9","CAMİLİ YOLU","DERELİ","DOLUNAY","EZGİ","EZGİ/1","EZGİ/2","FASIL","FERMAN","KAYRANCIK YOLU","KAYRANCIK/1","KAYRANCIK/2","KIVRIM/1","MARTI","MÜEZZİN İBRAHİM","MÜEZZİN İBRAHİM/1","MÜEZZİN İBRAHİM/2","MÜEZZİN İBRAHİM/3","MÜEZZİN İBRAHİM/5","MÜEZZİN İBRAHİM/6","MÜEZZİN İBRAHİM/7","MÜEZZİN İBRAHİM/8","NAZLI","PERVANE","SEYİR","SEYİR/1","SÜLEYMAN DİŞLİ","YAKUT","YAKUT/1","ÇİFTLİK1","ŞEHİT HİKMET CAN-"],"PAPUÇÇULAR":["690 NOLU","691 NOLU","692 NOLU","693 NOLU","694 NOLU","695 NOLU","696 NOLU","698 NOLU","699 NOLU","ADNAN MENDERES","AKKADIN","ARKA","ATATÜRK","AY","BEZEN","BOSTANCI","BİZİM","DEĞİRMENHAN","GÜLLÜK","HARMANLIK","HAYIRLI","MİS","PAPUÇÇULAR","ROYAL","SAKİN","SALKIM","SARAY BOSNA","SARI","SERVET","TAN","TÜTÜNCÜ","YARGIÇ","ZAFER","ÇIRACILAR","ŞENLİK"],"BİLECİLER":["1802 NOLU/3","5721 NOLU","5722 NOLU","5723 NOLU","5724 NOLU","5725 NOLU","BİLECİLER/2","DERNEKKIRI","GÜN1","GÜN1/1","SARIKAMIŞ","SARIYER","SARIYER/1","İLYASLAR/2"],"KARAOSMAN":["461 NOLU","462 NOLU","463 NOLU","464 NOLU","465 NOLU","466 NOLU","467 NOLU","468 NOLU","469 NOLU","470 NOLU","471 NOLU","472 NOLU","473 NOLU","474 NOLU","475 NOLU","476 NOLU","477 NOLU","478 NOLU","479 NOLU","480 NOLU","481 NOLU","482 NOLU","483 NOLU","484 NOLU","486 NOLU","AYAN","BAYRAKLI","BAŞKAN","BEZİRCİ","BEŞİK","CEYLAN","DEVOĞLU","DUMAN","DUTLU","ENDER","ESKİ","ESKİ HENDEK","KANAL","KARAAĞAÇ","KAVŞAK","KÖROĞLU","MEHTAP","MERT","MESTCİ","SAKA","SAVAŞ","SOYLU","ULUS","YAPRAK","YAVRU","ZEMİN","ÇIKRIKÇI","ÇÖVENCİ","İSMET İNÖNÜ","ŞEHİTLER"],"ŞEKER":["710 NOLU","807 NOLU","808 NOLU","809 NOLU","810 NOLU","811 NOLU","812 NOLU","813 NOLU","815 NOLU","816  NOLU","817  NOLU","818  NOLU","819 NOLU","820 NOLU","821 NOLU","822 NOLU","824 NOLU","825  NOLU","826 NOLU","837 NOLU","839 NOLU","840 NOLU","841 NOLU","842 NOLU","844 NOLU","845 NOLU","846 NOLU","847 NOLU","848 NOLU","849 NOLU","850 NOLU","851 NOLU","852 NOLU","853 NOLU","854 NOLU","855 NOLU","858 NOLU","859 NOLU","860 NOLU","861 NOLU","862 NOLU","863 NOLU","864 NOLU","865 NOLU","866 NOLU","867 NOLU","868 NOLU","869 NOLU","870 NOLU","871 NOLU","872 NOLU","873 NOLU","874 NOLU","875 NOLU","876 NOLU","877 NOLU","878 NOLU","879 NOLU","880 NOLU","881 NOLU","882 NOLU","883 NOLU","884 NOLU","885 NOLU","886 NOLU","887 NOLU","891 NOLU","892 NOLU","893 NOLU","894 NOLU","895 NOLU","896 NOLU","897 NOLU","898 NOLU","900 NOLU","901 NOLU","902 NOLU","903 NOLU","904 NOLU","905 NOLU","906 NOLU","907 NOLU","908 NOLU","920 NOLU","AHMET YESEVİ","AK","ARACI","ASMA","ATLI","BAHTİYAR","BEDİR","BELLİ","BÖLÜK","CİCİ","CİHAT","DARALI","DONANMA","DOST","DURGUN","DİNÇ","EGEMEN","ERBAŞ","ERKAN","EVREN","FARABİ","GENÇ","GEZİCİ","GURBET","GÜVERCİN","KADER","KALE","KANARYA","KARACA","KARDEŞ","KAYA","KIRGIN","KISMET","KORUN","KOÇ","KÖŞE","MAHMUT ARSLAN","MELEK","MESİRE","METE","NEŞE","NİLGÜN","PEHLİVAN","PROFESÖR DOKTOR SABAHATTİN ZAİM","RENK","RUŞEN","SEDA","SEDAT KİRTETEPE","SEHA","SENA","SEVİNÇ","SEZEN","SOLMAZ","SONGÜL","STAD","TANIŞ","TAYFUN","TEL","TETİK","UN","UYGAR","VİŞNE","ZARİF","ZENGİN","ZEYTİN","ÇARK","ÇAY","ÇELİK","ÇEVRE YOLU","ÇİÇEK","ÖMÜR","ÖREN","ÜSTÜN","İYİ","ŞAKRAK","ŞEHİT CEVDET ÖZDEMİR","ŞEHİT EKREM BAYRAMOĞLU","ŞEHİT MUSA AYTAR","ŞEHİT SELÇUK ESATOĞLU","ŞEHİT YÜZBŞ. YALÇIN AYDIN-","ŞEHİT YÜZBŞ.YALÇIN AYDIN","ŞEHİT ÜST TEĞMEN CENGİZ ULUSİNAN","ŞEKER","ŞEREF","ŞİFA","ŞİRİN"],"15 TEMMUZ CAMİLİ":["1497","1498 KÜME EVLER","1501 KÜME EVLER","1502 KÜME EVLER","1506 KÜME EVLER","1507","1508 KÜME EVLER","1509 KÜME EVLER","1510 KÜME EVLER","1511 KÜME EVLER","1512 KÜME EVLER","1514","1515 KÜME EVLER","1516 KÜME EVLER","1518","1519","1520 KÜME EVLER","1521 KÜME EVLER","1522 KÜMEEVLER","1523 KÜME EVLER","1524 KÜME EVLER","1525 KÜME EVLER","1526 KÜME EVLER","1527 KÜME EVLER","1528 KÜME EVLER","1534","1535 KÜMEEVLER","1536 KÜME EVLER","1537 KÜME EVLER","1538 KÜME EVLER","1539 KÜME EVLER","1540 KÜME EVLER","1541 KÜME EVLER","1542 KÜME EVLER","1543 KÜME EVLER","1545","1546","1548","1549 KÜME EVLER","1550 KÜME EVLER","1551","1552","1552/1","1553 KÜME EVLER","1554 KÜME EVLER","1555","1556 KÜME EVLER","1557 KÜME EVLER","1558 KÜMEEVLER","1559 KÜME EVLER","1565 KÜME EVLER","1566 KÜME EVLER","1567 KÜME EVLER","1568 KÜME EVLER","1569 KÜME EVLER","1570 KÜME EVLER","1571 KÜME EVLER","1572 KÜME EVLER","1573 KÜME EVLER","1574 KÜME EVLER","1577 KÜME EVLER","1578 KÜME EVLER","1579 KÜME EVLER","1583 KÜME EVLER","1586 KÜME EVLER","1587 KÜME EVLER","1588 KÜME EVLER","1590 KÜME EVLER","1591 KÜME EVLER","1592 KÜME EVLER","1593 KÜME EVLER","1594 KÜME EVLER","1595 KÜME EVLER","1596","1597 KÜME EVLER","1598 KÜME EVLER","1600 KÜME EVLER","1601 KÜME EVLER","1602 KÜME EVLER","1603 KÜME EVLER","1604 KÜME EVLER","1605 KÜME EVLER","1607","1610 KÜME EVLER","1611 KÜME EVLER","1613","1614","1616","1617 KÜME EVLER","1620 KÜME EVLER","1621","1624 KÜME EVLER","1625","1626 KÜME EVLER","1627","1630 KÜME EVLER","1631","1632","1633","1634","1636 KÜME EVLER","1637 KÜME EVLER","1638 KÜME EVLER","1639 KÜME EVLER","1640 KÜME EVLER","1641 KÜME EVLER","1642 KÜME EVLER","1643 KÜME EVLER","1644 KÜME EVLER","1646 KÜME EVLER","1647 KÜME EVLER","1648 KÜME EVLER","1649","1650 KÜME EVLER","1651 KÜME EVLER","1652 KÜME EVLER","1653 KÜME EVLER","1654 KÜME EVLER","1655 KÜME EVLER","1657 KÜME EVLER","1658 KÜMEEVLER","1659","1661 KÜME EVLER","1662 KÜME EVLER","1663 KÜME EVLER","1665 KÜME EVLER","1670 KÜME EVLER","1671 KÜME EVLER","1672 KÜME EVLER","1673 KÜME EVLER","1676 KÜME EVLER","2001 NOLU","2002 NOLU","2003 NOLU","2004 NOLU","2005 NOLU","2006 NOLU","2007 NOLU","2008 NOLU","2009 NOLU","2010 NOLU","2011 NOLU","2012 NOLU","2013 NOLU","2014 NOLU","2015 NOLU","2016 NOLU","2017 NOLU","2018 NOLU","2019 NOLU","2020 NOLU","2021 NOLU","2024 NOLU","2025 NOLU","2026 NOLU","2027 NOLU","2028 NOLU","2029 NOLU","2032 NOLU","2033 NOLU","2034 NOLU","2035 NOLU","2036 NOLU","2037 NOLU","2038 NOLU","2039 NOLU","204.","2042 NOLU","2043 NOLU","2044 NOLU","2045 NOLU","2046 NOLU","2047 NOLU","2048 NOLU","2049 NOLU","205.","2052 NOLU","2053 NOLU","2054 NOLU","2057 NOLU","2058 NOLU","2059 NOLU","2060 NOLU","2061 NOLU","2062 NOLU","2063 NOLU","2064 NOLU","2065 NOLU","2066 NOLU","2067 NOLU","2068 NOLU","2069 NOLU","207.","2070 NOLU","2071 NOLU","2072 NOLU","2073 NOLU","2074 NOLU","2076 NOLU","2077 NOLU","2078 NOLU","2079 NOLU","2081 NOLU","2082 NOLU","2083 NOLU","2084 NOLU","2085 NOLU","2086 NOLU","2087 NOLU","2088 NOLU","2089 NOLU","209.","2090 NOLU","2091 NOLU","2092 NOLU","2093 NOLU","2094 NOLU","2095 NOLU","2096 NOLU","2097 NOLU","2098 NOLU","2099 NOLU","210.","2100 NOLU","2101 NOLU","2102 NOLU","2103 NOLU","2104 NOLU","2105 NOLU","2106 NOLU","2107 NOLU","2108 NOLU","2109 NOLU","2110 NOLU","2111 NOLU","2112 NOLU","2113 NOLU","2114 NOLU","2115 NOLU","2116 NOLU","2117 NOLU","2118 NOLU","2119 NOLU","212.","2120 NOLU","2121 NOLU","2122 NOLU","2123 NOLU","2125 NOLU","2126 NOLU","2127 NOLU","2128 NOLU","2129 NOLU","213.","2130 NOLU","2131 NOLU","2132 NOLU","2133 NOLU","2134 NOLU","2135 NOLU","2136 NOLU","2137 NOLU","214.","2140 NOLU","2141 NOLU","2142 NOLU","2143 NOLU","2144 NOLU","2145 NOLU","2146 NOLU","2147 NOLU","2148 NOLU","2149 NOLU","215.","2150 NOLU","2151 NOLU","2152 NOLU","2153 NOLU","2154 NOLU","2155 NOLU","2156 NOLU","2157 NOLU","2158 NOLU","2159 NOLU","216.","2160 NOLU","2161 NOLU","2162 NOLU","2163 NOLU","2164 NOLU","2165 NOLU","2166 NOLU","2167 NOLU","2168 NOLU","2169 NOLU","217 NOLU","2170 NOLU","2171 NOLU","2172 NOLU","2173 NOLU","2174 NOLU","2175 NOLU","2176 NOLU","2177 NOLU","2178 NOLU","218.","219 NOLU","221.","223.","224.","225.","226.","227.","230.","231.","232.","233.","234.","AHUDUDU","BEYAZIT","CUMHURİYET","KAMİL YAŞAR EŞER","KENT","KONURALP","M.CAHİT KIRAÇ","NAZAR","PROFESÖR DOKTOR SABAHATTİN ZAİM","TUĞBA","ÖĞRETMEN MURAT YAZICI","ÜNİVERSİTE","ŞEHİT HİKMET CAN","ŞEHİT J. KOM. ÇVŞ. RECEP BAĞCI","ŞEHİT KAYMAKAM MUHAMMET FATİH SAFİTÜRK","ŞEHİT ÇETİN USLU_1"],"TUZLA":["1101 NOLU","1109 NOLU","1220 NOLU","1221 NOLU","1222 NOLU","1223 NOLU","1224 NOLU","1225  NOLU","1226 NOLU","1230 NOLU","1231 NOLU","1232 NOLU","1233 NOLU","1234 NOLU","1235 NOLU","1236 NOLU","1237 NOLU","1238  NOLU","1239 NOLU","1240 NOLU","1241 NOLU","1242 NOLU","1243  NOLU","1244 NOLU","1245  NOLU","1246 NOLU","1247 NOLU","1248 NOLU","1249 NOLU","1250 NOLU","1251 NOLU","1252 NOLU","1253 NOLU","1254 NOLU","1255 NOLU","1256 NOLU","1257 NOLU","1258  NOLU","1259NOLU","1260 NOLU","1261 NOLU","1262 NOLU","1263 NOLU","1264  NOLU","1265  NOLU","1266  NOLU","1267  NOLU","1268  NOLU","1269 NOLU","1270 NOLU","1271 NOLU","1272 NOLU","1273  NOLU","1274 NOLU","1275  NOLU","1276 NOLU","1277 NOLU","1278 NOLU","1279  NOLU","1280 NOLU","1281 NOLU","1282 NOLU","1283 NOLU","1284 NOLU","1285 NOLU","1286 NOLU","1287 NOLU","1288 NOLU","1289 NOLU","1290 NOLU","1291 NOLU","1292 NOLU","1293 NOLU","1294 NOLU","1295 NOLU","1300 NOLU","1301 NOLU","1304 NOLU","1305 NOLU","1306 NOLU","1307 NOLU","1308 NOLU-","1312 NOLU-","50 NOLU","51 NOLU","52 NOLU","53 NOLU","54 NOLU","ALPARSLAN TÜRKEŞ","ANKARA","ATMACA","BULAN","DENİZ","DEVOĞLU","GAZİ","HAL","KADİR","KANAL","KÜÇÜK HAFIZ","NERGİZ","OLGUN","OTLAK","SANAYİ","SAVAŞ","SÜLÜN","T.AHMET EFENDİ","TARIM","TAŞLI","TEK","TEKELER","TOPAÇ","YARDIMCI","YENER","ÇEVRE YOLU","ÇOBAN","İNCİ","İSMET İNÖNÜ","ŞEHİT İSMAİL ŞEREMET"],"KARAMAN":["1401 KÜME EVLERİ","1402 KÜME EVLERİ","1403 KÜME EVLERİ","1404 KÜME EVLERİ","1405 KÜME EVLERİ","1406 KÜME EVLER","1407 KÜME EVLER","1408 KÜME EVLER","1409 KÜME EVLERİ","1410 KÜME EVLERİ","1411 KÜME EVLERİ","1412 KÜME EVLERİ","1414 KÜME EVLERİ","1416 KÜME EVLERİ","1417","1419 KÜME EVLERİ","1420 KÜME EVLER","1421 KÜME EVLER","1422 KÜME EVLERİ","1424 KÜME EVLERİ","1425 KÜME EVLERİ","1426 KÜME EVLERİ","1429","1430 KÜME EVLER","1431 KÜME EVLER","1432 KÜME EVLERİ","1433 KÜME EVLERİ","1435 KÜME EVLERİ","1436 KÜME EVLERİ","1437 KÜME EVLERİ","1438 KÜME EVLERİ","1440 KÜME EVLERİ","1441 KÜME EVLERİ","1442 KÜME EVLER","1444 KÜME EVLERİ","1445 KÜME EVLERİ","1446 KÜME EVLERİ","1447 KÜME EVLERİ","1448 KÜME EVLERİ","1449 KÜME EVLERİ","1450 KÜME EVLERİ","1451 KÜME EVLERİ","1452 KÜME EVLER","1453 KÜME EVLER","1455 KÜME EVLER","1456 KÜME EVLER","1457 KÜME EVLERİ","1458 KÜME EVLERİ","1459 KÜME EVLER","1460 KÜME EVLERİ","1461 KÜME EVLERİ","1462 KÜME EVLER","1463 KÜME EVLER","1464 KÜME EVLER","1465 KÜME EVLER","1466 KÜME EVLER","1468 KÜME EVLER","1469 KÜME EVLER","1471 KÜMEEVLER","1472 KÜME EVLER","1473 KÜME EVLER","1474 KÜME EVLER","1475 KÜME EVLERİ","1476 KÜME EVLER","1477 KÜME EVLER","1478 KÜME EVLERİ","1479 KÜME EVLERİ","1480 KÜME EVLER","1481 KÜME EVLER","1482 KÜME EVLERİ","1483 KÜME EVLERİ","1484 KÜME EVLERİ","1485 KÜME EVLERİ","1490 KÜME EVLER","1491 KÜME EVLERİ","1492 KÜME EVLERİ","1493","1494 KÜME EVLERİ","1495 KÜME EVLERİ","1496 KÜME EVLER","1775 KÜME EVLER","1776 KÜME EVLER","1777","2291","2292 KÜME EVLERİ","2293 KÜME EVLER","2296","3001 NOLU","3002 NOLU","3003 NOLU","3004 NOLU","3005 NOLU","3006 NOLU","3007 NOLU","3008 NOLU","3009 NOLU","3010 NOLU","3011 NOLU","3012 NOLU","3013 NOLU","3014 NOLU","3015 NOLU","3016 NOLU","3017 NOLU","3018 NOLU","3019 NOLU","3020 NOLU","3021 NOLU","3022 NOLU","3023 NOLU","3024 NOLU","3025 NOLU","3026 NOLU","3027 NOLU","3028 NOLU","3029 NOLU","303.","3030 NOLU","3031 NOLU","3032 NOLU","3033 NOLU","3034 NOLU","3035 NOLU","3036 NOLU","3037 NOLU","3038 NOLU","3039 NOLU","3040 NOLU","3041 NOLU","3042 NOLU","3043 NOLU","3044 NOLU","3045 NOLU","3046 NOLU","3047 NOLU","3048 NOLU","3049 NOLU","3050 NOLU","3051 NOLU","3052 NOLU","3053 NOLU","3054 NOLU","3055 NOLU","3056 NOLU","3057 NOLU","3058 NOLU","3059 NOLU","306.","3060 NOLU","3061 NOLU","3062 NOLU","3063 NOLU","3064 NOLU","3065 NOLU","3066 NOLU","3067 NOLU","3068 NOLU","3069 NOLU","307.","3070 NOLU","3071 NOLU","308.","309.","310.","311.","312.","315.","318.","319","ADAPAZARI KAYNARCA","ASIR","CANSU","HÜRRİYET","KAHRAMAN","M.CAHİT KIRAÇ","MEVLANA","PROFESÖR DOKTOR SABAHATTİN ZAİM","SAHRA","UÇAR","İREM","ŞEHİT A.GAFFAR OKKAN","ŞEHİT SAFFET OKUMUŞ","ŞEHİT ÇETİN USLU"],"NASUHLAR":["ABBAS","AMBAR","CAMİLİ YOLU","CUMHURİYET","KÖSEOĞLU","KÖSEOĞLU/1","KÖSEOĞLU/2","NASUHLAR/1","SİTELER"],"TAŞLIK":["5601 NOLU","5602 NOLU","5603 NOLU","5604 NOLU","5605 NOLU","5606 NOLU","5606 NOLU/1","5607 NOLU","5608 NOLU","5609 NOLU","5610 NOLU","5611 NOLU","5612 NOLU","5615 NOLU","5616 NOLU","5617 NOLU","5618 NOLU","5619 NOLU","5620 NOLU","DEREALTI","HATİPLER","KOZLUK","KOZLUK/1","NEHİR","NEVİYE","TAŞLIK"],"OZANLAR":["452 NOLU","700 NOLU","701 NOLU","702 NOLU","703 NOLU","704 NOLU","705 NOLU","706 NOLU","707 NOLU","708 NOLU","709 NOLU","710 NOLU","711 NOLU","712 NOLU","713 NOLU","714 NOLU","715 NOLU","717 NOLU","718 NOLU","719 NOLU","720 NOLU","897 NOLU","901 NOLU","902 NOLU","ADİL","AKAN","AKAR","ALACA","ALKAN","ARK","ATAK","AÇIK","BALKAN","BRANDACI","BÜYÜKGAZİ","DÖNER","DİBEKTAŞ","DİNÇ","DİP","FUNDA","GEZİCİ","GÜLCE","GÜVERCİN","HOŞ","KARAKAMIŞ","KARANFİL","KUYTU","KUZEY","LEYLAK","MANOLYA","MELTEM","NİNE","OZANLAR","PEHLİVANOĞLU","PROFESÖR DOKTOR SABAHATTİN ZAİM","SENA","SÜRAT","TABAK","YAMAN","YİĞİT","ÇAĞLA","ÇEVRE YOLU","ÇİĞDEM","ÖZLEM","ÜNAL OZAN","ŞEHİT CEVDET ÖZDEMİR","ŞEHİT MUSTAFA ÖZEN","ŞEHİT REMZİ ÖZÜPEK","ŞEHİT YÜZBŞ.YALÇIN AYDIN","ŞEHİT ÜST TEĞMEN CENGİZ ULUSİNAN","ŞİFA"],"MİTHATPAŞA":["585 NOLU","586 NOLU","587 NOLU","588 NOLU","589 NOLU","590 NOLU","591 NOLU","592 NOLU","593 NOLU","594 NOLU","595 NOLU","596 NOLU","597 NOLU","598 NOLU","599 NOLU","600 NOLU","601 NOLU","602 NOLU","603 NOLU","604 NOLU","605 NOLU","606 NOLU","608 NOLU","609 NOLU","610 NOLU","611 NOLU","612 NOLU","613 NOLU","614 NOLU","616 NOLU","617 NOLU","618 NOLU","633 NOLU","634 NOLU","635 NOLU","636 NOLU","638 NOLU","660 NOLU","661 NOLU","662 NOLU","665 NOLU","922 NOLU","ADNAN MENDERES","AKASYA","AKIN","ALTINOVA","BALIK","BEZGİN","BİLGE","CANDAŞ","CANLI","CEVHER","DİLŞAD","DİSPANSER","EMEL","FEZA","GEÇER","GEÇİT","GÜLEN","GÜLLÜK","GÜNGÖR","GÜZEL","GÜÇ","HARMANLIK","HAZAN","KAPLAN","KARTAL","KESER","KUDÜS","KUL","KUMRU","MALİYE","MİLLİ EGEMENLİK","SERÇE","SEVİMLİ","ULU","YER","YÖN","ZÜBEYDE HANIM","ZİNDE","ÇARK","ÖN","İBRAHİM KANGAL","ŞAFAK","ŞAHİN","ŞAN"],"ACIELMALIK":["ACIELMALIK","ACIELMALIK/1","AKLI","DEFNE","EKREM ALİCAN/1","KIVRIM","KIVRIM/1","KIVRIM/2","KÜME","SELİN","SIRMA","TEZ","TOPRAK","UFAK","UYAR","ZENCEFİL"],"GÜNEŞLER YENİ":["16 NOLU","24 NOLU","5201 NOLU","5202 NOLU","5203 NOLU","5204 NOLU","5205 NOLU","5207 NOLU","5209 NOLU","5210 NOLU","5211 NOLU","5212 NOLU","5213 NOLU","5214 NOLU","5215 NOLU","5218 NOLU","5219 NOLU","5220 NOLU","5221 NOLU","5222 NOLU","5223 NOLU","5225 NOLU","5226 NOLU","5228 NOLU","5229 NOLU","5230 NOLU","5231 NOLU","5232 NOLU","5233 NOLU","5234 NOLU","5235 NOLU","5236 NOLU","5237 NOLU","5238 NOLU","5240 NOLU","5241 NOLU","5242 NOLU","5243 NOLU","5244 NOLU","5245 NOLU","8.","ANKARA","CAMİİ","HAL","HAL İÇİ","KARASU YOLU","KARTALLAR","KOŞAR","MERKEZ","YENİ","ÇAY 1","ÇAY 2","ÇEVRE YOLU","ÇİFTÇİ","ÜNSAL"],"KARAKÖY":["5521 NOLU","5521/1","5522 NOLU","5523 NOLU","5524 NOLU","5525 NOLU","5529 NOLU","ANKARA","KARAKÖY","KARAKÖY/1","NEVİYE","SETALTI","SETALTI/2","SETALTI/3","SETALTI/4","SETALTI/5","SETALTI/6","SETALTI/7","VATAN"],"SAKARYA":["1029 NOLU","1066 NOLU","721 NOLU","722 NOLU","723 NOLU","724 NOLU","725 NOLU","726 NOLU","727 NOLU","728 NOLU","729 NOLU","730 NOLU","731 NOLU","732 NOLU","733 NOLU","734 NOLU-","735 NOLU","736 NOLU","737 NOLU","738 NOLU","739 NOLU","740 NOLU","741 NOLU","742 NOLU","744 NOLU","745 NOLU","746 NOLU","747 NOLU","748 NOLU","749 NOLU","750 NOLU","ATALAR","AĞA","BARIŞ","BAŞAR","BEYKALFA","BUYRUK","CEM","DERE","DERMAN","DURAL","DURU","DÖNÜŞ","EĞİTİM","GELİNCİK","GÜRBÜZ","HACI BAYRAMLAR","HAMAM","HANCI","HANDE","HANIMELİ","HOŞNUT","KARAKOL","KATI","KISA","KLAVUZ","KÜLTÜR","MERAL","OCAK","SAFİR","SALİM","YILGIN","YILMAZ","YÜKSEL","ÇATAL","ÇELEBİ","ÇEVRE YOLU","ÖĞRETMENLER","ÜNAL OZAN","İSMET İNÖNÜ"],"BUDAKLAR":["5716 NOLU","5741 NOLU","5741 NOLU/1","5742 NOLU","5743 NOLU","5744 NOLU","5744/1","5745 NOLU","5746 NOLU","5746/1","5748 NOLU","5748/1","5749 NOLU","5750 NOLU","5751 NOLU","5752 NOLU","5753 NOLU","5754 NOLU","5755 NOLU","5756 NOLU","5757 NOLU","5758 NOLU","ABALI","ANKARA","ANKARA/1","ANKARA/2","ANKARA/3","ANKARA/4","DERNEKKIRI","ESENCE","ESENCE/1","KUZEY MARMARA"],"YENİGÜN":["15 TEMMUZ","1539 NOLU","1540 NOLU","1541 NOLU","1542 NOLU","1543 NOLU","1544 NOLU","1545 NOLU","1546 NOLU","1547 NOLU","1548 NOLU","1549 NOLU","1550 NOLU","1551 NOLU","1552 NOLU","1553 NOLU","1554 NOLU","1555 NOLU","1556 NOLU","1557 NOLU","1558 NOLU","1560 NOLU","1561 NOLU","1562 NOLU","1563 NOLU","1564 NOLU","1565 NOLU","1566 NOLU","1567 NOLU","1568 NOLU","1569 NOLU","1571 NOLU","ADAPINAR","AKARCA","AKARSU","ALEMDAR","AYTEKİN","BABALIK","BARÇIN","BAĞIŞLAR","BAŞAK","BAŞLAR","BERAT","BEYLER","BÜYÜK ÇIKMAZ","DANIŞ","DAĞLI","DOĞAN","DUT","DİLİM","ELİBOŞ","EMİN","ENGİN","ERİŞEN","ESER","GEMİ","GÖK","GÖKHAN","GÜLTEKİN","GÜLŞEN","GÜN","HACI SADIK","HASIRCILAR","HEYBETLİ","HURMA","HÜRREM","KARE","KESİK","KILIÇ","KIR","KIRIMLI","KOCACIK","KOL","KURBANLAR","MEHTAPLI","MELİK","METİN","NAL","NUR","OKAN","PARALI","RECEP","SAKARYA","SOMUN","SUNA","SÖNMEZ","TEKERCİ","TEPELİ","TERAZİ","TERZİOĞLU","TURAN","VALİDE","VEZİR","YAMUK","YAVAŞ","YAZAR","YAĞIZ","YAĞMUR","YENİCAMİ","YEĞENLER","ZÜMRÜT","ÇAKMAK","ÇIRAK","ÖBEK","ÖMER","ÖZAL","ÖZATA","ÜNLÜ","ŞEHİT MEHMET NURİ KOCABIYIK","ŞEHİT YAKUP TÖRÜN","ŞENER"],"GÜNEŞLER MERKEZ":["111 NOLU","112 NOLU","113 NOLU","114","116","126 NOLU","127 NOLU","129 NOLU","147 NOLU","149 NOLU","150 NOLU","155 NOLU","5001 NOLU","5002 NOLU","5003 NOLU","5004 NOLU","5005 NOLU","5006 NOLU","5007 NOLU","5008 NOLU","5009 NOLU","5010 NOLU","5015 NOLU","5017 NOLU","5018 NOLU","5019 NOLU","5020 NOLU","5021 NOLU","5023 NOLU","5030 NOLU","5034 NOLU","5035 NOLU","5036 NOLU","5038 NOLU","5039 NOLU","5040 NOLU","5041 NOLU","5042 NOLU","5043 NOLU","5044 NOLU","5048 NOLU","5051 NOLU","5052 NOLU","5053 NOLU","5054 NOLU","5057 NOLU","5058 NOLU","5059 NOLU","5060 NOLU","5061 NOLU","5062 NOLU","5063 NOLU","5064 NOLU","5065 NOLU","5066 NOLU","5067 NOLU","5068 NOLU","5069 NOLU","5070 NOLU","5071 NOLU","5072 NOLU","5073 NOLU","5074 NOLU","5075 NOLU","5076 NOLU","5077 NOLU","5078 NOLU","ANKARA","ERKAYA","FATİH SULTAN MEHMET","GONCA","GÖNÜL","GÜL","GÜNEŞ","ILGAZ","KABASAKAL","KARASU YOLU","KUM","KÖYİÇİ","SET ARKASI","SÜMBÜL","YAREN","YILDIRIM1","YILDIRIM2","YILDIRIM3","YONCA","ÇAĞDAŞ","ÖZCAN"],"KARAKAMIŞ":["3070 NOLU","320 NOLU","441 NOLU","442 NOLU","443 NOLU","444 NOLU","445 NOLU","446 NOLU","447 NOLU","448 NOLU","449 NOLU","450 NOLU","451 NOLU","452 NOLU","ADAPAZARI KAYNARCA","KARAKAMIŞ","KAYNARCA","PROFESÖR DOKTOR SABAHATTİN ZAİM","SAHA YOLU","TÜRBE","ŞEHİT BİROL ELMAS","ŞEHİT MUZAFFER EKMEN","ŞEHİT ÜST TEĞMEN CENGİZ ULUSİNAN"],"ALANDÜZÜ":["395 NOLU","396 NOLU","397 NOLU","AKPINAR","ALANDÜZÜ","BAL","DAR","DİCLE","DİYAR","ELVAN","ESKİ BEŞEVLER","EYLÜL","GÜNER","HARMAN","KAPAKLI","KAZIMPAŞA","KAZIMPAŞA/1","KAZIMPAŞA/2","KONAK","LALE","MAZLUM","PINAR.","PINAR./1","SARAY","USTA","USTA/2","UZUN","ZAMBAK","ÇEŞME","İBRAHİM KAYA","İBRAHİM KAYA/1","ŞENLİ","ŞIK"],"TIĞCILAR":["1211 NOLU","1212 NOLU","1213 NOLU","1214 NOLU","1215 NOLU","1216 NOLU","1217 NOLU","1218 NOLU","AKÇA","ATATÜRK","ATIF ŞENEL","AÇELYA","BARO","DÖNER GEÇİT","DİKEN","HASIRCILAR","KADİR HOCA","KARAOSMAN","KAVAKLAR","KESCİ","KOL","KÜÇÜK OSMAN","MÜFTÜ","PAMUKLAR","TEKİN","TURAN","YAĞCIOĞLU","YENİCAMİ","YUNUS AĞA","ÇETİN","İPEK"],"MALTEPE":["511 NOLU","512 NOLU","513 NOLU","514 NOLU","521 NOLU","523 NOLU","524 NOLU","525 NOLU","526 NOLU","527 NOLU","528 NOLU","529 NOLU","530 NOLU","531 NOLU","532 NOLU","533 NOLU","535 NOLU","536 NOLU","537 NOLU","541 NOLU","542 NOLU","543 NOLU","544 NOLU","545 NOLU","546 NOLU","547 NOLU","548 NOLU","549 NOLU","550 NOLU","551 NOLU","552 NOLU","553 NOLU","554 NOLU","555 NOLU","556 NOLU","557 NOLU","558 NOLU","559 NOLU","560 NOLU","561 NOLU","562 NOLU","563 NOLU","564 NOLU","565 NOLU","566 NOLU","567 NOLU","570 NOLU","571 NOLU","572 NOLU","573 NOLU","574 NOLU","575 NOLU","577 NOLU","578 NOLU","579 NOLU","922 NOLU","AYAZ","BATUR","BAYIR","BAĞLIK","BEŞKÖPRÜ","DİK","EFE","FİDELİ","GÜNEY","GÜR","KARABAYIR","KAYAR","MALTEPE","MERAM","MÜRSEL","NİŞAN","OKUL","ORHANGAZİ","OĞUZ.","PETEK","PTT","TANER","TEPEÜSTÜ","TOYGAR","ULUDAĞ","YAMAÇ","YAŞLI","YEŞİLKENT SİTESİ","YOKUŞDİBİ","ZORLU","ÇAMLI","ÇAĞLAYAN","ÖNDEREVLERİ","ÖNER","ÖZGÜR","ŞEHİT METİN AKKUŞ","ŞEHİT MÜRSEL ULUNÇ","ŞEHİT OSMAN TEMİZ"],"SEMERCİLER":["1. GEÇİT","780 NOLU","781 NOLU","782 NOLU","783 NOLU","784 NOLU","785 NOLU","786 NOLU","787 NOLU","788 NOLU","789 NOLU","790 NOLU","791 NOLU","792 NOLU","793 NOLU","794 NOLU","795 NOLU","797 NOLU","ANBARLI","ATATÜRK","BADEM","BONCUK","BOZKURT","DALLI","DR. NURİ BAYAR","DİRİ","EMECİ","FENER","GÖKÇE","GÖMEÇ","HALİÇ","KADI","KANCA","KARŞI","KIYI","KUDÜS","KÜÇÜK","LÜLECİ","MİLLİ EGEMENLİK","MİNE","PAPUÇÇULAR","PARLAK","PELİN","POSTAHANE","POYRAZ","SARAY BOSNA","SARAÇLAR","SAİT FAİK","YALIM","YAMANLAR","YAVUZ","YUVAM","YÖRÜK","ÇAKIR","ÇARK","ÇEVİK","ÇINAR","ÇIRACILAR","ÖNDER","İTFAİYE","ŞEN"],"YAHYALAR":["1471 NOLU","1472 NOLU","1473 NOLU","1474 NOLU","1475 NOLU","1476 NOLU","1477 NOLU","1478 NOLU","1479 NOLU","1480 NOLU","1481 NOLU","1482 NOLU","1483 NOLU","1484 NOLU","ANAR","ANKARA","BAHAR","BÜLBÜL","EMEKÇİ","ESKİ HENDEK","GÜLSER","HAN","HESNA SUNTER","ITIR","KETEN","KONCA","KURU","KUTLU","MANAVLAR","MUALLİM NACİ","MUMCU","MUTLU","NURLU","ORTANCA","PİRİNÇ","SEVİL","TEŞVİKİYE","TURAN","YEĞENLER","YOĞURTÇU","ÇEŞME MEYDANI","ÖZDE","ŞEHİT HAKAN BAYRAM"],"GÜLLÜK":["360 NOLU","362 NOLU","363 NOLU","364 NOLU","365 NOLU","366 NOLU","367 NOLU","372 NOLU","373 NOLU","375 NOLU","376 NOLU","377 NOLU","378 NOLU","379 NOLU","380 NOLU","ADNAN MENDERES","AKDAL","AKŞEMSETTİN","AMASYALI","AYDINLI","AYVALI","BARAN","BAĞCILAR","BELDE","CESUR","DAL","DONAT","DOĞA","DOĞRU","ERDEMLİ","FATİH","HELVACI","KORU","LÜTFÜ YAMAN","MURAT","SAĞLIK","SON","SİTE","TAÇ","TEKEOĞLU","TEMİZEL","TEPE","TEZGEL","ZÜBEYDE HANIM","ÇIKMAZ","ÖRNEK","ÜZÜM","İBRAHİM AĞA"],"YEŞİLYURT":["5820 NOLU","5821 NOLU","5822 NOLU","5822 NOLU/1","DERNEKKIRI","DERNEKKIRI/1"],"GÖKTEPE":["ATILIM","CEYDA","DEREBOYU","GÖKTEPE/1","GÖKTEPE/2","GÖKTEPE/3","GİZEM","HARMANTEPE YOLU","KABATAŞ","KAPAN","LİDER","TERTİP","YOKUŞ","ÇARDAK","ÇETİNKILIÇ","ŞEHİT.AST.OĞUZHAN ALTINTAŞ","ŞENGÜL"],"İSTİKLAL":["421 NOLU","422 NOLU","423 NOLU","424 NOLU","425 NOLU","426 NOLU","427 NOLU","428 NOLU","429 NOLU","430 NOLU","431 NOLU","432 NOLU","433 NOLU","434 NOLU","AK","AYDIN","BAYRAM","BAĞ","BÖLÜK","BİÇER","DERİN","DİBEKTAŞ","GÜNEŞLİ","KARAAĞAÇ","MELAL","PİLAVCI","SAĞLAM","SIRIM","TÜTEN","YAY","YILDIZ","ZEMBİL","ÇEREZ","İLKER","ŞEREF"],"DEMİRBEY":["6008","BEYLİK","BEYLİK/1","KARASU YOLU","KARASU YOLU/1","KARDELEN","ONUR","ONUR/1","SAYGIN"],"CUMHURİYET":["1. ARA","1.GEÇİT","192 NOLU","194 NOLU","195 NOLU","196 NOLU","198 NOLU","2.GEÇİT","3.GEÇİT","4.GEÇİT","5.GEÇİT","ANKARA","ANNEM","ARABACILAR ÇARŞISI","ATATÜRK","AYAKKABICILAR ÇARŞISI","AYNALIKAVAK  ÇARŞISI","AĞACAMİ ÇARŞISI","BAHÇIVAN","BAKIRCILAR ÇARŞISI","BANKALAR","BASIK","BİLEN","BİRLİK","DEĞERLİ","DR. NURİ BAYAR","DR.KAMİL","FARABİ","FULYA","FİKRET","GÖKALP","HATİP","HÜSEYİN RAHMİ","KANARA","KARACA","KASAPLAR ÇARŞISI","KAVAKLAR","KAYI","KAYIN","KOLAĞASI","KÜÇÜK HAMAM","KİRAZ","MENEKŞE","NADİR","ONAT","PANCAR","PAPATYA","PİRİNÇPAZARI  ÇARŞISI","SEBZECİLER ÇARŞISI","SEDAT KİRTETEPE","SEFA","SERPİL","SOĞAN PAZARI","TELLİ","TENEKECİLER ÇARŞISI","TOPLU","TÜL","TÜMEN","UN KAPANI ÇARŞISI","UZUN ÇARŞI","YAKIN","YALI","YASEMİN","YEL","ÇALIM","ÇARK","ŞAL"],"ÇALTICAK":["BAHÇELER","GÖKÇELER","GÖKÇELER/1","GÖKÇELER/2","GÖLYAKA","GÖLYAKA/1","GÖLYAKA/2","GÜLTEPE","GÜLÇİN","KONAKLI","SEVGİ","YÜCEL","ÇUBUKLU"],"İKİZCE MÜSLİM":["ACIELMALIK","BEŞEVLER","DR. TACETTİN","DR. TACETTİN/1","DR. TACETTİN/2","IHLAMURLAR","KIZILCIKLAR","PARK","SIRAEVLER","ŞEHİT YAŞAR"],"ORTA":["670 NOLU","671 NOLU","673 NOLU","674 NOLU","675 NOLU","676 NOLU","677 NOLU","678 NOLU","679 NOLU","680 NOLU","681 NOLU","682 NOLU","683 NOLU","684 NOLU","685 NOLU","686. NOLU","687 NOLU","ACUN","ADAŞ","ALTAN KUTLUATA","ANKARA","AVCILAR","BOYACI","CAN","DEMİRKAPI","DOĞU","DURAN","ESKİ HENDEK","KARAAĞAÇ","KATİP","KAVAKLAR","KEÇECİ","KUZU","KÖKÇÜ","KÜÇÜK HAMAM","KÜÇÜK HAMAM ÇIKMAZI","NAZLI_1","PAZAR GEÇİDİ","SOĞAN PAZARI","TEĞMEN","ULUS","UN KAPANI ÇARŞISI","UĞURLU","ÇEŞME MEYDANI","ÇİL"],"ŞİRİNEVLER":["921 NOLU","922 NOLU","ADNAN MENDERES","AKSU","AKŞEMSETTİN","ARMUTLU","BAYSAL","CENAP","GÖKSU","GÖÇMEN","GÜLNİHAL","ISLAR","KORCAN","KORU","KUDRET","MALTEPE","SAK","SARIKIŞLA","SAĞLIK","SEBAT","SELVİNAZ","SERİN","VAGON","ÇETİNLİ","ÖNER","İBRAHİM KANGAL","İSKAN","ŞAFAK"],"DAĞDİBİ":["240 NOLU","241 NOLU","242 NOLU","243 NOLU","244 NOLU","245 NOLU","246 NOLU","247 NOLU","248 NOLU","249 NOLU","250 NOLU","252 NOLU","253 NOLU","254 NOLU","255 NOLU","257 NOLU","258 NOLU","259 NOLU","260 NOLU","261 NOLU","262 NOLU","263 NOLU","264 NOLU","265 NOLU","266 NOLU","267 NOLU","268 NOLU","270 NOLU","271 NOLU","272 NOLU","273 NOLU","274 NOLU","275 NOLU","276 NOLU","277 NOLU","278 NOLU","284 NOLU","285 NOLU","287 NOLU","288 NOLU","290 NOLU","291 NOLU","292 NOLU","293 NOLU","298 NOLU","299 NOLU","300 NOLU","301 NOLU","303 NOLU","304 NOLU","305 NOLU","306 NOLU","307 NOLU","308 NOLU","309 NOLU","310 NOLU","311 NOLU","312 NOLU","313 NOLU","314 NOLU","315 NOLU","316 NOLU","317 NOLU","960 NOLU","ADAPAZARI KAYNARCA","BAHRİYELİ","ENKA YOLU","KARAGÖZ","KARASU","KARASU ÇIKMAZI","MÜJDE","SELVİ","YAYLA","ÇAM YOLU","ÇİFTLİK"],"TAŞKISIĞI":["931 NOLU","932 NOLU","933 NOLU","934 NOLU","935 NOLU","936 NOLU","937 NOLU","938 NOLU","939 NOLU","940 NOLU","941 NOLU","941 NOLU/1","942 NOLU","943 NOLU","943 NOLU/1","944 NOLU","945 NOLU","946 NOLU","946 NOLU/1","947 NOLU","ATIK","ENKA","ENKA/1","GÖLYAKA","HARMANTEPE YOLU","TAŞKISIĞI","TAŞKISIĞI/1","TAŞKISIĞI/2","TAŞKISIĞI/3","TAŞKISIĞI/4"],"YENİCAMİ":["1501 NOLU","1502 NOLU","1503 NOLU","1504 NOLU","1505 NOLU","1506 NOLU","1507 NOLU","1508 NOLU","1509 NOLU","1510 NOLU","1511 NOLU","1512 NOLU","1513 NOLU","1514 NOLU","1515 NOLU","1516 NOLU","1517 NOLU","1518 NOLU","1519 NOLU","ADNAN MENDERES","BÜYÜK GEÇİT","DEĞİRMEN","SAKARYA"],"HIZIRTEPE":["381 NOLU","382 NOLU","383 NOLU","384 NOLU","ACAR","ACARLI","ADNAN MENDERES","AKDAL","AKGÜL","AKGÜN","AYDINLIK","AYRI","BARBAROS","BAYGIN","BAYRAK","BULUT","BİLGİ","BİÇİMLİ","CEVAT AYHAN","DALYAN","DOĞRU","DR.AYDIN","DÖNMEZ","EFELİ","ERKİN","FATİH","FİGEN SAKALLIOĞLU","GÖREN","GÜMÜŞ","GÜRAY","HAT","HIZIR","KASIRGA","KAYGAN","KEKİK","KIRIK","KIZÇEŞME","KIŞLA","KORU","KÖKSAL","M.IŞIK","MAYA","NİLAY","ORHANGAZİ","PAMUK","PIRIL","SADIK","SEMA","SERDAROĞLU","SİPER","SİSTEM","TRAFO","TÜKENMEZ","UFUK","UĞUR","YAKA","YALÇIN","YANIK","YAŞMAK","YUNUS","İBRAHİM ÖZYURT","ŞEFKAT","ŞEHİT MUSTAFA AKYILDIZ"],"ÇUKURAHMEDİYE":["226 NOLU","227 NOLU","228 NOLU","229 NOLU","230 NOLU","ADA","AKAY","AKBAY","AKINCILAR","ARA","BAHÇE","BALA","CANTEK","DEMİRCİ","DÜZ","EKİCİ","EREN","HİCRET","KIRIM","MEYDAN","ORTAK","OĞUL","PATATES HALİ","SAKARYA","ÇAYIR","ÇUKUR","ŞEHİT ASTSUBAY YAŞAR GÜLLER"],"EVRENKÖY":["320 NOLU","321 NOLU","322 NOLU","323 NOLU","324 NOLU","325 NOLU","326 NOLU","327 NOLU","328 NOLU","329 NOLU","330 NOLU","331 NOLU","331 NOLU/1","332 NOLU","333 NOLU","334 NOLU","334 NOLU/1","334 NOLU/2","335 NOLU","336 NOLU","337 NOLU","338 NOLU","339 NOLU","340 NOLU","341 NOLU","342 NOLU","343 NOLU","344 NOLU","345 NOLU","346 NOLU","347 NOLU","348 NOLU","349 NOLU","350 NOLU","351 NOLU","352 NOLU","353 NOLU","353 NOLU/1","354 NOLU","355 NOLU","KUZEY MARMARA","KUZEY MARMARA/1","NEŞET","NEŞET/1","PROFESÖR DOKTOR SABAHATTİN ZAİM","YENİKENT","YENİKENT/1"],"BAĞLAR":["BAĞLAR","BAĞLAR/2","FERAH","FERAH 1","KIZILCIK","KUZEY MARMARA","KÖPRÜ","KÖPRÜ/1","MERKEZ","MEZARLIK","ÇAM1","ÇAM2","ÇEVRE YOLU","ŞEHİT MEHMET DURMUŞ"],"KORUCUK":["1680","1681 KÜME EVLER","1682 KÜME EVLER","1683 KÜME EVLER","1688 KÜME EVLER","1689","1690","1691 KÜME EVLER","1693","1695","1696 KÜME EVLER","1697","1698 KÜMEEVLER","1699 KÜME EVLER","1700 KÜMEEVLER","1701 KÜMEEVLER","1702 KÜME EVLER","1710","1711 KÜMEEVLER","1713 KÜME EVLER","1714 KÜMEEVLER","1726","1728","1735 KÜME EVLER","1737 KÜME EVLER","1739 KÜME EVLER","1740 KÜME EVLER","2922 KÜME EVLER","2923 KÜME EVLER","2935 KÜME EVLER","2968 KÜME EVLER","2969 KÜME EVLER","3103 KÜME EVLER","3106 KÜME EVLER","3329","3349 KÜME EVLER","3351 KÜME EVLER","3353","4001 NOLU","4002 NOLU","4003 NOLU","4004 NOLU","4005 NOLU","4006 NOLU","4007 NOLU","4008 NOLU","401.","4010 NOLU","4011 NOLU","4012 NOLU","4013 NOLU","4014 NOLU","4015 NOLU","4016 NOLU","4017 NOLU","4018 NOLU","4019 NOLU","402.","4020 NOLU","4021 NOLU","4022 NOLU","4023 NOLU","4024 NOLU","4025 NOLU","4026 NOLU","4027 NOLU","4028 NOLU","4029 NOLU","403.","4030 NOLU","4031 NOLU","4032 NOLU","4033 NOLU","4034 NOLU","4035 NOLU","4036 NOLU","4037 NOLU","4038 NOLU","4039 NOLU","404.","4040 NOLU","4041 NOLU","4043 NOLU","4044 NOLU","4045 NOLU","4046 NOLU","4047 NOLU","405 NOLU","4051 NOLU","4052 NOLU","4053 NOLU","4054 NOLU","4055 NOLU","4056 NOLU","4057 NOLU","4058 NOLU","4059 NOLU","406.","4060 NOLU","4061 NOLU","4062 NOLU","4063 NOLU","4064 NOLU","4065 NOLU","4066 NOLU","4067 NOLU","4068 NOLU","4069 NOLU","4070 NOLU","4071 NOLU","4072 NOLU","4073 NOLU","4074 NOLU","4075 NOLU","4076 NOLU","4077 NOLU","4078 NOLU","4079 NOLU","408 NOLU","4080 NOLU","4082 NOLU","4084 NOLU","4085 NOLU","4086 NOLU","4087 NOLU","4088 NOLU","4089 NOLU","409.","4090 NOLU","4091 NOLU","4092 NOLU","4093 NOLU","4094 NOLU","4095 NOLU","4096 NOLU","4098 NOLU","4099 NOLU","4100 NOLU","4101 NOLU","4103 NOLU","4105 NOLU","4106 NOLU","4109 NOLU","4110 NOLU","4111 NOLU","4112 NOLU","4113 NOLU","4114 NOLU","4115 NOLU","4116 NOLU","4117 NOLU","4118 NOLU","4119 NOLU","4120 NOLU","4121 NOLU","4122 NOLU","4123 NOLU","4124 NOLU","4125 NOLU","4126 NOLU","4127 NOLU","4128 NOLU","4129 NOLU","413.","4130 NOLU","4131 NOLU","4132 NOLU","4133 NOLU","4134 NOLU","4135 NOLU","4136 NOLU","4137 NOLU","4138 NOLU","4139 NOLU","4140 NOLU","4141 NOLU","4142 NOLU","4143 NOLU","4144 NOLU","4146 NOLU","4147 NOLU","4148 NOLU","4149 NOLU","4150 NOLU","4151 NOLU","4152 NOLU","4153 NOLU","4154 NOLU","4156 NOLU","4157 NOLU-","4158 NOLU","4159 NOLU","4165 NOLU","4166 NOLU","4167 NOLU","4168 NOLU","4169 NOLU","4171 NOLU","4172 NOLU","4173 NOLU","4174 NOLU","4175 NOLU","4176 NOLU","4177 NOLU","4178 NOLU","4179 NOLU","4180 NOLU","4181 NOLU","4182 NOLU","4183 NOLU","4184 NOLU","4185 NOLU","4187 NOLU","4188 NOLU","4189 NOLU","4190 NOLU","4191 NOLU","4192 NOLU","4193 NOLU","4194 NOLU","4195 NOLU","4196 NOLU","4197 NOLU","4198 NOLU","4199 NOLU","497 NOLU","AKPINAR","ALANDÜZÜ YOLU","AZİZ","CEVAT UNCUOĞLU","FETİH","HASTANE","KEREM COŞKUN","KONURALP","KORUCUK","OĞUZATA","VAKIF","YAŞAM"],"ÇÖKEKLER":["5444 NOLU","5461 NOLU","5462 NOLU","5463 NOLU","5464 NOLU","5465 NOLU","5466 NOLU","5466 NOLU/1","5526 NOLU","5527 NOLU","5528 NOLU","5584 NOLU","5594 NOLU","5596 NOLU","5597 NOLU","5755 NOLU-","ANKARA","ANKARA/5","DERNEKKIRI","VATAN","ÇAVUŞLAR","ÇERÇİLER","ÇERÇİLER/1","ÇÖKEKLER","ÇÖKEKLER/1"],"SÜLEYMANBEY":["BAHÇECİ","FERAH","KARASU YOLU","KIZILCIK","KUZEY MARMARA","MERKEZ","MERKEZ/1","SÜLEYMANBEY","ÖZ"],"KÖPRÜBAŞI":["5243 NOLU","5840 NOLU","5841 NOLU","5842 NOLU","5843 NOLU","5844 NOLU","ANKARA","ANKARA/12","ANKARA/13","ANKARA/14","BAHÇECİ","BAHÇECİK","BAHÇECİK/1","BAHÇECİK/2","BAHÇECİK/3","KARASU YOLU","KUZEY MARMARA","KÖPRÜBAŞI","KÖPRÜBAŞI/1","KÖPRÜBAŞI/2"],"YENİDOĞAN":["1520 NOLU","1521 NOLU","1522 NOLU","1523 NOLU","1524 NOLU","1525 NOLU","1526 NOLU","1527 NOLU","1528 NOLU","1529 NOLU","1530 NOLU","796 NOLU","ANA","CANAN","CANER","FABRİKA","FİDANLIK","GEYİK","GÜZ","HACER","HARMANLIK","HAYIRLI","IHLAMUR","KAR","KEKLİK","KONUK","MERCAN","MERMER","MİLLİ EGEMENLİK","NEMLİ","PAPUÇÇULAR","PEMBE","SARAY BOSNA","SAVUL","SAYDAM","TOR","TUNÇ","VARLIK","YALIN","YAN","ÖZEN"],"BÜYÜKHATAPLI":["GEZGİN","GEZGİN/1","GEZGİN/2","GEZGİN/3","HALILAR","HALILAR /3","HALILAR/1","HALILAR/2","HATAPLI","HATAPLI/1","HATAPLI/2","HÜSEYİNLER","KERNE","MUHARREMLER","YENİ BULVAR"],"KURTULUŞ":["501 NOLU","502 NOLU","504 NOLU","506 NOLU","507 NOLU","ATİK","BAHÇIVAN","BANKALAR","BİL","DEPO","DİLBER","EYÜP","GARİP","GÜNEŞLİ","GİRNE","HAMİTBEY ÇIKMAZI","HUZUR","IŞIK","KARAAĞAÇ","MİL","SUBAŞI","TARLA","TÜTEN","UÇAK","YILDIZ","ZUHAL","ÇAPA","ŞANLI","ŞEHİT CELAL HAYTA","ŞEHİT MEHMET TEKCAN"],"İKİZCE OSMANİYE":["406 NOLU","407 NOLU","408 NOLU_1","409 NOLU","410 NOLU","410 NOLU/1","410/1","410/2","411 NOLU","412 NOLU","413 NOLU","414 NOLU","415 NOLU","ADAPAZARI KAYNARCA","ADAPAZARI KAYNARCA/5","ADAPAZARI KAYNARCA/7","ADAPAZARI KAYNARCA/8","ADAPAZARI KAYNARCA/9","ATIK","BEŞEVLER","EKREM ALİCAN","EKREM ALİCAN/1","FİKRİ ALİCAN","KUZEY MARMARA","TEKELER/2","TEKELER/20"],"KÖMÜRLÜK":["ELMAS","ELMAS/1","KARASU YOLU","KORULUK","KUZEY MARMARA","KÖMÜRLÜK/1","KÖMÜRLÜK/2","ÇAYIRLI"],"KAVAKLIORMAN":["1801 NOLU","1802 NOLU","1802 NOLU/2","1802 NOLU/3","1802 NOLU/4","1802 NOLU/5","SARIKAMIŞ","SARIKAMIŞ/2"],"RÜSTEMLER":["5568 NOLU","5570 NOLU","5571 NOLU","5572 NOLU","5573 NOLU","5574 NOLU","5575 NOLU","5576 NOLU","5577 NOLU","5578 NOLU","5578 NOLU/1","5581 NOLU","5581 NOLU/1","5582 NOLU","5583 NOLU","5584 NOLU","5585 NOLU","5586 NOLU","5587 NOLU","5588 NOLU","5589 NOLU","5590 NOLU","5591 NOLU","5592 NOLU","5593 NOLU","5594 NOLU","5595 NOLU","5598","5598 NOLU","5599 NOLU","ANKARA","DADAŞ","KUZEY MARMARA","SELANİK","SELANİK/1","SET ÜSTÜ"],"KIŞLA":["ADAPAZARI KAYNARCA","ADAPAZARI KAYNARCA/5.","AKSAL","AKSAL/1","EMEKLİ","KIŞLA/1","KIŞLALI","KIŞLALI/1","ÖZDEM"],"TURNADERE":["5830 NOLU","5831 NOLU","5832 NOLU","5833 NOLU","5834 NOLU","5835 NOLU","5836 NOLU","5837 NOLU","5838 NOLU","5839 NOLU","SARIKAMIŞ","SET ÜSTÜ","TURNA"],"ELMALI":["ALTINDAĞ","HACI ARİF BEY","SU DEPOSU","YÖRÜKLER","ÇAVUŞ","ŞEHİT ALİ","ŞEHİT ALİ/1"],"ÖRENTEPE":["ACILIK","CAMİLİ","CAMİLİ/1","CAMİLİ/2","CAMİLİ/3","CAMİLİ/4","CAMİLİ/5","DEVA","HASAT","MISRA","MISRA/1","TUTKUN","TUTKUN/1","YENİ SAKARYA","YENİ SAKARYA/1","YENİ SAKARYA/2"],"ÇAĞLAYAN":["ÇAĞLAR","ÇAĞLAR/1","ÇAĞLAR/2","ÇAĞLAR/3"],"KÜÇÜKHATAPLI":["ADAPAZARI KAYNARCA","ADAPAZARI KAYNARCA/2","ALİMOĞLU","ESKİ KAYNARCA YOLU/1","ESKİ KAYNARCA YOLU/2","ESKİKAYNARCA YOLU","İPEKYOLU"],"SOLAKLAR":["5561 NOLU-","5730 NOLU","5731 NOLU","5732 NOLU","5733 NOLU","5734 NOLU","5735 NOLU","DERNEKKIRI","KURTDOĞAN","SARIKAMIŞ","SARIYER","SARIYER/1","SOLAKLAR"],"ABALI":["1720 NOLU-","1726 NOLU","5700 NOLU","5709 NOLU","5710 NOLU","5711 NOLU","5712 NOLU","5713 NOLU","5714 NOLU","5715 NOLU","5716 NOLU","5716 NOLU/1","5716 NOLU/2","5717 NOLU","ABALI","ABALI/1","ANKARA","BOSTANCILAR","BOSTANCILAR/2","HACILAR"],"HACILAR":["1720 NOLU","1721 NOLU","1722 NOLU","1723 NOLU","1724 NOLU","1725 NOLU","1726 NOLU","1727 NOLU","1728 NOLU","1729 NOLU","5802 NOLU-","HACILAR"],"HARMANTEPE":["AŞAĞI","AŞAĞI/1","DÜZEN","DÜZEN/1","GÖLYAKA","HARMANTEPE","HARMANTEPE/1","HARMANTEPE/2","HARMANTEPE/3","KİBAR","ÖRGÜN","ÖRGÜN/2","İMREN","İMREN/2"],"ÇAMYOLU":["201 NOLU","202 NOLU","203 NOLU","204 NOLU","205 NOLU","206 NOLU","207 NOLU","208 NOLU","209 NOLU","210 NOLU","211 NOLU","ADAPAZARI KAYNARCA","ENKA YOLU","GİZEM","KUZEY MARMARA","SEFEROĞLU","ŞEHİT İBRAHİM GÜNEŞ","ŞEHİT İBRAHİM GÜNEŞ/1","ŞEHİT İBRAHİM GÜNEŞ/2"],"AŞIRLAR":["ABAY","ABAY/1","AL","ALİM","ALİM/1","AŞIRLAR","AŞIRLAR/1","AŞIRLAR/2","AŞIRLAR/3","AŞIRLAR/4","KAVAKLI","KAVAKLI/1","KIRMIZI","REYHAN","REYHAN/1","REŞİT","YAŞ","ÇAM"],"IŞIKLAR":["ATILGAN","DORUK","DORUK/1","DORUK/2","DORUK/3","GÜNDÜZ","GÜNDÜZ/1","VOLKAN","ŞÜKÜR","ŞÜKÜR/1","ŞÜKÜR/2","ŞÜKÜR/3"],"KARADAVUTLU":["KALDIRIM","KARAHASAN","KARAHASAN/1","KARAHASAN/2","KARAHASAN/3","REHBER","REHBER/1","REHBER/2","ZEYBEK","ZEYBEK/1","ZEYBEK/2"],"İLYASLAR":["5801 NOLU","5802 NOLU","5803 NOLU","5804 NOLU","5805 NOLU","5806 NOLU","5807 NOLU","5808 NOLU","5809 NOLU","5810 NOLU","BOSTANCILAR","DERNEKKIRI","HACILAR","İLYASLAR/2"],"KARAPINAR":["488 NOLU","489 NOLU","490 NOLU","491 NOLU","492 NOLU","493 NOLU","494 NOLU","495 NOLU","496 NOLU","497 NOLU","498 NOLI","499 NOLU","500 NOLU","ALANDÜZÜ YOLU","KARAPINAR","KONURALP","NEŞET-","PROFESÖR DOKTOR SABAHATTİN ZAİM"],"MAHMUDİYE":["CİHAN","EVRİM","KAMER","MERİÇ","SARMAŞIK","ÇAYIRLAR","ÇAYIRLAR/1","İLKE","İLKE/1"],"POYRAZLAR":["ESEN","ESEN/1","HASRET","KARASU YOLU","KARASU YOLU/3","KARASU YOLU/4","KARDELEN","KÖMÜRLÜK/1","OYLUM","POYRAZLI","SANCAK","SEHER","SILA"],"ÇELEBİLER":["8801 NOLU","8802 NOLU","8803 NOLU","8804 NOLU","8805 NOLU","KUZEY MARMARA","SELANİK","SET ÜSTÜ","ÇELEBİLER","ÇELEBİLER/1"],"ÇERÇİLER":["5441 NOLU","5442 NOLU","5443 NOLU","5444 NOLU","5445 NOLU","5446 NOLU","5447 NOLU","5448 NOLU","5449 NOLU","5450 NOLU","KUZEY MARMARA","SELANİK","ÇERÇİLER"],"DOĞANCILAR":["5481 NOLU","5482 NOLU","5483 NOLU","KURTDOĞAN","KURTDOĞAN/4","KURTDOĞAN_1","SET ÜSTÜ","SET ÜSTÜ/1","SET ÜSTÜ/2","TURNA"],"KURTBEYLER":["5502 NOLU","5561 NOLU","5562 NOLU","5563 NOLU","5564 NOLU","5565 NOLU","5566 NOLU","5567 NOLU","KURTDOĞAN","KURTDOĞAN/1","KURTDOĞAN/2","KURTDOĞAN/5","ORTA"],"HACIRAMAZANLAR":["5501 NOLU","5502 NOLU","5503 NOLU","5504 NOLU","5504 NOLU/1","5505 NOLU","5506 NOLU","5507 NOLU","5567 NOLU","5750 NOLU","DERNEKKIRI","KURTDOĞAN","KUZEY MARMARA","SELANİK"],"KASIMLAR":["5445 NOLU","5541 NOLU","5541/1","5542 NOLU","5543 NOLU","5544 NOLU","KASIMLAR","KASIMLAR/1","KUZEY MARMARA","SELANİK","SET ÜSTÜ","ÇERÇİLER"],"BAYRAKTAR":["1302 NOLU","5701 NOLU","5701 NOLU/1","5701 NOLU/2","5702 NOLU","5703 NOLU","5704 NOLU","5707 NOLU","ANKARA"]}