{"ÇAMALAN":["AHLATLI","KARAKAHYALAR","MERKEZ_14","TAHTACILAR","İNİŞDİBİ"],"GÖDEKLİ":["AŞAĞIALAN","BOZARMUT","HACIKÖSE","KEPELLER","KIRANYAYLA","KOÇOSMANLAR","MERKEZ_4","TAŞKESİK","ÇUKURYURT"],"KARŞIYAKA":["220.SOKAK","221.SOKAK","222.SOKAK","223.SOKAK","302.SOKAK","315.SOKAK","319","321","389","398","400","403","406","ADNAN OTUGEN SOKAK","AFYON SOKAK","AKINCILAR SOKAK","AKKONAK SOKAK","ALAATTİN KEYKUBAT SOKAK","ALPTEKİN","ALİ KUSÇU SOKAK","ATATÜRK BULVARI","AY SOKAK","BATUM SOKAK","BEYKONAK SOKAK","BEYOĞLU SOKAK","BOĞAZKÖY SOKAK","BULUŞ SOKAK","BÜLBÜLDERESİ SOKAK","CENGİZ BALKAN SOKAK","CENGİZ TOPEL CADDESİ","DALMAÇYA SOKAK","DİYARBAKIR SOKAK","EDİRNE SOKAK","EKİN SOKAK","EMET SOKAK","HACI İLBEY SOKAK","HAFIZ AHMET PAŞA SOKAK","HALİT PAŞA SOKAK","HÜNKAR SOKAK","HİCRET SOKAK","IĞDIR SOKAK","KANİJE SOKAK","KEMERKAYA SOKAK","KESAN SOKAK","KINALI SOKAK","KIRIKKALE SOKAK","KIRKLARELİ SOKAK","KÜTAHYA SOKAK","LEFKE SOKAK","MALKOÇOĞLU SOKAK","MANİSA SOKAK","MEKKE CADDESİ","MESNEVİ SOKAK","MUĞLA SOKAK","MİLLİMÜCADELE","NEVŞEHİR SOKAK","NİĞDE SOKAK","OK SOKAK","PAPATYA SOKAK","PİRLER SOKAK","PİYALEPAŞA SOKAK","SAADET TÖNGEL","SAMANOĞULLARI SOKAK","SARIYAPRAK SOKAK","SELAHATTİN EYYÜBİ SOKAK","SEMİZ SOKAK","SULTANHAN SOKAK","SİLAHTARAĞA SOKAK","TEKİRDAĞ SOKAK","TERAKKİ SOKAK","TEVFİK İLERİ SOKAK","TOPKAPI SOKAK","TRABLUSGARP SOKAK","TUFANBEYLİ SOKAK","ULUS1 SOKAK","UZUN KÖPRÜ SOKAK","VİLLA SOKAK","YENİHAYAT SOKAK","YEŞİLOVA","ZEYTİNBEYLİ SOKAK","ZİGETVAR","ÇANKIRI SOKAK","ÇAVDARHİSAR","İBRAHİM ÖNGÖREN SOKAK","İLKADIM BULVARI","İLKBAHAR SOKAK","İMAM GAZALİ SOKAK","İNCESU SOKAK","İPSALA SOKAK","İSKİLİP BULVARI","ŞÜKRÜ BEY"],"HACI İSMAİL":["153.SOKAK","154.SOKAK","155.SOKAK","156.SOKAK","157.SOKAK","158.SOKAK","159.SOKAK","160.SOKAK","161.SOKAK","163.SOKAK","254.SOKAK","256.SOKAK","257","258","259.SOKAK","275","276","277","278","279","303. SOKAK","304.SOKAK","311.SOKAK","394","395","396","410","412.SOKAK","413.SOKAK","450.SOKAK","469.SOKAK","701.","702.","703.","705.","706.","707.","708.","802.","803.","804.","805.","806.","807.","808.","809.","817.","818.","819.","820.","821.","822.","823.","824.","825.","826.","827.","828.","829.","AYDINLIK SOKAK","BOZA SOKAK","CAMİ SOKAK","CENNET SOKAK","CEVHER NESİBE HATUN","GONDOL SOKAK","GİRNE SOKAK","HARZEMŞAH SOKAK","HÜSEYİN ALP CADDESİ","KORUCU ALİ SOKAK","OLİMPİYAT","SAĞLIK SOKAK","YALÇIN AKSOY CADDESİ","YILDIRIM SOKAK","ZİRVE SOKAK"],"GECEHAN":["AŞAĞI GECEHAN","DELİ BAŞLAR","TAHMAZLAR","YUKARI GECEHAN"],"BAŞALAN":["HODİNİ","MERKEZ_16","MERKEZ_19","PERÇEMLER","ÇAKIRLAR","ÇANGALEVİ","ÇERKEZLER","İMAMLAR"],"YENİMAHALLE":["1.SOKAK","10.SOKAK","100. YIL BULVARI","11.SOKAK","12.SOKAK","13.SOKAK","14.SOKAK","15.SOKAK","16.SOKAK","17.SOKAK","18.SOKAK","19.SOKAK","2.SOKAK","20.SOKAK","21.SOKAK","22.SOKAK","23.SOKAK","24.SOKAK","25.SOKAK","26.SOKAK","27.SOKAK","28.SOKAK","280.SOKAK","281.SOKAK","282.SOKAK","283","284","287.SOKAK","288.SOKAK","289.SOKAK","29.SOKAK","290","291","3.SOKAK","30.SOKAK","301.SOKAK","31.SOKAK","32.SOKAK","33.SOKAK","34.SOKAK","35.SOKAK","36.SOKAK","37.SOKAK","38.SOKAK","39.SOKAK","40.SOKAK","41.SOKAK","42.SOKAK","43.SOKAK","44.SOKAK","45.SOKAK","46.SOKAK","47.SOKAK","48.SOKAK","49.SOKAK","5.SOKAK","50.SOKAK","51.SOKAK","52.SOKAK","54.SOKAK","56.SOKAK","58.SOKAK","6.SOKAK-","60.SOKAK","62.SOKAK","64.SOKAK","66.SOKAK","68.SOKAK","7.SOKAK","8.SOKAK-","839.","849","850","9.SOKAK","AHIEVRAN CADDESİ","ALTINTAŞLI SOKAK","ALTUNTAŞ SOKAK","ALİ RIZA BEY BULVARI","ATATÜRK BULVARI","AYNUR SOKAK","BARBAROS CADDESİ","BASIN SOKAK","DOĞU PARK KÜMESİ","EMEK CADDESİ","EROĞLU SOKAK","FİRUZE SOKAK","GÜLEÇ SOKAK","GÜN SOKAK","GİRESUN SOKAK","KILIÇARSLAN CADDESİ","MİLLET CADDESİ","NEŞE SOKAK","SABRİ ÇAVUS SOKAK","SARACIK SOKAK","TUGRULBEY SOKAK","TUNCELİ SOKAK","ULUS CADDESİ","UŞAK SOKAK","VATAN CADDESİ","YAHŞİYAN SOKAK","YENİ ŞEN SOKAK","YURTSEVER CADDESİ","ZAHİRECİ SOKAK","ÇARŞAMBA CADDESİ","ÖZSU SOKAK","İLKADIM BULVARI","ŞEHİT EROL SOKAK","ŞEHİT MESUT BİRİNCİ CAD.","ŞENGÜL SOKAK"],"İKİYÜZ EVLER":["202.SOKAK","203.SOKAK","204.SOKAK","205.SOKAK","206.SOKAK","207.SOKAK","208.SOKAK","209.SOKAK","210.SOKAK","211.SOKAK","212.SOKAK","213.SOKAK","214.SOKAK","215.SOKAK","216.SOKAK","217.SOKAK","218.SOKAK","219.SOKAK","318.","429.","431.","432.","433.","434.","435.","436.","437.","438.","İLKADIM BULVARI"],"KUZEY YILDIZI":["100. YIL BULVARI","104.SOKAK","105.SOKAK","106.SOKAK","107.SOKAK","108.SOKAK","19 MAYIS","296.SOKAK","298","299.SOKAK","412.","651.","652.-","653.","654.","655.","656.","ALİ RIZA BEY BULVARI","ANIL SOKAK","BAKIR SOKAK","CAN SOKAK","CEVDET PAŞA SOKAK","CİDDE SOKAK","DİVANYOLU SOKAK","FAHRETTİN ALTAY SOKAK","FAS SOKAK","GÖKMEN SOKAK","GÖLCÜK SOKAK","GÖZDE SOKAK-","HACI EVLIYA SOKAK","HAKPEREST SOKAK","HAMSİ SOKAK","HATTAT SOKAK","HAZAN SOKAK","KARACILAR SOKAK","KAYIKHANE SOKAK","KERVANSARAY SOKAK","KOCA SINAN PASA SOKAK","KUTLUK SOKAK","MALTA SOKAK","OĞUL (YEŞİLOVA)","SANDIKLI SOKAK","SARIZ SOKAK-","SERAPSU SOKAK","SEYRANİ SOKAK","SULUOVA SOKAK","TALAS SOKAK-","TEMİZ SOKAK","VENÜS SOKAK","YAKUT TÜRKLERİ","YENİÇERİ SOKAK","ZEKİ BAYRAKTAR SOKAK","ÇİFTLİK CADDESİ","ÇİFTLİK CADDESİ (YEŞİLOVA)","İLKADIM BULVARI","İPEKÇİ SOKAK-","ŞEHİT EROL İŞAL SOKAK","ŞEHİT MESUT BİRİNCİ CAD.","ŞEHİT MUSTAFA ZIVALI"],"TOPTEPE":["226.SOKAK","227.SOKAK","228.SOKAK","229.SOKAK","230.SOKAK","231.SOKAK","232.SOKAK","234.SOKAK-","235.SOKAK","236.SOKAK","237.SOKAK-","380","381","385","401-","417","ACIGÖL SOKAK","AK MESCİT SOKAK","ATATÜRK BULVARI","AŞIK VEYSEL CADDESİ","BALKAN TÜRKLERİ SOKAK","BAYIRLI SOKAK","BERHAN ÇAVUŞ SOKAK","DAL SOKAK","DERİNKUYU SOKAK","DOKUZPINAR SOKAK","GEDİZ SOKAK","GEDİZ SOKAK_1","GİRİT TÜRKLERİ SOKAK","HACI MANSUR SOKAK","HARİKA SOKAK","IŞIL SOKAK","KAMELYA SOKAK","KARAÇAM SOKAK","KAYAALTI SOKAK","KEMAH SOKAK","KIRIM TÜRKLERİ SOKAK","KOZAKLI SOKAK","TACİKİSTAN TÜRKLERİ SOKAK","TAŞKIN PAŞA SOKAK","USLU SOKAK","YEŞİLGÖLCÜK SOKAK","YUSUF AĞA SOKAK","ÖZBEKİSTAN TÜRKLERİ SOKAK","ÜNLÜ SOKAK","ÜSKÜP CADDESİ","ÜZÜMLÜ SOKAK","İRAN TÜRKLERİ SOKAK","ŞEHİT PİYADE ER ERDOĞAN DİNDAR"],"HASKÖY":["164.SOKAK","165.SOKAK-","166.SOKAK-","167.SOKAK","168.SOKAK","169.SOKAK-","170.SOKAK","171.SOKAK","172.SOKAK","173.SOKAK","174.SOKAK","175.SOKAK","176.SOKAK","177.SOKAK","178.SOKAK","179.SOKAK","180.SOKAK","181.SOKAK","182.SOKAK","183.SOKAK","184.SOKAK","185.SOKAK","186.SOKAK","187.SOKAK","188.SOKAK","189.SOKAK","190.SOKAK","191.SOKAK","192.SOKAK","193.SOKAK-","194.SOKAK","195.SOKAK","196.SOKAK","197.SOKAK","198.SOKAK-","199.SOKAK","200.SOKAK","201.SOKAK","229.SOKAK","310.SOKAK","322","333","334-","335","336","340-","341-","343","344","345","346","347","348","349","350","351","352","353","354","355","356","357","358","360","361-","362","363","364-","365","366-","367","368","369","370","371","372","373","374","375","376","377","378","380","381","382","383","384-","385","391","397","593.","650.","709.","713.","720-","836.","ALTINOVA SOKAK","ALTINTEPE SOKAK","ANGIN SOKAK","ANILLAR SOKAK","ARKADAŞ SOKAK","ARMA SOKAK","ARMAĞAN SOKAK","ASİL SOKAK","AYLA SOKAK","AŞIK VEYSEL CADDESİ","AŞIK VEYSEL CADDESİ-","BAHÇELİ SOKAK","BAYIRLI SOKAK","BAĞLAMA SOKAK","BELGİ SOKAK","BESTEKAR SOKAK","BOZKIR SOKAK","BUKLE SOKAK","BULANIK SOKAK","BİLİM SOKAK","CANDAN SOKAK","CANER SOKAK","CENGİZ TOPEL CADDESİ","DOKUZPINAR SOKAK","DÜZKIŞLA SOKAK","EBRU SOKAK","ERENTEPE","FAZİLET SOKAK","GEDİZ SOKAK_1","GERÇEK SOKAK","GÜRDAL SOKAK","HACILAR SOKAK","KARADİREK SOKAK","KARANLIKDERE SOKAK","KARAÇAM SOKAK","MADEN SOKAK","NAKIŞ SOKAK","NİKSAR SOKAK","OP.DR.AYNUR DAĞDEMİR","SARIPINAR SOKAK","SESLİKAYA SOKAK","SEZER","SULUSARAY SOKAK","TOPÇU SOKAK","TURHAL SOKAK","ULUDERE","ULUKIŞLA SOKAK","VAKIF SOKAK-","YALVAÇ SOKAK","YENİ SAMSUN","YENİKENT SOKAK","YEŞİLGÖLCÜK SOKAK","YEŞİLKENT SOKAK","YÖRÜKLER SOKAK","ÇAMARDI SOKAK","ÖVÜNÇ SOKAK","ÖZCAN SOKAK","ÖZENLİ SOKAK","ÖZGÜR SOKAK","ÖZLÜ SOKAK","ÜSKÜP CADDESİ","ÜZÜM SOKAK","ŞEHİT PİYADE ER ERDOĞAN DİNDAR"],"ULUDAĞ":["177.SOKAK","238.SOKAK-","239.SOKAK","240.SOKAK","241.SOKAK","242.SOKAK-","243.SOKAK","244.SOKAK","245.SOKAK","246.SOKAK","247.SOKAK","248.SOKAK","249.SOKAK","250.SOKAK","251.SOKAK","312.SOKAK","ALTINOLUK SOKAK","ANADOLU SOKAK","ANILLAR SOKAK","ASYA SOKAK","ATABEY SOKAK","BALABAN SOKAK","BATUM SOKAK","BURDUR SOKAK-","BİNBİRGECE SOKAK","CENGİZ TOPEL CADDESİ","DELLAZADE SOKAK","DERİK SOKAK","EBRU SOKAK","ELA SOKAK","EMİRGAZİ SOKAK","ESKİKONAK SOKAK","GEDİZLİ SOKAK","GÜREL SOKAK","HACILAR SOKAK","HATIRA SOKAK","IŞIKTEPE SOKAK","KADIRGA SOKAK","KINALI SOKAK","KUŞDİLİ SOKAK","KÖŞK MEDRESE SOKAK","LALEZAR SOKAK","LAÇİN SOKAK","MADEN SOKAK","MAHMUDİYE SOKAK","MAZIDAĞI SOKAK","MIDYAT1","MİDYAT","MİLLİMÜCADELE","NUSAYBİN SOKAK","OK SOKAK","OKÇULAR SOKAK","OSMAN TURAN SOKAK","PAŞAZADE SOKAK","SEDEFKAR SOKAK","SEVGİ SOKAK","TOPÇU SOKAK","VAKIF SOKAK","VAKIFLI SOKAK","YALVAÇ SOKAK","ÇAĞDAŞ SOKAK","ÖMERLİ SOKAK","ÖZATA SOKAK","İSKİLİP SOKAK","ŞAHİKA SOKAK","ŞEHİT PİYADE ER ERDOĞAN DİNDAR","ŞEKERZADE SOKAK","ŞÜKRÜ BEY"],"YAVUZ SELİM":["219.SOKAK","252.SOKAK-","253.SOKAK","259.SOKAK","260.SOKAK","261.SOKAK","262.SOKAK","263.SOKAK","264.SOKAK","265.SOKAK-","266.SOKAK","267.SOKAK","268.SOKAK","269.SOKAK","270.SOKAK","272.SOKAK","273.SOKAK","274.SOKAK","277","399-","402","409","410","411.SOKAK","AKÇAKIŞLA SOKAK","ALACAHAN SOKAK","BAHÇEKAPI SOKAK","BEYZADE SOKAK","BURÇ SOKAK","CEVHER SOKAK","DEVEDİKENİ SOKAK","DONANMA SOKAK","DUTLUK SOKAK","DİBEK SOKAK","EGE SOKAK","EMANETÇİ SOKAK","EMEKTAR","ESKİDOLAP SOKAK","ESKİÇESME SOKAK","ESTERGON SOKAK","FATİH GÖKMEN SOKAK","FERMAN SOKAK","GAYRET SOKAK","GAZİ ETHEM PAŞA SOKAK","GAZİ GİRAY SOKAK-","GONDOL SOKAK","GÖKDERE SOKAK","GÖÇMEN SOKAK","HARZEMŞAH SOKAK","KEFELİZADE SOKAK","MERCİDABIK SOKAK","MUHAMMET İKBAL CADDESİ_1","NAZAR SOKAK","OLİMPİYAT","PETEK SOKAK","SEBİL SOKAK","SEDİR SOKAK","SUBAT SOKAK","SİPAHİ SOKAK","YAHYALI SOKAK","YEŞİLHİSAR SOKAK","ÇAĞLAR SOKAK","ÖZVATAN SOKAK","İLKADIM BULVARI"],"GAZİOSMANPAŞA":["114.SOKAK","115.SOKAK","116.SOKAK","117.SOKAK","118.SOKAK","119.SOKAK","120.SOKAK","121.SOKAK","122.SOKAK","123.SOKAK","124.SOKAK","125.SOKAK","126.SOKAK","127.SOKAK","128.SOKAK","129.SOKAK","130.SOKAK","131.SOKAK","132.SOKAK","133.SOKAK","134.SOKAK","136.SOKAK","137.SOKAK","138.SOKAK","139.SOKAK","140.SOKAK","141.SOKAK","142.SOKAK","143.SOKAK","144.SOKAK","145.SOKAK","146.SOKAK","147.SOKAK","148.SOKAK","149.SOKAK","151.SOKAK","152.SOKAK-","271.SOKAK","305.SOKAK","307.SOKAK","308.SOKAK","309.SOKAK","316","317","323","324-","325-","326","327","328","329","330","332","390","405","414.SK","415-","416","553.","554.","ABALIOĞLU SOKAK","ADALAR SOKAK","ADSIZ TEPE SOKAK","AHBAP SOKAK","AKBALIK SOKAK","AKDAĞ SOKAK","AKIŞ SOKAK","AKMAN SOKAK","AKOVA SOKAK","AKSEKİ SOKAK","AKSUNGUR SOKAK","AKYEL SOKAK","AKÇADAĞ SOKAK","AKİK SOKAK","ALACA SOKAK","ALAGÖZ SOKAK","ALEV SOKAK","ALİBABA SOKAK","ARASTA SOKAK","ARİF NİHAT ASYA SOKAK","ARİF NİHAT SOKAK-","AVŞAR BOYU SOKAK","AVŞAR SOKAK","AYDEDE SOKAK","AYDINOĞULLARI SOKAK","AYVACIK SOKAK","AZİMKAR SOKAK","AĞARMIŞ SOKAK","AŞHANE SOKAK","BAL SOKAK","BALKAPANI SOKAK","BATUM SOKAK","BAŞAK SOKAK","BOĞAZİÇİ SOKAK","BUHARA SOKAK","BİLGE SOKAK","CEVDET PAŞA SOKAK","CEYLAN SOKAK","CUMAOVASI SOKAK","DEDE EFENDİ SOKAK","DEMİRTAŞ SOKAK","DENİZ SOKAK","DERECİK SOKAK","DODURGA SOKAK","DOĞA SOKAK","DOĞAL","DRAMA SOKAK","DÜNDAR TEPE SOKAK","EKBERŞAH SOKAK","ESENLER SOKAK","ESKİ PAZAR SOKAK","FAZİLET SOKAK","GERÇEK SOKAK","GÖKMEDRESE SOKAK","GÖKMESCİT SOKAK","GÖKTEPE SOKAK","GÖKÇEKAYA SOKAK","GÖLHİSAR SOKAK","GÖLKAYA SOKAK","GÜLFİDAN SOKAK","GÜMÜLCİNE SOKAK","HACILAR SOKAK","HARZEMŞAH SOKAK","HEKİMOĞLU ALİPAŞA SOKAK","HİZMET SOKAK","KAHİRE SOKAK","KARAMANLI SOKAK","KARAÇOBAN SOKAK","KARTALOĞLU SOKAK","KAYIBOYU SOKAK","KAĞIZMAN SOKAK","KOCA YUSUF SOKAK","KOÇİBEY SOKAK","KUTALMIŞ SOKAK","LEFKOŞE SOKAK","MADEN SOKAK","MAHMUDİYE SOKAK","MALATYA SOKAK","MARTI SOKAK","MARİFET SOKAK","MEHMET EMİN YURDAKUL SOK.","MEHMET PAŞA SOKAK","MENGEN SOKAK","MERSİN SOKAK","MEÇHUL ASKER SOKAK","MUDURNU SOKAK","MUHAMMET İKBAL CADDESİ","MUSUL SOKAK","NADİR SOKAK","NAZARLIK SOKAK","NEVRUZ SOKAK","NİMET SOKAK","OLCAYTU SOKAK","OLTU SOKAK","ORTANCA SOKAK","PALU SOKAK","PAPAĞAN SOKAK","PASİNLER SOKAK","PERVANE SOKAK","RAVZA SOKAK","REVANİ SOKAK","REYHAN SOKAK","SARAYKÖY SOKAK","SEREN SOKAK","SEVİN SOKAK","SOĞUK ÇEŞME SOKAK","SUNGURBEY SOKAK","SÜMER SOKAK","SÜTÇÜ İMAM SOKAK","SİNCAP SOKAK","SİPAHİLER SOKAK","TAHRAN SOKAK","TAVAS SOKAK","TAŞDELEN SOKAK","TAŞLIÇAY SOKAK","TIBBİYE SOKAK","TOPÇUBAŞI SOKAK","TORUNTAY SOKAK","ULUKIŞLA SOKAK","UZUNÇARSILI SOKAK","VATANPERVER SOKAK","YALVAÇ SOKAK","YAPRAKLI SOKAK","YARIMCA SOKAK","YÜREKLİ SOKAK","ZEMZEM SOKAK","ÇAKABEY SOKAK","ÇAMLIBEL SOKAK","ÇAYHANE SOKAK","ÇAĞLA SOKAK","ÇAĞRIBEY SOKAK","ÇEMBERLİTAŞ SOKAK","ÜSTAT SOKAK","İLKADIM BULVARI-","İLKE SOKAK","İNEBAHTI SOKAK","İSKENDER PAŞA SOKAK","ŞAHMERDAN SOKAK","ŞAHİNBEY SOKAK","ŞAHİNLER SOKAK","ŞAMDAN SOKAK","ŞEHIT POLIS MEMURU ADEM KESKİN","ŞEHİT MESUT BİRİNCİ CAD.","ŞEHİT POLİS MEMURU MESUT YILMAZ","ŞEKER AHMET SOKAK","ŞİFAHANE SOKAK"],"DEVGERİŞ":["843.","844.","845.","846.","847.","848","CAMİ","DERBENT","DEVGERİŞ KÖYÜ","KASAPLAR","MEVLÜT","MEZARLIK","OKUL","ONDOKUZ MAYIS","TONYALILAR","ÇAYLEK","ÇEŞME","ÇİFTLİK"],"GÖKÇEPINAR":["AHLATLI","AŞIKLAR","BALİGAR","BAĞYERİ","DADAMLAR","DEVEYATAĞI","KUYULAR","MERKEZ_19","YESİFLER"],"KIZILOĞLAK":["DERE","DEĞİRMENYOLU","MERKEZ_21","TÜNEL ÜSTÜ","TÜNELLER"],"MURATLI":["MERKEZ_18","MURATLI"],"SARIBIYIK":["163.SOKAK","311.SOKAK","827.","828.","829.","830.","AŞAĞI_1","CEVHER NESİBE HATUN","MERKEZ_12","TEPE","YILANCI DERE"],"KESTANEPINAR":["AŞAĞI","DADAMLAR","KÜÇÜKKÖY","MERKEZ_5","PİRELİBEL"],"DÜVECİK":["318.","421.","425.","426.","427.","428.","429.","430.","431.","442.","447.","449.","451.","452.","453.","454.","455.","456.","457.","458.","459.","460.-","461.-","462.","463.","464.","465.","466.","467.","470.","471.","472.","473.","474.","475.","478.","479.","480.","481.","482.","483.","484.","485.","486.","487.","488.","489.","490.","491.","492.","493.","494.","495.","496.","499","MERKEZ_12","MERKEZ_20","OVA_1","YUKARI_1","ŞEHİT PİYADE UZMAN ONBAŞI TAYFUN PEKEL"],"KAŞYAYLA":["KARLIK","KATIRCILAR","KAYA ALTI","MERKEZ_17","SUNGURLU","YILANLIDERE"],"SOĞUKSU":["224.SOKAK","225.SOKAK","404-","ADANA SOKAK","ADIYAMAN SOKAK","AFYON SOKAK","AKMAN SOKAK","ANADOLU SOKAK","ARK SOKAK","ATABEY SOKAK","AYDINOĞULLARI SOKAK","AZİZLER SOKAK","BATUM SOKAK","BELGRAT SOKAK","BUDİN SOKAK","BİNGAZİ SOKAK","CANDAROĞLU SOKAK","COŞAR SOKAK","CÜNEYD BAĞDADİ SOKAK","CİHADİ EKBER SOKAK","DAĞISTAN SOKAK","DENİZ SOKAK","DERGAH SOKAK","DOĞANBEY SOKAK","DUYGU SOKAK","FERHAT PAŞA SOKAK","FIRAT SOKAK","GAZİ GİRAY SOKAK","GERMİYANOĞLU SOKAK","GÖKAY SOKAK","GÜNYÜZÜ SOKAK","GÜR SOKAK","HALİL RIFAT PAŞA SOKAK","KARAYAZI SOKAK","KOÇİBEY SOKAK","KÖŞK MEDRESE SOKAK","LEFKOŞE SOKAK","MEDİNE SOKAK","MUHAMMET İKBAL CADDESİ","OSMAN GAZİ SOKAK","PAZARYOLU SOKAK","PINARCIK SOKAK","PİRLER SOKAK","RÜSTEM PAŞA SOKAK","SELAHATTİN EYYÜBİ SOKAK","SELANİK SOKAK","SULTAN MURAT SOKAK","SUNGURBEY SOKAK","SİLİSTRE SOKAK","TAŞ MEDRESE SOKAK","TEBRİZ SOKAK","TRABZON SOKAK","ULUBEY SOKAK","UYVAR SOKAK","VARDAR SOKAK","YEMEN SOKAK","YEŞİLOVA","ÇALIKUŞU SOKAK","İLKADIM BULVARI","İLKE SOKAK","İSPİR SOKAK","ŞAHMERAN SOKAK","ŞEHİT MESUT BİRİNCİ CAD."],"İMAMLAR":["AHLATLI","AŞIKLAR","MANGIRLAR","İMAMLAR"],"YAYLA":["KÜRTLER","KÜÇÜKÇAYIR","MERKEZ_8","ÇUBUK"],"TUZAKLI":["KARAPINAR","MERKEZ_7","SİVASLI"],"ULUÇAYIR":["AŞAĞI_2","GÖBÜTLER","GÖBÜTLER KARŞI","KARAMAN","KELHASANLAR","KÖROĞLU","MERKEZ_11","PANCARLIK"],"ALİBEYLİ":["AŞAĞI TAŞDİBEK","KIRKAMBAR","MERKEZ","MERKEZ_18","YENİDOĞAN","YUKARI TAŞDİBEK"],"GÖLALAN":["DEĞİRMENÖNÜ","KENDİRLİK","KUBBE SIRTI","MALAZLAR","MERKEZ_15","PATRİKLİ","SARI ALAN","YOLÇATI","YUKARI_3"],"KALEBOĞAZI":["KOBUK","MERKEZ_10","SÖĞÜTLÜPINAR"],"BELEDİYE EVLERİ":["100.SOKAK","101.SOKAK","103.SOKAK","19MAYISGENÇLİK","320","386","387","840.","AHLAT SOKAK","AKÇAY SOKAK","ALAŞEHİR SOKAK","ALTAY SOKAK","ATATÜRK BULVARI","AYDIN REİS SOKAK","AŞIK DERTLİ SOKAK","AŞIK PAŞA SOKAK","AŞIKLAR SOKAK","CEM SULTAN SOKAK","CENGİZ TOPEL CADDESİ","DARENDE SOKAK","DEFNE SOKAK","DR. MUSTAFA BAŞOĞLU SOKAK","DÜDEN SOKAK","ERTUĞRUL SOKAK","FAHRETTİN ERSAN","GEDİZLİ SOKAK","GİRNE SOKAK_1","HAYRAT SOKAK","HEKİMHAN SOKAK","HİTİT SOKAK","KARGI SOKAK","KUVAYİ  MİLLİYE SOKAK","MARMARA SOKAK","MEHMET ALİ ULUSOY SOKAK","MELİKŞAH SOKAK","MÜHÜRDAR SOKAK","RESNE SOKAK","TARLA SOKAK","TERAKKİ SOKAK","ULUDAĞ SOKAK","YAZIHAN SOKAK","YÜCEL SOKAK","ÇAMLICA SOKAK","ÇİĞDEM TEPE SOKAK","ŞEHİT PİYADE ER ERDOĞAN DİNDAR","ŞEHİT UĞUR SOKAK"],"DEMİRCİ":["DEMİRCİ MERKEZ","İSTASYON"],"DÜZÖREN":["DÜZÖREN"],"ÜÇPINAR":["MERKEZ_7","YAVŞAN","ÇAMKÖY","ŞATIRLAR"],"AVLUCA":["ELMABAHÇE","KARATOKLU","MERKEZ_3"],"ÇAĞLAYAN":["DEĞİRMEN YANI","GENGEÇİT"],"TOYGAR":["MERKEZ_13"],"AMBARPINAR":["AMBARPINAR"],"GÜLTEPE":["İNCEGERİŞ"],"YENİKÖY":["KARACALAR","MERKEZ_17","MERKEZ_9","SOĞUKSU","YENİ","ÇAL"],"HACINAİPLİ":["HACINAİPLİ"],"ADATEPE":["ADATEPE","ELMABAHÇE","YILANLIDERE"],"KOZLU":["KOZLU","SÖBECE"],"YEŞİLPINAR":["YEŞİLPINAR"],"GÜRGENYATAK":["841","842","MERKEZ_18","YENİDOĞAN","YERLİCE"],"ATATÜRK":["418.","419.","420.","421.","422.-","423.","424.","425.","426.","429.","430.","439.","440.","441.","442.","443.","444.","445.","446.","447.","448.","452.","460.","461.","462.","498.","499.","501.","502.","521.","649.","810.","811.","812.","813.","814.","815","816.","835-","851","OVA","OVA_1","SEMİŞLİ"],"HİLALTEPE":["MAKMARA","SERNİÇ","ZEYVE"],"DÜZARDIÇ":["KARAKAHYALAR","MERKEZ_2","TANGALLI","YUKARI_2"],"DERELER":["810.","KARAMETDAĞ","MERKEZ_1","SEMİŞLİ"],"BAŞKONAK":["DEMİRCİSU","KARANLIKDERE","KİLİSECİK","MAKMARA","MAÇKALILAR","MECİDÜZÜ","YAYLABAŞI","YUKARI","ÇAMKÖY"],"TEKKİRAZ":["DEVEYATAĞI","KOCAALAN","MERKEZ_6"],"TEKNEPINAR":["134.SOKAK","135.","151.SOKAK","152.","326","338","407","415.","520.","550.","551.","552.","553.","554.","555.","556","557.","558.","559.","560.","561.","562.","563.","564.","565.","566.","567.","568.","569.","570.","571.","572.","573.","574.","575.","576.","577.","578.","579.","580.","581.","582.","583.","584.","585.","586.","587.","588.","589.","590.","591.","592.","593.","594.","595.","596.","597.","598.","599.","600.","601.","602.","603.","604.","605.","606.","607.","608.","609.","610.","611.","612.","613.","614.","615.","616.","617.","618.","619.","620.","621.","622.","623.","624.","625.","626.","627.","628.","629.","630.","631.","632.","633.","634.","635.","636.","637.","639.","640.","641.","642.","643.","644.","645.","646.","647.","648.","861","ALTINTEPE SOKAK","AVŞAR SOKAK","DEDE EFENDİ SOKAK","KARŞI","ORTA","TIBBİYE SOKAK","YENİ SAMSUN","YENİ_1","ŞEHİT MESUT BİRİNCİ CAD."]}